Workbook

Sheet Read me
A1: Literature map: urban, digital and urban–digital research
A2: Stage 2 build, 2026-10-08. 7666 deduplicated records, of which 388 come only from the supplementary query set and 919 are repository-only. Records per primary theme: A1: 170, A2: 243, A3: 170, A4: 158, A5: 166, A6: 205, A7: 185, A8: 274, A9: 211, A10: 163, A11: 165, A12: 164, A13: 182, A14: 189, A15: 155, A16: 211, B1: 167, B2: 158, B3: 147, B4: 184, B5: 199, B6: 187, B7: 177, B8: 217, B9: 179, B10: 173, B11: 196, B12: 146, B13: 151, B14: 153, C1: 194, C2: 181, C3: 88, C4: 123, C5: 115, C6: 112, C7: 120, C8: 121, C9: 186, C10: 144, C11: 100, C12: 92, C13: 153, C14: 103, C15: 85, C16: 126, C17: 118, C18: 60.
A3: What this is
A4: A representative, reproducible map — not a census — of three domains (A urban, B digital society, C urban × digital), 48 themes. Every record comes from an OpenAlex API response; raw responses are cached in data/raw/ of the repository. See BRIEF.md, queries.yaml, PROGRESS.md and scripts/.
A5: Tabs
A6: Records — one row per work (schema below). Gap matrix — live COUNTIFS of theme × region, theme × method, theme × period (supplementary-only records excluded). Growth — OpenAlex-wide counts per theme, precision-adjusted and normalised (Stage 3 input). Emerging terms — Stage 3. Landmarks by theme — records from the 'landmarks' slice, repository-only records excluded. India subset — India-flagged records. Shortlist — records touching current leads.
A7: How records were found
A8: For each theme, 2–6 queries (queries.yaml) run against the OpenAlex API in exact-phrase mode over title and abstract (Stage 1 pilot slices: title, abstract and keywords), in three slices: landmarks (the theme's queries OR-ed, top 100 by citations; page 2 where fewer than 25 survived), recent (2022–2026, one search per query string, top 15–25 by relevance), India/South Asia (each query AND South Asian place names, top 15–25 by relevance). A supplementary query set (S1–S7: railway stations, waiting, night-time transit, fare integration/NCMC, rail-led urbanism, elevated rail, Haryana secondary cities) was searched separately; records found only there are tagged Supplementary = Y and given the query's home theme.
A9: Screening
A10: Rule-based on title + abstract (rules v3, queries.yaml header): the theme's core concept in the title or twice in the abstract, plus its context terms (for C themes the urban context, or a named city, is required). Borderline cases (single mention named by a keyword tag, flagged technical/biomedical terms with the core in the title, stub abstracts) were decided by hand (data/screening/manual_review.csv). Records whose OpenAlex primary-topic field is biomedical or natural-science are excluded unless kept by hand. Book reviews, errata, paratext, editorials, datasets and retracted works are excluded. A work is assigned the primary theme with the strongest match among the themes whose searches found it. Deduplicated by DOI, then by normalised title.
A11: Columns that are inferred automatically (check before citing)
A12: Places studied / Region: place names matched in title + abstract (not author affiliations). Region buckets: Global North (Europe, North America, Australia, NZ, Russia), China & East Asia, South Asia, Southeast Asia (incl. Pacific islands), Africa (incl. North Africa), Latin America (incl. Caribbean), Middle East (incl. Central Asia and Caucasus); two or more buckets = Multi-region; none = Not place-specific. India / Delhi-NCR / Haryana flags: same matching. Method: keyword cues in the abstract; 'unclear' when there is no abstract or no cue. Landmark flag: found in a landmarks slice and not repository-only. Repository-only: every merged version sits only in a repository or preprint server (Zenodo, SSRN, arXiv, institutional repositories). C4 orientation: critical vs technical (keyword cues). Emerging flag (provisional): published 2022+ with FWCI ≥ 1.5. One-line summary and Stated gaps: sentences copied from the abstract, marked 'auto:'. Screening confidence: high = rule-included with the core concept and context; medium = rule-included via other routes or kept by hand; low = no abstract.
... A16: Supplementary / Supplementary query = found only by / also by the supplementary query set; Found in = theme:slice combinations that returned the work ('<-X' marks a work moved by hand from theme X); Duplicates merged = other OpenAlex IDs folded into this record; FWCI = OpenAlex field-weighted citation impact.

Sheet Records
A1: ID | B1: Title | C1: Year | D1: Authors | E1: Venue | F1: Document type | G1: DOI | H1: OpenAlex ID | I1: Link | J1: Open-access link | K1: Cited-by count | L1: Domain | M1: Primary theme | N1: Secondary theme | O1: Places studied | P1: Region | Q1: India flag | R1: Delhi/NCR flag | S1: Haryana flag | T1: Method | U1: Landmark flag | V1: Emerging flag | W1: One-line summary | X1: Stated gaps | Y1: Shortlist tag | Z1: Screening confidence | AA1: Repository-only | AB1: Supplementary | AC1: Supplementary query | AD1: C4 orientation | AE1: Found in | AF1: Duplicates merged | AG1: FWCI
A2: LM00001 | B2: From Managerialism to Entrepreneurialism: The Transformation in Urban Governance in Late Capitalism | C2: 1989 | D2: David Harvey | E2: Geografiska Annaler Series B Human Geography | F2: article | G2: 10.1080/04353684.1989.11879583 | H2: W2069072514 | I2: https://doi.org/10.1080/04353684.1989.11879583 | K2: 4713 | L2: A | M2: A1 | P2: Not place-specific | T2: unclear | U2: Y | W2: auto: This paper explores the context of this shift from managerialism to entrepreneurialism in urban governance and seeks to show how mechanisms of inter-urban competition shape outcomes and generate macroeconomic consequences. | Z2: high | AE2: A1:landmarks | AF2: W4244456534 | AG2: 65.4685
A3: LM00002 | B3: New State Spaces | C3: 2004 | D3: Neil Brenner | E3: Oxford University Press eBooks | F3: book | G3: 10.1093/acprof:oso/9780199270057.001.0001 | H3: W2477465903 | I3: https://doi.org/10.1093/acprof:oso/9780199270057.001.0001 | K3: 2295 | L3: A | M3: A1 | O3: Europe | P3: Global North | T3: qualitative | U3: Y | W3: auto: This book develops a new interpretation of the transformation of statehood under contemporary globalizing capitalism. | Z3: medium | AE3: A1:landmarks | AG3: 64.4303
A4: LM00003 | B4: THE DANGERS OF DECENTRALIZATION | C4: 1995 | D4: Rémy Prud’homme | E4: The World Bank Research Observer | F4: article | G4: 10.1093/wbro/10.2.201 | H4: W2124222250 | I4: https://doi.org/10.1093/wbro/10.2.201 | K4: 1897 | L4: A | M4: A1 | P4: Not place-specific | T4: conceptual | U4: Y | W4: auto: This article looks at some of the negative effects of decentralization in the hope that a better understanding of its dangers will contribute to a wiser application of potentially desirable decentralization programs. | Z4: medium | AE4: A1:landmarks | AG4: 112.1795
A5: LM00004 | B5: New State Spaces: Urban Governance and the Rescaling of Statehood | C5: 2004 | D5: Neil Brenner | E5: OUP Catalogue | F5: article | H5: W1513313904 | I5: https://ideas.repec.org/b/oxp/obooks/9780199270064.html | K5: 1885 | L5: A | M5: A1 | P5: Not place-specific | T5: conceptual | U5: Y | W5: auto: Introduction: Cities, States, and the 'Explosion of Spaces' 2. | Z5: high | AE5: A1:landmarks | AG5: 219.8337
A6: LM00005 | B6: Liberalism, Neoliberalism, and Urban Governance: A State–Theoretical Perspective | C6: 2002 | D6: Bob Jessop | E6: Antipode | F6: article | G6: 10.1111/1467-8330.00250 | H6: W2095842624 | I6: https://doi.org/10.1111/1467-8330.00250 | K6: 1460 | L6: A | M6: A1 | P6: Not place-specific | T6: conceptual | U6: Y | W6: auto: This paper discusses the recurrence and the recurrent limitations of liberalism as a general discourse, strategy, and regime. | X6: auto: This paper discusses the recurrence and the recurrent limitations of liberalism as a general discourse, strategy, and regime. | Z6: high | AE6: A1:landmarks | AG6: 100.4158
A7: LM00006 | B7: Globalisation as Reterritorialisation: The Re-scaling of Urban Governance in the European Union | C7: 1999 | D7: Neil Brenner | E7: Urban Studies | F7: article | G7: 10.1080/0042098993466 | H7: W2128580910 | I7: https://doi.org/10.1080/0042098993466 | K7: 1134 | L7: A | M7: A1 | O7: Europe; European | P7: Global North | T7: conceptual | U7: Y | W7: auto: This article argues that processes of reterritorialisation—the reconfiguration and re-scaling of forms of territorial organisation such as cities and states—constitute an intrinsic moment of the current round of globalisation. | Z7: high | AE7: A1:landmarks | AG7: 133.6439
A8: LM00007 | B8: Spaces of Neoliberalism | C8: 2002 | D8: Neil 1969- Brenner; Nik Theodore | E8: Wiley eBooks | F8: book | G8: 10.1002/9781444397499 | H8: W245352281 | I8: https://doi.org/10.1002/9781444397499 | K8: 1059 | L8: A | M8: A1 | O8: Canada; Chicago; Europe; Manchester; New York; Toronto; United Kingdom | P8: Global North | T8: conceptual | U8: Y | W8: auto: From the 'New Localisma to the Spaces of Neoliberalism: Neil Brenner (New York University) & Nik Theodore (University of Illinois at Chicago). | Z8: medium | AE8: A1:landmarks | AG8: 19.2653
A9: LM00008 | B9: The Political Economy of Democratic Decentralization | C9: 1999 | D9: James Manor | E9: World Bank, Washington, DC eBooks | F9: book | G9: 10.1596/0-8213-4470-6 | H9: W1494416504 | I9: https://doi.org/10.1596/0-8213-4470-6 | K9: 967 | L9: A | M9: A1 | N9: A7 | O9: Africa; African; Bangladesh; Brazil; Central AsiaJournal; China; Ethiopia; Ghana; India; Indonesia; Italy; Lagos; Malawi; Nigeria; Norway; Pakistan; Sierra Leone; South Africa; South AsiaInternational; South Asian; South Korea; Southeast AsiaEnvironment; Thailand; United Kingdom; United States; Uruguay; West Bengal; Zambia | P9: Multi-region | Q9: Y | T9: review | U9: Y | W9: auto: No AccessDirections in Development - General1 Feb 2013The Political Economy of Democratic DecentralizationAuthors/Editors: James ManorJames Manorhttps://doi.org/10.1596/0-8213-4470-6SectionsAboutPDF (0.4 MB) ToolsAdd to favoritesDownload CitationsTrack Citations ShareFacebookTwitterLinked In Abst… | X9: auto: This report examines the origins and implications decentralization from a political economy perspective, with a focus on its promise and limitations. | The experience of commune councils in CambodiaAsia Pacific Journal of Public Administration, Vol.40, No.227 June 2018The Trap of Neo-patrimonialism: Social Accountability and Good Governance in CambodiaAsian Studies Review, Vol.42, No.117 January 2018The impact of central-local inter-governmental relations on cultural democracy's developmentAs… | Z9: high | AE9: A1:landmarks; A7:landmarks | AG9: 27.3527
A10: LM00009 | B10: Decentralized Authoritarianism in China | C10: 2008 | D10: Pierre F. Landry | E10: Cambridge University Press eBooks | F10: book | G10: 10.1017/cbo9780511510243 | H10: W1591209570 | I10: https://doi.org/10.1017/cbo9780511510243 | K10: 847 | L10: A | M10: A1 | O10: China | P10: China & East Asia | T10: conceptual | U10: Y | W10: auto: China, like many authoritarian regimes, struggles with the tension between the need to foster economic development by empowering local officials and the regime's imperative to control them politically. | Z10: high | AE10: A1:landmarks | AG10: 29.1742
A11: LM00010 | B11: An inconvenient cost: The effects of climate change on municipal bonds | C11: 2019 | D11: Marcus Painter | E11: Journal of Financial Economics | F11: article | G11: 10.1016/j.jfineco.2019.06.006 | H11: W2952070778 | I11: https://doi.org/10.1016/j.jfineco.2019.06.006 | K11: 823 | L11: A | M11: A1 | P11: Not place-specific | T11: unclear | U11: Y | Z11: low | AE11: A1:landmarks | AG11: 58.2588
A12: LM00011 | B12: Urban Economics and Real Estate Markets | C12: 1995 | D12: Denise DiPasquale; William C. Wheaton | F12: article | H12: W1508404391 | I12: https://bvbr.bib-bvb.de:443/F?func=service&doc_library=BVB01&local_base=BVB01&doc_number=007702443&sequence=000001&line_number=0001&func_code=DB_RECORDS&service_type=MEDIA | K12: 785 | L12: A | M12: A1 | P12: Not place-specific | T12: quantitative | U12: Y | W12: auto: INTRODUCTION TO REAL ESTATE MARKETS. 1. | Z12: high | AE12: A1:landmarks | AG12: 29.0192
A13: LM00012 | B13: Roads, Railroads, and Decentralization of Chinese Cities | C13: 2017 | D13: Nathaniel Brandt Baum-Snow; Loren Brandt; J. Vernon Henderson; Matthew A. Turner; Qinghua Zhang | E13: The Review of Economics and Statistics | F13: article | G13: 10.1162/rest_a_00660 | H13: W2168707163 | I13: https://doi.org/10.1162/rest_a_00660 | J13: https://direct.mit.edu/rest/article-pdf/99/3/435/1918446/rest_a_00660.pdf | K13: 761 | L13: A | M13: A1 | O13: China | P13: China & East Asia | T13: unclear | U13: Y | W13: auto: We investigate how urban railroad and highway configurations have influenced urban form in Chinese cities since 1990. | Z13: medium | AE13: A1:landmarks | AG13: 82.4858
A14: LM00013 | B14: Building Institutional Capacity through Collaborative Approaches to Urban Planning | C14: 1998 | D14: Patsy Healey | E14: Environment and Planning A Economy and Space | F14: article | G14: 10.1068/a301531 | H14: W1983137693 | I14: https://doi.org/10.1068/a301531 | K14: 704 | L14: A | M14: A1 | O14: Europe; United Kingdom | P14: Global North | T14: conceptual | U14: Y | W14: auto: I argue that a key element of such capacity lies in the quality of local policy cultures. | X14: auto: Others are fragmented, lack the connections to sources of power and knowledge, and the mobilisation capacity, to organise to make a difference. | Z14: medium | AE14: A1:landmarks | AG14: 63.5545
A15: LM00014 | B15: Rethinking Decentralization in Developing Countries | C15: 1998 | D15: Jennie I. Litvack; Junaid Aḥmad; Richard Miller Bird | E15: World Bank, Washington, DC eBooks | F15: book | G15: 10.1596/0-8213-4350-5 | H15: W1230600452 | I15: https://doi.org/10.1596/0-8213-4350-5 | K15: 634 | L15: A | M15: A1 | N15: A7 | O15: Africa; African; Australia; Benin; Bolivia; Brazil; Burkina Faso; Chile; China; Europe; European; Ghana; Hungary; India; Indonesia; Kampala; Karnataka; Kolkata; Madhya Pradesh; Mali; Mexico; Odisha; Pakistan; Peru; Philippines; Senegal; Seoul; Southeast Asian; Tanzania; Timor-Leste; Uganda; Ukraine; United States; West Bengal | P15: Multi-region | Q15: Y | T15: review | U15: Y | W15: auto: No AccessStand Alone Books1 Feb 2013Rethinking Decentralization in Developing CountriesAuthors/Editors: Jennie Litvack, Junaid Ahmad, Richard BirdJennie Litvack, Junaid Ahmad, Richard Birdhttps://doi.org/10.1596/0-8213-4350-5SectionsAboutPDF (0.2 MB) ToolsAdd to favoritesDownload CitationsTrack C… | X15: auto: Institutions, interests, ideas and networks in three cases of policy reformHealth Policy and Planning, Vol.31, No.927 May 2016Decentralization of Health and Education in Developing Countries: A Quality-Adjusted Review of the Empirical LiteratureWorld Bank Research Observer, Vol.31, No.220 March 2017Healthcare under the Panchayati Raj Institutions (PRIs) in a decentralised health systemLeadership in Health Services, Vol.29, No.2The path dependence of district manager decision-space in GhanaHea… | Z15: high | AE15: A14:landmarks; A1:landmarks; A7:landmarks | AG15: 12.1991
A16: LM00015 | B16: Does decentralization increase government responsiveness to local needs? | C16: 2003 | D16: Jean-Paul Faguet | E16: Journal of Public Economics | F16: article | G16: 10.1016/s0047-2727(02)00185-8 | H16: W1995980461 | I16: https://doi.org/10.1016/s0047-2727(02)00185-8 | J16: https://www.sciencedirect.com/science/article/pii/S0047272702001858 | K16: 566 | L16: A | M16: A1 | P16: Not place-specific | T16: unclear | U16: Y | Z16: low | AE16: A1:landmarks | AG16: 78.2836
A17: LM00016 | B17: The environment and the entrepreneurial city: searching for the urban ‘sustainability fix’ in Manchester and Leeds | C17: 2004 | D17: Aidan H. While; Andrew E. G. Jonas; David C. Gibbs | E17: International Journal of Urban and Regional Research | F17: article | G17: 10.1111/j.0309-1317.2004.00535.x | H17: W2032751183 | I17: https://doi.org/10.1111/j.0309-1317.2004.00535.x | K17: 562 | L17: A | M17: A1 | O17: Manchester; United Kingdom | P17: Global North | T17: conceptual | U17: Y | W17: auto: In this article we explore how different demands on and for urban environmental policy have played out vis‐à‐vis changing modes and practices of governance in two English post‐industrial cities. | Z17: high | AE17: A1:landmarks | AG17: 29.5553
A18: LM00017 | B18: Du gouvernement des villes à la gouvernance urbaine | C18: 1995 | D18: Patrick Le Galès | E18: Revue française de science politique | F18: article | G18: 10.3406/rfsp.1995.403502 | H18: W2059028256 | I18: https://doi.org/10.3406/rfsp.1995.403502 | K18: 556 | L18: A | M18: A1 | O18: France; United Kingdom; United States | P18: Global North | T18: conceptual | U18: Y | W18: auto: From the governing of cities to urban governance. | Z18: high | AE18: A1:landmarks | AG18: 49.2554
A19: LM00018 | B19: Models of Urban Governance | C19: 1999 | D19: Jon Pierre | E19: Urban Affairs Review | F19: article | G19: 10.1177/10780879922183988 | H19: W2095162523 | I19: https://doi.org/10.1177/10780879922183988 | K19: 515 | L19: A | M19: A1 | O19: Europe | P19: Global North | T19: unclear | U19: Y | W19: auto: Local governments in Western Europe have become increasingly involved in network building with the local business community. | Z19: high | AE19: A1:landmarks | AG19: 33.4298
A20: LM00019 | B20: Inventing Local Democracy | C20: 2000 | D20: Rebecca Neaera Abers | E20: Lynne Rienner Publishers eBooks | F20: book | G20: 10.1515/9781626371378 | H20: W4300242732 | I20: https://doi.org/10.1515/9781626371378 | K20: 513 | L20: A | M20: A1 | O20: Brazil | P20: Latin America | T20: conceptual | U20: Y | W20: auto: Countless studies of citizen participation in public decisionmaking point out the limitations of direct democracy when it is transported from the realm of political theory into the "real world." In contrast, this book examines a case where an innovative city government gave major decisionmaking p… | X20: auto: Countless studies of citizen participation in public decisionmaking point out the limitations of direct democracy when it is transported from the realm of political theory into the "real world." In contrast, this book examines a case where an innovative city government gave major decisionmaking power to ordinary citizens on a large scale—and managed to survive and prosper. | Z20: high | AE20: A1:landmarks | AG20: 11.8416
A21: LM00020 | B21: European Cities | C21: 2002 | D21: Patrick Le Galès | E21: Oxford University Press eBooks | F21: book | G21: 10.1093/acprof:oso/9780199243570.001.0001 | H21: W4254087421 | I21: https://doi.org/10.1093/acprof:oso/9780199243570.001.0001 | K21: 512 | L21: A | M21: A1 | O21: European | P21: Global North | T21: unclear | U21: Y | W21: auto: Taking examples through the European Union, this book explores the impact of the transformation of the nation states on cities and the change of local societies and local governments. | Z21: high | AE21: A1:landmarks | AG21: 18.577
A22: LM00021 | B22: Social Cohesion and Multilevel Urban Governance | C22: 2000 | D22: Ade Kearns; Ray Forrest | E22: Urban Studies | F22: article | G22: 10.1080/00420980050011208 | H22: W2034882398 | I22: https://doi.org/10.1080/00420980050011208 | K22: 499 | L22: A | M22: A1 | P22: Not place-specific | T22: unclear | U22: Y | Z22: low | AE22: A1:landmarks | AG22: 16.5289
A23: LM00022 | B23: Urban governance and the production of new state spaces in western Europe, 1960–2000 | C23: 2004 | D23: Neil Brenner | E23: Review of International Political Economy | F23: article | G23: 10.1080/0969229042000282864 | H23: W4245283280 | I23: https://doi.org/10.1080/0969229042000282864 | K23: 491 | L23: A | M23: A1 | O23: Europe; European | P23: Global North | T23: conceptual | U23: Y | W23: auto: Against the background of contemporary debates on globalization and the crystallization of a post-Westphalian world order, this article develops an interpretation of state spatial restructuring in post-1970s western Europe While many analyses of globalization and the changing state have focused o… | Z23: high | AE23: A1:landmarks | AG23: 41.049
A24: LM00023 | B24: Selling City Futures: The Financialization of Urban Redevelopment Policy | C24: 2010 | D24: Rachel N. Weber | E24: Economic Geography | F24: article | G24: 10.1111/j.1944-8287.2010.01077.x | H24: W1779394378 | I24: https://doi.org/10.1111/j.1944-8287.2010.01077.x | K24: 473 | L24: A | M24: A1 | O24: Chicago; United States | P24: Global North | T24: qualitative | U24: Y | W24: auto: abstract This article examines the specific mechanisms that have allowed global financial markets to penetrate deeply into the activities of U.S. cities. | Z24: high | AE24: A1:landmarks | AG24: 15.2392
A25: LM00024 | B25: Decentralization, Local Government, and the Welfare State | C25: 2007 | D25: Jefferey M. Sellers; Anders Lidström | E25: Governance | F25: article | G25: 10.1111/j.1468-0491.2007.00374.x | H25: W1501190759 | I25: https://doi.org/10.1111/j.1468-0491.2007.00374.x | K25: 463 | L25: A | M25: A1 | P25: Not place-specific | T25: unclear | U25: Y | W25: auto: This article, drawing on the first systematic index of decentralization to local government in 21 countries, demonstrates a close relation between Social Democratic welfare states and an intergovernmental infrastructure that in important respects ranks as the most decentralized among advanced ind… | Z25: medium | AE25: A1:landmarks | AG25: 43.728
A26: LM00025 | B26: Do Political Parties Matter? Evidence from U.S. Cities* | C26: 2009 | D26: Fernando V. Ferreira; Joseph Gyourko | E26: The Quarterly Journal of Economics | F26: article | G26: 10.1162/qjec.2009.124.1.399 | H26: W2135146089 | I26: https://doi.org/10.1162/qjec.2009.124.1.399 | K26: 439 | L26: A | M26: A1 | O26: United States | P26: Global North | T26: quantitative | U26: Y | W26: auto: We investigate three mechanisms that could account for the striking lack of partisan impact at the local level, and find the most support for Tiebout competition among localities within metropolitan areas. | X26: auto: We investigate three mechanisms that could account for the striking lack of partisan impact at the local level, and find the most support for Tiebout competition among localities within metropolitan areas. | Z26: medium | AE26: A1:landmarks | AG26: 141.7297
A27: LM00026 | B27: Source Separation and Decentralization for Wastewater Management | C27: 2013 | D27: Tove A. Larsen; Kai M. Udert; Judit Lienert | E27: IWA Publishing eBooks | F27: book | G27: 10.2166/9781780401072 | H27: W161525005 | I27: https://doi.org/10.2166/9781780401072 | J27: https://doi.org/10.2166/9781780401072 | K27: 433 | L27: A | M27: A1 | P27: Not place-specific | T27: conceptual | U27: Y | W27: auto: The area is in rapid development, but many of the fundamental insights presented in this book will stay valid. | Z27: high | AE27: A1:landmarks | AG27: 36.4917
A28: LM00027 | B28: China's Changing Urban Governance in the Transition Towards a More Market-oriented Economy | C28: 2002 | D28: Fulong Wu | E28: Urban Studies | F28: article | G28: 10.1080/00420980220135491 | H28: W2049842115 | I28: https://doi.org/10.1080/00420980220135491 | K28: 431 | L28: A | M28: A1 | O28: China | P28: China & East Asia | T28: unclear | U28: Y | W28: auto: This article aims to analyse the forces released both inside and outside the formal socialist state system and the impacts on phenomenal restructuring of urban governance, especially at local levels. | X28: auto: Relatively, the governing of Chinese cities is still underresearched. | Z28: high | AE28: A1:landmarks | AG28: 30.1101
A29: LM00028 | B29: China's Local Political Budget Cycles | C29: 2009 | D29: Gang Guo | E29: American Journal of Political Science | F29: article | G29: 10.1111/j.1540-5907.2009.00390.x | H29: W2128534216 | I29: https://doi.org/10.1111/j.1540-5907.2009.00390.x | K29: 429 | L29: A | M29: A1 | O29: China | P29: China & East Asia | T29: quantitative | U29: Y | W29: auto: This article examines the political budget cycles in Chinese counties. | Z29: high | AE29: A1:landmarks | AG29: 25.3844
A30: LM00029 | B30: Decentralisation, participation and accountability in Sahelian forestry: legal instruments of political-administrative control | C30: 1999 | D30: Jesse Ribot | E30: Africa | F30: article | G30: 10.2307/1161076 | H30: W2070217518 | I30: https://doi.org/10.2307/1161076 | K30: 423 | L30: A | M30: A1 | O30: Burkina Faso; Mali | P30: Africa | T30: conceptual | U30: Y | W30: auto: Rather than pitting the state against society by depicting the state as a negative force and society and non-state institutions as positive—as is done in many decentralisation and participatory efforts—this article suggests that representation through local government can be the basis of general … | Z30: high | AE30: A1:landmarks | AG30: 20.1903
A31: LM00030 | B31: Community Development: Creating community alternatives - vision, analysis and practice | C31: 1995 | D31: Jim Ife | E31: UWA Profiles and Research Repository (University of Western Australia) | F31: book | H31: W1525923982 | I31: https://admin.research-repository.uwa.edu.au/en/publications/568f8586-e780-4cca-aef0-c74526cd5e0f | K31: 420 | L31: A | M31: A1 | P31: Not place-specific | T31: conceptual | W31: auto: *The Crisis in Human Services and the Need for Community The crisis in the welfare state Community-based services as an alternative The missing ingredient: community development The next steps *Foundations of Community Work: An Ecological Perspective Environmental crisis Environmental responses a… | Z31: high | AA31: Y | AE31: A1:landmarks | AG31: 5.0739
A32: LM00031 | B32: Resilience, ecology and adaptation in the experimental city | C32: 2011 | D32: James Evans | E32: Transactions of the Institute of British Geographers | F32: article | G32: 10.1111/j.1475-5661.2010.00420.x | H32: W1503263161 | I32: https://doi.org/10.1111/j.1475-5661.2010.00420.x | J32: https://onlinelibrary.wiley.com/doi/pdfdirect/10.1111/j.1475-5661.2010.00420.x | K32: 410 | L32: A | M32: A1 | N32: A7 | O32: United States | P32: Global North | T32: conceptual | U32: Y | W32: auto: This paper traces one particular lineage of experimentation to resilience ecology, which rejects the possibility of external control over a system, casting planning and administrative functions, and even scientists themselves, as part of a Social‐Ecological System. | Z32: high | AE32: A1:landmarks; A7:landmarks | AG32: 18.2627
A33: LM00032 | B33: Financial Intermediation and the Costs of Trading in an Opaque Market | C33: 2006 | D33: Richard C. Green; Burton Hollifield; Norman Schürhoff | E33: Review of Financial Studies | F33: article | G33: 10.1093/rfs/hhl012 | H33: W3022314381 | I33: https://doi.org/10.1093/rfs/hhl012 | K33: 408 | L33: A | M33: A1 | P33: Not place-specific | T33: quantitative | U33: Y | W33: auto: We analyze a database of trades between broker-dealers and customers in municipal bonds. | Z33: high | AE33: A1:landmarks | AG33: 21.3327
A34: LM00033 | B34: Decentralization of health systems in Ghana, Zambia, Uganda and the Philippines: a comparative analysis of decision space | C34: 2002 | D34: Thomas John Bossert | E34: Health Policy and Planning | F34: article | G34: 10.1093/heapol/17.1.14 | H34: W1983617101 | I34: https://doi.org/10.1093/heapol/17.1.14 | J34: https://academic.oup.com/heapol/article-pdf/17/1/14/9806466/170014.pdf | K34: 406 | L34: A | M34: A1 | O34: Ghana; Philippines; Uganda; Zambia | P34: Multi-region | T34: conceptual | U34: Y | W34: auto: This study reviews the experience of decentralization in four developing countries: Ghana, Uganda, Zambia and the Philippines. | X34: auto: The authors suggest that this is a major area for future research. | Z34: medium | AE34: A1:landmarks | AG34: 11.0655
A35: LM00034 | B35: Urban Governance and the Politics of Climate change | C35: 2017 | D35: Vanesa Castán Broto | E35: World Development | F35: article | G35: 10.1016/j.worlddev.2016.12.031 | H35: W2587562756 | I35: https://doi.org/10.1016/j.worlddev.2016.12.031 | J35: https://discovery.ucl.ac.uk/1532905/2/Castan_Broto_Manuscript.pdf | K35: 404 | L35: A | M35: A1 | P35: Not place-specific | T35: unclear | U35: Y | Z35: low | AE35: A1:landmarks | AG35: 25.5082
A36: LM00035 | B36: Telecommunications and Organizational Decentralization | C36: 1975 | D36: Jack M. Nilles | E36: IRE Transactions on Communications Systems | F36: article | G36: 10.1109/tcom.1975.1092687 | H36: W2063371681 | I36: https://doi.org/10.1109/tcom.1975.1092687 | K36: 400 | L36: A | M36: A1 | P36: Not place-specific | T36: conceptual | U36: Y | W36: auto: In recent years, several phenomena have caused significant pressures on the traditional, centralized urban structure. | Z36: high | AE36: A1:landmarks | AG36: 0
A37: LM00036 | B37: Social Innovation and Civil Society in Urban Governance: Strategies for an Inclusive City | C37: 2005 | D37: Julia Gerometta; Hartmut Häußermann; Giulia Longo | E37: Urban Studies | F37: article | G37: 10.1080/00420980500279851 | H37: W2116855395 | I37: https://doi.org/10.1080/00420980500279851 | K37: 398 | L37: A | M37: A1 | P37: Not place-specific | T37: unclear | U37: Y | W37: auto: This article seeks to explore the role of civil society in new urban governance arrangements that will hopefully contribute to counter the trends towards social exclusion. | Z37: high | AE37: A1:landmarks | AG37: 20.6616
A38: LM00037 | B38: Adaptive urban governance: new challenges for the second generation of urban adaptation strategies to climate change | C38: 2010 | D38: Joern Birkmann; Matthias Garschagen; Frauke Kraas; Nguyen Quang | E38: Sustainability Science | F38: article | G38: 10.1007/s11625-010-0111-3 | H38: W1996012883 | I38: https://doi.org/10.1007/s11625-010-0111-3 | K38: 396 | L38: A | M38: A1 | P38: Not place-specific | T38: unclear | U38: Y | Z38: low | AE38: A1:landmarks | AG38: 13.9246
A39: LM00038 | B39: The reform of intergovernmental fiscal relations in developing and emerging market economies | C39: 1994 | D39: Anwar Ali Shah | E39: World Bank, Washington, DC eBooks | F39: book | G39: 10.1596/0-8213-2836-0 | H39: W1526821310 | I39: https://doi.org/10.1596/0-8213-2836-0 | K39: 389 | L39: A | M39: A1 | O39: Africa; Argentina; Benin; Bolivia; Brazil; China; European; Indonesia; Ireland; Latin AmericaLatin; Latin AmericaSSRN; Latin American; Mali; Mexico; Pakistan; Philippines; Poland; South Korea; Switzerland; Vietnam | P39: Multi-region | T39: review | U39: Y | W39: auto: No AccessStand Alone Books1 Feb 2013The reform of intergovernmental fiscal relations in developing and emerging market economiesAuthors/Editors: Anwar ShahAnwar Shahhttps://doi.org/10.1596/0-8213-2836-0SectionsAboutPDF (0.6 MB) ToolsAdd to favoritesDownload CitationsTrack Citations ShareFacebookT… | X39: auto: Comparative PerspectivePublic Administration Review, Vol.69Fiscal Decentralization, Chinese Style: Good for Health Outcomes?World Development, Vol.37, No.12Assigning State Taxes in a Federal Country: The Case of AustraliaSSRN Electronic JournalResource Windfalls, Fiscal Effort and Public Spending: Evidence from Brazilian MunicipalitiesSSRN Electronic JournalFiscal Federalism in the European Union: How Far Are We?Citizen-centred Local Governance: Strategies to combat democratic deficitsDevelop… | Z39: high | AE39: A1:landmarks | AG39: 17.1557
A40: LM00039 | B40: Decentralisation in Africa: goals, dimensions, myths and challenges | C40: 2003 | D40: Paul Smoke | E40: Public Administration and Development | F40: article | G40: 10.1002/pad.255 | H40: W1974289285 | I40: https://doi.org/10.1002/pad.255 | K40: 384 | L40: A | M40: A1 | O40: Africa | P40: Africa | T40: unclear | U40: Y | W40: auto: Drawing selectively on the large academic and practitioner literature on decentralisation and the articles in this volume, this article briefly outlines a number of typical prominent goals of decentralisation. | Z40: medium | AE40: A1:landmarks | AG40: 56.535
A41: LM00040 | B41: Transforming governance: Challenges of institutional adaptation and a new politics of space1 | C41: 2006 | D41: Patsy Healey | E41: European Planning Studies | F41: article | G41: 10.1080/09654310500420792 | H41: W2059072403 | I41: https://doi.org/10.1080/09654310500420792 | K41: 379 | L41: A | M41: A1 | O41: Europe | P41: Global North | T41: conceptual | U41: Y | W41: auto: In the context of the widespread recognition of significant changes in urban and regional governance in Europe, this paper explores the ways of understanding the dynamics of these changes and comments on the implications for recent themes in contemporary debates about urban governance—the extent … | Z41: high | AE41: A1:landmarks | AG41: 87.1603
A42: LM00041 | B42: Remote Sensing and GIS Techniques for Evaluation of Groundwater Quality in Municipal Corporation of Hyderabad (Zone-V), India | C42: 2007 | D42: S.S. Asadi; Padmaja Vuppala; M. Anji Reddy | E42: International Journal of Environmental Research and Public Health | F42: article | G42: 10.3390/ijerph2007010008 | H42: W2107658191 | I42: https://doi.org/10.3390/ijerph2007010008 | J42: https://www.mdpi.com/1660-4601/4/1/45/pdf?version=1403129951 | K42: 251 | L42: A | M42: A1 | O42: Hyderabad; India | P42: South Asia | Q42: Y | T42: computational | W42: auto: Groundwater quality in Hyderabad has special significance and needs great attention of all concerned since it is the major alternate source of domestic, industrial and drinking water supply. | Z42: high | AE42: A1:india | AG42: 3.5811
A43: LM00042 | B43: Urban governance in India | C43: 2017 | D43: Isher Judge Ahluwalia | E43: Journal of Urban Affairs | F43: article | G43: 10.1080/07352166.2016.1271614 | H43: W2620068598 | I43: https://doi.org/10.1080/07352166.2016.1271614 | J43: https://www.tandfonline.com/doi/pdf/10.1080/07352166.2016.1271614?needAccess=true&role=button | K43: 137 | L43: A | M43: A1 | O43: India | P43: South Asia | Q43: Y | T43: conceptual | W43: auto: This article examines the institutional features and devolution mechanisms of the federal framework within which cities have to deliver better quality of life for their residents and generate an investment climate that is capable of sustaining the rapid growth. | X43: auto: It argues that though planned urbanization is needed for the industry and services sectors and also for rural rejuvenation, the lack of empowerment of cities is constraining their ability to translate the urban development agenda into action. | Z43: high | AE43: A1:india; A1:india<-A7 | AG43: 64.2821
A44: LM00043 | B44: Arsenic in groundwater of the Kolkata Municipal Corporation (KMC), India: Critical review and modes of mitigation | C44: 2017 | D44: Dipankar Chakraborti; Bhaskar Das; Mohammad Mahmudur Rahman‬; Bishwajit Nayak; Arup Pal; Mrinal Kumar Sengupta; Sad Ahamed; Md. Amir Hossain; Uttam Kumar Chowdhury; Bhajan Kumar Biswas et al. | E44: Chemosphere | F44: article | G44: 10.1016/j.chemosphere.2017.04.051 | H44: W2606837565 | I44: https://doi.org/10.1016/j.chemosphere.2017.04.051 | K44: 76 | L44: A | M44: A1 | O44: India; Kolkata | P44: South Asia | Q44: Y | T44: unclear | Z44: low | AE44: A1:india | AG44: 4.0436
A45: LM00044 | B45: MUNICIPAL FINANCE SYSTEMS IN CONFLICT CITIES: CASE STUDIES ON AHMEDABAD AND SRINAGAR, INDIA | C45: 2007 | D45: Pritha Venkatachalam | F45: article | H45: W2160646180 | I45: http://r4d.dfid.gov.uk/pdf/outputs/crisisstates/wp15.2.pdf | K45: 72 | L45: A | M45: A1 | P45: Not place-specific | T45: unclear | Z45: low | AE45: A1:india | AG45: 131.1841
A46: LM00045 | B46: Implementing property tax reforms in Bangalore: an actor-network perspective | C46: 2004 | D46: Shirin Madon; Sundeep Sahay; Jyotsna Sahay | E46: Information and Organization | F46: article | G46: 10.1016/j.infoandorg.2004.07.002 | H46: W2168020096 | I46: https://doi.org/10.1016/j.infoandorg.2004.07.002 | K46: 66 | L46: A | M46: A1 | O46: Bangalore | P46: South Asia | Q46: Y | T46: unclear | Z46: low | AE46: A1:india | AG46: 10.1066
A47: LM00046 | B47: Innovating urban governance: A research agenda | C47: 2022 | D47: Pauline Mc̱Guirk; Tom Baker; Alistair Sisson; Robyn Dowling; Sophia Maalsen | E47: Progress in Human Geography | F47: article | G47: 10.1177/03091325221127298 | H47: W4297236445 | I47: https://doi.org/10.1177/03091325221127298 | K47: 61 | L47: A | M47: A1 | P47: Not place-specific | T47: conceptual | V47: Y | W47: auto: This paper suggests dialogue between urban political geography and public sector innovation literatures as a productive way forward. | Z47: high | AE47: A1:recent | AG47: 23.2682
A48: LM00047 | B48: City Profile: Dhaka, Bangladesh | C48: 2019 | D48: Shilpi Roy; Tanjil Sowgat; Jhuma Mondal | E48: Environment and Urbanization Asia | F48: article | G48: 10.1177/0975425319859126 | H48: W2969879478 | I48: https://doi.org/10.1177/0975425319859126 | K48: 47 | L48: A | M48: A1 | O48: Bangladesh; Dhaka | P48: South Asia | T48: conceptual | W48: auto: Despite numerous complex urban challenges, Dhaka, the capital of Bangladesh, is rapidly growing in terms of both population and extent. | Z48: high | AE48: A1:india | AG48: 11.847
A49: LM00048 | B49: Municipal Finance in India: An Assessment | C49: 2007 | D49: P. K. Mohanty; B. M. Misra; Rajan Goyal; P. D. Jeromi | E49: RePEc: Research Papers in Economics | F49: preprint | H49: W2118773761 | I49: http://www.esocialsciences.org/Download/repecDownload.aspx?fname=Document12912008580.8057672.pdf&fcategory=Articles&AId=1357&fref=repec | K49: 42 | L49: A | M49: A1 | O49: India | P49: South Asia | Q49: Y | T49: quantitative | W49: auto: This study, entitled â€œMunicipal Finance in India â€“ An Assessmentâ€ , undertaken for the Development Research Group (DRG), Reserve Bank of India examines the performance of Urban Local Bodies (ULBs) in India. | Z49: high | AA49: Y | AE49: A1:india
A50: LM00049 | B50: Integrated Influencing Mechanism of Potential Drivers on Seasonal Variability of LST in Kolkata Municipal Corporation, India | C50: 2022 | D50: Dipankar Bera; Nilanjana Das Chatterjee; Faisal Mumtaz; Santanu Dinda; Subrata Ghosh; Na Zhao; Sudip Bera; Aqil Tariq | E50: Land | F50: article | G50: 10.3390/land11091461 | H50: W4295067630 | I50: https://doi.org/10.3390/land11091461 | J50: https://www.mdpi.com/2073-445X/11/9/1461/pdf?version=1662370663 | K50: 30 | L50: A | M50: A1 | O50: India; Kolkata | P50: South Asia | Q50: Y | T50: quantitative | V50: Y | W50: auto: Therefore, this study was designed to examine the spatial variations and patterns of LST during the different seasons in relation to influencing factors in Kolkata Municipality Corporation (KMC), a city of India. | Z50: high | AE50: A1:india | AG50: 2.06
A51: LM00050 | B51: Reforming Urban Governance in Bangladesh | C51: 2017 | D51: Pranab Kumar Panday | E51: Springer eBooks | F51: book | G51: 10.1007/978-3-319-49598-9 | H51: W2582583590 | I51: https://doi.org/10.1007/978-3-319-49598-9 | K51: 23 | L51: A | M51: A1 | O51: Bangladesh | P51: South Asia | T51: unclear | Z51: low | AE51: A1:india | AG51: 2.919
A52: LM00051 | B52: Outsourced urban governance as a state rescaling strategy in Hyderabad, India | C52: 2018 | D52: Loraine Kennedy; Ashima Sood | E52: Cities | F52: article | G52: 10.1016/j.cities.2018.09.001 | H52: W2892268530 | I52: https://doi.org/10.1016/j.cities.2018.09.001 | J52: https://doi.org/10.1016/j.cities.2018.09.001 | K52: 22 | L52: A | M52: A1 | O52: Hyderabad; India | P52: South Asia | Q52: Y | T52: unclear | Z52: low | AE52: A1:india | AG52: 7.4562
A53: LM00052 | B53: Urban governance and electricity losses: An exploration of spatial unevenness in Karachi, Pakistan | C53: 2021 | D53: Ijlal Naqvi; Ate Poorthuis; Anirudh Govind | E53: Energy Research & Social Science | F53: article | G53: 10.1016/j.erss.2021.102166 | H53: W3178031697 | I53: https://doi.org/10.1016/j.erss.2021.102166 | J53: https://www.sciencedirect.com/science/article/pii/S2214629621002590/pdf | K53: 22 | L53: A | M53: A1 | N53: A7 | O53: Karachi; Pakistan | P53: South Asia | T53: quantitative | W53: auto: The inadequate supply of electricity in Pakistan disrupts everyday life and hampers industry and business; in this it is an emblematic indicator of the poor quality of urban governance pervasive in much of the Global South. | Z53: high | AE53: A1:india; A7:india | AG53: 10.732
A54: LM00053 | B54: Neoliberal Urban Governance | C54: 2023 | D54: Carolina Sternberg | E54: Springer eBooks | F54: book | G54: 10.1007/978-3-031-21718-0 | H54: W4318938565 | I54: https://doi.org/10.1007/978-3-031-21718-0 | K54: 20 | L54: A | M54: A1 | P54: Not place-specific | T54: unclear | V54: Y | Z54: low | AE54: A1:recent | AG54: 13.001
A55: LM00054 | B55: Decentralization, Local Government Elections and Voter Turnout in Pakistan | C55: 2008 | D55: Kamiljon T. Akramov; Sarfraz Khan Qureshi; Regina Birner; Bilal Khan; Akramov, Kamiljon T.; Qureshi, Sarfraz; Birner, Regina; Khan, Bilal Hasan | E55: AgEcon Search (University of Minnesota, USA) | F55: article | G55: 10.22004/ag.econ.42345 | H55: W1596345304 | I55: https://doi.org/10.22004/ag.econ.42345 | J55: http://ageconsearch.umn.edu/record/42345 | K55: 17 | L55: A | M55: A1 | O55: Pakistan | P55: South Asia | T55: quantitative | W55: auto: This study used survey data on the 2005 local government elections in Pakistan to analyze the impact of electoral mechanisms, the credibility of elections, and voters’ socioeconomic characteristics on voter turnout. | Z55: medium | AA55: Y | AE55: A1:india | AG55: 14.9029
A56: LM00055 | B56: Decentralization and Local Government Performance: Empirical Evidence From Ghana | C56: 2024 | D56: Asaah Sumaila Mohammed; Francis Xavier Dery Tuokuu; Alex Bokuma | E56: Journal of Asian and African Studies | F56: article | G56: 10.1177/00219096241228777 | H56: W4391841824 | I56: https://doi.org/10.1177/00219096241228777 | J56: https://journals.sagepub.com/doi/pdf/10.1177/00219096241228777?download=true | K56: 16 | L56: A | M56: A1 | O56: Ghana | P56: Africa | T56: mixed | V56: Y | W56: auto: This study presents practical and theoretical implications and identifies avenues for future research in this field. | X56: auto: This study presents practical and theoretical implications and identifies avenues for future research in this field. | Z56: high | AE56: A1:recent | AG56: 27.5506
A57: LM00056 | B57: Mumbai Human Development Report 2009 , (Municipal Corporation of Greater Mumbai), 2009 | C57: 2010 | D57: Chetan Vaidya; Satmohini Srivastva | E57: Environment and Urbanization Asia | F57: article | G57: 10.1177/097542531000100214 | H57: W1991995671 | I57: https://doi.org/10.1177/097542531000100214 | K57: 15 | L57: A | M57: A1 | O57: Mumbai | P57: South Asia | Q57: Y | T57: unclear | Z57: low | AE57: A1:india | AG57: 4.6199
A58: LM00057 | B58: Decentralization in Local Government Empowerment of Bangladesh | C58: 2021 | D58: Shah Md Azimul Ehsan | E58: Springer eBooks | F58: reference-entry | G58: 10.1007/978-3-319-31816-5_4323-1 | H58: W4206292611 | I58: https://doi.org/10.1007/978-3-319-31816-5_4323-1 | K58: 11 | L58: A | M58: A1 | O58: Bangladesh | P58: South Asia | T58: unclear | Z58: low | AE58: A1:india; A1:recent | AF58: W4362646541
A59: LM00058 | B59: Local Government Finance in Pakistan Post 2001 | C59: 2006 | D59: Shahid Kardar | E59: The Lahore journal of economics | F59: article | G59: 10.35536/lje.2006.v11.isp.a7 | H59: W102163451 | I59: https://doi.org/10.35536/lje.2006.v11.isp.a7 | J59: https://doi.org/10.35536/lje.2006.v11.isp.a7 | K59: 9 | L59: A | M59: A1 | O59: Pakistan | P59: South Asia | T59: unclear | W59: auto: The paper calls for financial devolution from the federal and provincial levels to the local level. | X59: auto: The paper calls for financial devolution from the federal and provincial levels to the local level. | Z59: medium | AE59: A1:india | AG59: 4.0829
A60: LM00059 | B60: Women's Reservations and Electoral Politics in Urban Local Bodies: An Analysis of Chennai Municipal Corporation Elections, 2001 | C60: 2003 | D60: Archana Ghosh | E60: Indian Journal of Gender Studies | F60: article | G60: 10.1177/097152150301000106 | H60: W2027894409 | I60: https://doi.org/10.1177/097152150301000106 | K60: 9 | L60: A | M60: A1 | O60: Chennai | P60: South Asia | Q60: Y | T60: unclear | Z60: low | AE60: A1:india | AG60: 0
A61: LM00060 | B61: Decentralization, Supervision, and Chinese Local Government Debt | C61: 2024 | D61: Chunfei Yang; Yongyou Li; Yu Qi; Yanzhe Xu | E61: China & World Economy | F61: article | G61: 10.1111/cwe.12545 | H61: W4400832319 | I61: https://doi.org/10.1111/cwe.12545 | K61: 9 | L61: A | M61: A1 | O61: China | P61: China & East Asia | T61: quantitative | V61: Y | W61: auto: Abstract Decentralization can alter the incentive structure of local governments and one outcome of this is debt accumulation. | Z61: high | AE61: A1:recent | AG61: 15.4972
A62: LM00061 | B62: Urban Governance in India—Spotlight on Mumbai | C62: 2008 | D62: Maria Socorro Diógenes Pinto | E62: SAGE Publications India Pvt Ltd eBooks | F62: book-chapter | G62: 10.4135/9788132101390.n2 | H62: W2493086812 | I62: https://doi.org/10.4135/9788132101390.n2 | K62: 8 | L62: A | M62: A1 | O62: India; Mumbai | P62: South Asia | Q62: Y | T62: unclear | Z62: low | AE62: A1:india | AG62: 2.702
A63: LM00062 | B63: Democratic Decentralization and Empowerment of Local Government Associations in Kerala | C63: 2009 | D63: N Ramakantan | E63: Commonwealth Journal of Local Governance | F63: article | G63: 10.5130/cjlg.v0i2.995 | H63: W2119083365 | I63: https://doi.org/10.5130/cjlg.v0i2.995 | J63: https://epress.lib.uts.edu.au/journals/index.php/cjlg/article/download/995/1017 | K63: 7 | L63: A | M63: A1 | O63: India; Kerala | P63: South Asia | Q63: Y | T63: unclear | W63: auto: During the past decade the Indian state of Kerala has been successfully carrying out democratic decentralization, and has substantially transformed the functions of local governments in line with the 73rd and 74th Constitutional Amendment Acts, which institutionalised the local government system … | Z63: medium | AE63: A1:india | AG63: 1.0829
A64: LM00063 | B64: Participatory Urban Governance in Bangladesh | C64: 2016 | D64: Mohammad Shahidul Hasan Swapan | E64: Environment and Urbanization Asia | F64: article | G64: 10.1177/0975425316652548 | H64: W2551414598 | I64: https://doi.org/10.1177/0975425316652548 | K64: 7 | L64: A | M64: A1 | O64: Bangladesh; South Asian | P64: South Asia | T64: qualitative | W64: auto: In this article, I emphasize the theoretical foundations and practice shaping participatory urban development in developing countries. | X64: auto: In recent years, participation in planning projects has been significantly low, indicating a significant gap between theory and practice. | An in-depth investigation on embedded factors that affect participatory governance process can address this gap. | Z64: high | AE64: A1:india | AG64: 2.4541
A65: LM00064 | B65: Housing adequacy in Delhi, Dhaka and Karachi: Strategies for promoting sustainable and inclusive housing | C65: 2025 | D65: Sohail Ahmad; Faisal Munir; Ram Avtar; Tanjil Sowgat; Debolina Kundu; Ya Ping Wang | E65: Cities | F65: article | G65: 10.1016/j.cities.2025.105779 | H65: W4407909339 | I65: https://doi.org/10.1016/j.cities.2025.105779 | J65: https://doi.org/10.1016/j.cities.2025.105779 | K65: 7 | L65: A | M65: A1 | O65: Delhi; Dhaka; India; Karachi | P65: South Asia | Q65: Y | R65: Y | T65: quantitative | V65: Y | W65: auto: This study examines variations in housing adequacy and its determinants in Delhi, Dhaka and Karachi. | X65: auto: To achieve sustainable and inclusive housing, it is crucial to enhance access to adequate living spaces, particularly among disadvantaged communities, establish interlinkages between housing adequacy and socio-economic conditions and reimagine urban governance systems. • Karachi leads in housing adequacy, followed by Delhi and Dhaka. • Housing conditions have advanced most in Dhaka, with Delhi showing the least improvement. • Socio-cultural disadvantaged communities face severe challenges in … | Z65: high | AE65: A1:india | AG65: 14.8182
A66: LM00065 | B66: Dimension of decentralization process and rural local government in India : a comparison with Bangladesh | C66: 2014 | D66: Md Taufiqul Islam | E66: Journal of South Asian Studies | F66: article | H66: W2099993827 | I66: https://esciencepress.net/journals/JSAS/article/view/549 | J66: https://esciencepress.net/journals/JSAS/article/view/549 | K66: 7 | L66: A | M66: A1 | O66: Bangladesh; India; West Bengal | P66: South Asia | Q66: Y | T66: unclear | W66: auto: Decentralization is a widely used concept, and it is closely linked with democracy, development and good governance. | Z66: medium | AE66: A1:india | AG66: 0
A67: LM00066 | B67: Local Government and Decentralization | C67: 2022 | D67: Tobin Im | E67: Emerald Group Publishing Limited eBooks | F67: book-chapter | G67: 10.1108/s2053-769720220000035036 | H67: W4224437461 | I67: https://doi.org/10.1108/s2053-769720220000035036 | K67: 6 | L67: A | M67: A1 | P67: Not place-specific | T67: unclear | V67: Y | Z67: low | AE67: A1:recent | AG67: 4.8481
A68: LM00067 | B68: Implementation of Local Government and Decentralization within City: A Qualitative Study in Jakarta, Indonesia | C68: 2023 | D68: Dhany Sukma; Sumartono Sumartono; Choirul Saleh; Fadilah M. Amin; Bambang Slamet Riyadi | E68: International Journal of Membrane Science and Technology | F68: article | G68: 10.15379/ijmst.v10i3.1646 | H68: W4385768665 | I68: https://doi.org/10.15379/ijmst.v10i3.1646 | J68: https://cosmosscholars.com/phms/index.php/ijmst/article/download/1646/1063 | K68: 6 | L68: A | M68: A1 | O68: Indonesia; Jakarta | P68: Southeast Asia | T68: qualitative | V68: Y | W68: auto: This study aims to understand the institutional arrangement of city administration at the local government level based on a public policy perspective. | Z68: high | AE68: A1:recent | AG68: 6.3017
A69: LM00068 | B69: Local government finance: challenges in revenue-raising at the Municipal Corporation of Delhi | C69: 2015 | D69: Simanti Bandyopadhyay | E69: Commonwealth Journal of Local Governance | F69: article | G69: 10.5130/cjlg.v0i0.4486 | H69: W1651581627 | I69: https://doi.org/10.5130/cjlg.v0i0.4486 | J69: https://epress.lib.uts.edu.au/journals/index.php/cjlg/article/download/4486/4867 | K69: 5 | L69: A | M69: A1 | O69: Delhi; India | P69: South Asia | Q69: Y | R69: Y | T69: unclear | W69: auto: The main objective of this paper is to examine the extent to which the capital city of Delhi has gained financial autonomy over the years. | X69: auto: However, own revenues have been inadequate to meet growing expenditure requirements, resulting in high revenue expenditure gaps. | Z69: high | AE69: A1:india | AG69: 0
A70: LM00069 | B70: Metropolitan governance and local decentralisation in India: case of Chennai and Kolkata metropolitan regions | C70: 2019 | D70: Arindam Biswas; Tetsuo Kidokoro; Fumihiko Seta | E70: Asia-Pacific Journal of Regional Science | F70: article | G70: 10.1007/s41685-019-00115-w | H70: W2942400011 | I70: https://doi.org/10.1007/s41685-019-00115-w | K70: 5 | L70: A | M70: A1 | O70: Chennai; India; Kolkata | P70: South Asia | Q70: Y | T70: unclear | Z70: low | AE70: A1:india | AG70: 1.1608
A71: LM00070 | B71: Metropolitan and Peri-Urban Governance in India: Case Study of Chennai Metropolitan Area | C71: 2020 | D71: Chetna Singh | E71: Indian Journal of Public Administration | F71: article | G71: 10.1177/0019556120906586 | H71: W3007576890 | I71: https://doi.org/10.1177/0019556120906586 | K71: 5 | L71: A | M71: A1 | O71: Chennai; India; South Asia | P71: South Asia | Q71: Y | T71: qualitative | W71: auto: The rapid growth and economic importance of metropolitan cities is a known fact world over. | Z71: high | AE71: A1:india | AG71: 1.08
A72: LM00071 | B72: Supporting decentralised urban governance : training women municipal councillors in Mumbai, India | C72: 2003 | D72: Bernhard Holzner; Joop de Wit | E72: RePEc: Research Papers in Economics | F72: preprint | H72: W1607554412 | I72: https://repub.eur.nl/pub/19145/wp386.pdf | J72: http://repub.eur.nl/pub/19145 | K72: 5 | L72: A | M72: A1 | O72: India; Mumbai; Netherlands | P72: Multi-region | Q72: Y | T72: unclear | W72: auto: This article is about one set of such training programmes organised by a Mumbai training institution, with the support of the Dutch based Institute of Social Studies. | Z72: high | AA72: Y | AE72: A1:india
A73: LM00072 | B73: Decentralisation and Local Government | C73: 2022 | D73: Yooil Bae | E73: Oxford University Press eBooks | F73: book-chapter | G73: 10.1093/oxfordhb/9780192894045.013.32 | H73: W4213190465 | I73: https://doi.org/10.1093/oxfordhb/9780192894045.013.32 | K73: 4 | L73: A | M73: A1 | O73: South Korea | P73: China & East Asia | T73: unclear | W73: auto: Abstract South Korea’s central–local relations since its democratic transition in the late 1980s have been marked by institutionalization of local politics and delayed decentralization. | X73: auto: On the other hand, weak administrative and fiscal capacities of localities have led to frequent confrontation with the central government and a growing gap among localities. | Z73: high | AE73: A1:recent | AG73: 0
A74: LM00073 | B74: Determinants of Own Revenues in Urban Local Bodies: Evidence from an Indian State | C74: 2022 | D74: Kala Seetharam Sridhar; Vishal Ravi | E74: Environment and Urbanization Asia | F74: article | G74: 10.1177/09754253221076317 | H74: W4214879893 | I74: https://doi.org/10.1177/09754253221076317 | K74: 4 | L74: A | M74: A1 | O74: India; Karnataka | P74: South Asia | Q74: Y | T74: mixed | V74: Y | W74: auto: Our objective in this article is to understand the determinants of sustainable (own source) revenues of cities and empirically estimate it in the context of an econometric model. | Z74: high | AE74: A1:recent | AG74: 1.6738
A75: LM00074 | B75: Local government finance | C75: 2024 | D75: Piotr Bury; Carl-Johan Skovsgaard | E75: Routledge eBooks | F75: book-chapter | G75: 10.4324/9781003576563-6 | H75: W4403490626 | I75: https://doi.org/10.4324/9781003576563-6 | K75: 4 | L75: A | M75: A1 | P75: Not place-specific | T75: conceptual | W75: auto: This chapter deals with local government finance. | Z75: medium | AE75: A1:recent | AF75: W4318703913; W4206749264; W4226231556; W4394571663; W4399744271; W4403027075 | AG75: 0
A76: LM00075 | B76: Reflexive Urban Governance | C76: 2025 | D76: Ciaffi D.; Marra G.; Saporito E. | E76: Edward Elgar Publishing eBooks | F76: book | G76: 10.4337/9781803927343 | H76: W4410427078 | I76: https://doi.org/10.4337/9781803927343 | J76: https://doi.org/10.4337/9781803927343 | K76: 4 | L76: A | M76: A1 | O76: Italy | P76: Global North | T76: conceptual | V76: Y | W76: auto: This chapter aims to contribute to the discussion on reflexive governance by delving into the Italian experience of the ‘shared administration of common goods’ (Arena, 1997). | Z76: high | AE76: A1:recent | AG76: 12.5297
A77: LM00076 | B77: Local Government Financial Performance and Decentralization in Indonesia | C77: 2025 | D77: Daniel Hummel; Bevaola Kusumasari | E77: State and Local Government Review | F77: article | G77: 10.1177/0160323x251364379 | H77: W4413901581 | I77: https://doi.org/10.1177/0160323x251364379 | K77: 4 | L77: A | M77: A1 | O77: Indonesia | P77: Southeast Asia | T77: qualitative | V77: Y | W77: auto: This study compares these measures using 66 cities for macro-level analysis and 4 cities through a series of interviews with local officials across Indonesia for micro-level analysis. | Z77: high | AE77: A1:recent | AG77: 16.8537
A78: LM00077 | B78: A comparative overview of urban governance in Delhi, Hybderabad, Kolkata, and Mumbai | C78: 2009 | D78: Anindita Ghosh; Loraine Kennedy; Joël Ruet; Stéphanie Tawa Lama‐Rewal; Marie‐Hélène Zérah | F78: article | H78: W2741749344 | I78: https://www.documentation.ird.fr/hor/fdi:010052283 | K78: 4 | L78: A | M78: A1 | O78: Delhi; India; Kolkata; Mumbai | P78: South Asia | Q78: Y | R78: Y | T78: unclear | Z78: low | AE78: A1:india | AG78: 1.4539
A79: LM00078 | B79: Transforming Urban Governance to Manage Uncertainty and Climate Change in Mumbai, India | C79: 2018 | D79: Hans Nicolai Adam; Devanathan Parthasarathy; N. C. Narayanan | E79: Figshare | F79: report | H79: W2797228865 | I79: https://figshare.com/articles/report/Transforming_Urban_Governance_to_Manage_Uncertainty_and_Climate_Change_in_Mumbai_India/26483314 | J79: https://figshare.com/articles/report/Transforming_Urban_Governance_to_Manage_Uncertainty_and_Climate_Change_in_Mumbai_India/26483314 | K79: 4 | L79: A | M79: A1 | O79: India; Mumbai | P79: South Asia | Q79: Y | T79: conceptual | W79: auto: Despite unprecedented wealth accumulation, coastal Mumbai suffers from a myriad of socioeconomic and ecological challenges as well as connected uncertainties. | Z79: high | AA79: Y | AE79: A1:india
A80: LM00079 | B80: The Redress of Urban Governance and Marginality in Dhaka, Bangladesh | C80: 2012 | D80: Saleh Ahmed | E80: Advances in education in diverse communities | F80: book-chapter | G80: 10.1108/s1479-358x(2012)0000008025 | H80: W2183662269 | I80: https://doi.org/10.1108/s1479-358x(2012)0000008025 | K80: 3 | L80: A | M80: A1 | O80: Bangladesh; Dhaka | P80: South Asia | T80: conceptual | W80: auto: This chapter aims to approach this issue from a human dimension perspective, where peoples' choices and values are appropriately addressed and the marginalized population can have access to and influence on public policy and decision making. | Z80: high | AE80: A1:india | AG80: 8.8782
A81: LM00080 | B81: A Comparative Overview of Urban Governance in Delhi, Hyderabad, Kolkata, and Mumbai | C81: 2012 | D81: Joël Ruet; Keshab Das; Agnès Huchon; Guillaume Tricot | E81: Routledge eBooks | F81: book-chapter | G81: 10.4324/9780203151860-10 | H81: W4231959608 | I81: https://doi.org/10.4324/9780203151860-10 | K81: 3 | L81: A | M81: A1 | O81: Delhi; Hyderabad; India; Kolkata; Mumbai | P81: South Asia | Q81: Y | R81: Y | T81: unclear | Z81: low | AE81: A1:india | AG81: 0
A82: LM00081 | B82: Role of women councillors in urban local bodies : a case study of the Kolkata and the Howrah Municipal Corporation | C82: 2010 | D82: Anjana Ghosh | E82: Medical Entomology and Zoology | F82: book | H82: W608042492 | I82: http://ci.nii.ac.jp/ncid/BB09073172?l=en | K82: 3 | L82: A | M82: A1 | O82: Kolkata | P82: South Asia | Q82: Y | T82: unclear | Z82: low | AE82: A1:india | AG82: 0
A83: LM00082 | B83: Decentralization and Local Government in Sri Lanka | C83: 2003 | D83: Robert C. Oberst | E83: VS Verlag für Sozialwissenschaften eBooks | F83: book-chapter | G83: 10.1007/978-3-663-10676-0_6 | H83: W166487056 | I83: https://doi.org/10.1007/978-3-663-10676-0_6 | K83: 2 | L83: A | M83: A1 | O83: Sri Lanka | P83: South Asia | T83: conceptual | W83: auto: The public debate over local government in Sri Lanka has been dominated by the ethnic conflict in the country. | Z83: medium | AE83: A1:india | AG83: 0
A84: LM00083 | B84: Indian Municipal Finance 2022 | C84: 2022 | D84: Aromar Revi; Madhumitha Srinivasan; Amir Bashir Bazaz; Manish Kant Dubey; Midhat Fatima Safdar | F84: report | G84: 10.24943/imf02.2022 | H84: W4210463001 | I84: https://doi.org/10.24943/imf02.2022 | K84: 2 | L84: A | M84: A1 | O84: India | P84: South Asia | Q84: Y | T84: unclear | W84: auto: The Constitution (Seventy-fourth) Amendment Act 1992 sought to empower urban local bodies as a third-tier of governance. | Z84: high | AE84: A1:india
A85: LM00084 | B85: Assessing Urban Governance through the Prism of Healthcare Services in Delhi, Hyderabad and Mumbai | C85: 2012 | D85: Loraine Kennedy, Ravi Duggal and Ste´phanie Tawa Lama-Rewal | E85: Routledge eBooks | F85: book-chapter | G85: 10.4324/9780203151860-16 | H85: W4236809888 | I85: https://doi.org/10.4324/9780203151860-16 | K85: 2 | L85: A | M85: A1 | O85: Delhi; Hyderabad; India; Mumbai | P85: South Asia | Q85: Y | R85: Y | T85: conceptual | W85: auto: The aim of this empirical study is to refl ect on urban governance in India’s large metropolitan cities by examining healthcare services in Delhi, Hyderabad and Mumbai. | Z85: high | AE85: A1:india | AG85: 0
A86: LM00085 | B86: Role of Urban Local Bodies in Ensuring Primary Healthcare | C86: 2024 | D86: Parimal Kumar Roy | E86: Advances in medical education, research, and ethics (AMERE) book series | F86: book-chapter | G86: 10.4018/979-8-3693-1178-3.ch004 | H86: W4391312695 | I86: https://doi.org/10.4018/979-8-3693-1178-3.ch004 | K86: 2 | L86: A | M86: A1 | O86: Bangladesh | P86: South Asia | T86: qualitative | V86: Y | W86: auto: This study reflected the author's one-decade professional journey in Bangladesh when he worked on the urban local body. | Z86: high | AE86: A1:recent | AG86: 4.2853
A87: LM00086 | B87: Gender and urban governance | C87: 2024 | D87: Jo Beall | E87: Edward Elgar Publishing eBooks | F87: book-chapter | G87: 10.4337/9781786436139.00020 | H87: W4403417609 | I87: https://doi.org/10.4337/9781786436139.00020 | K87: 2 | L87: A | M87: A1 | P87: Not place-specific | T87: qualitative | V87: Y | W87: auto: This chapter discusses why gendered urban governance is so difficult to research and achieve, draws on case study examples of where advances have been made, and sets out future prospects for gendered urban governance in a context where global trends and challenges are impacting cities in gendered… | Z87: high | AE87: A1:recent | AG87: 8.1755
A88: LM00087 | B88: The Role of Property Tax in Municipal Budget | C88: 2024 | D88: Eva Tomášková; Michal Radvan | E88: Institutiones Administrationis | F88: article | G88: 10.54201/iajas.135 | H88: W4404500331 | I88: https://doi.org/10.54201/iajas.135 | J88: https://administrativescience.com/index.php/instadm/article/download/135/89 | K88: 2 | L88: A | M88: A1 | O88: Czechia | P88: Global North | T88: conceptual | V88: Y | W88: auto: This article is set to evaluate its role in the Czech municipal budgets, predominantly by way of comparing the economic data concerning the revenues of local selfgovernment units in OECD countries. | Z88: high | AE88: A1:recent | AF88: W4406347420 | AG88: 3.4438
A89: LM00088 | B89: FISCAL FEDERALISM AND LOCAL GOVERNMENT FINANCE IN NEPAL | C89: 2012 | D89: Hem Raj Lamichhane | F89: dissertation | H89: W3166867100 | I89: https://elibrary.tucl.edu.np/bitstream/123456789/2104/3/Ph.D.%20Thesis_March%202012-Final.pdf | K89: 2 | L89: A | M89: A1 | P89: Not place-specific | T89: unclear | Z89: low | AE89: A1:india
A90: LM00089 | B90: Financial Health of Urban Local Bodies of Rajasthan with Special Reference to Jodhpur Municipal Corporation | C90: 2013 | D90: S. Chitra | E90: IOSR Journal of Humanities and Social Science | F90: article | G90: 10.9790/0837-1865967 | H90: W2322428737 | I90: https://doi.org/10.9790/0837-1865967 | J90: https://doi.org/10.9790/0837-1865967 | K90: 1 | L90: A | M90: A1 | O90: India; Rajasthan | P90: South Asia | Q90: Y | T90: conceptual | W90: auto: Urban Local bodies (ULB's) in India are facing resource constraint and so they are incapable to perform their functions efficiently.On the other hand their expenditures are increasing enormously.So the gap between the income and expenditure of urban local bodies is portraying a financial crisis, … | X90: auto: Urban Local bodies (ULB's) in India are facing resource constraint and so they are incapable to perform their functions efficiently.On the other hand their expenditures are increasing enormously.So the gap between the income and expenditure of urban local bodies is portraying a financial crisis, which needed to be cured urgently.Also ULB's have little functional and financial autonomy under the existing legal framework.This paper is study of urban local bodies of Rajasthan with special refere… | Z90: high | AE90: A1:india | AG90: 0
A91: LM00090 | B91: The Capacity of Local Government in South Asia | C91: 2015 | D91: Amitava Basu | E91: Public Policy And Administration | F91: article | G91: 10.5755/j01.ppaa.14.3.13436 | H91: W2347019457 | I91: https://doi.org/10.5755/j01.ppaa.14.3.13436 | J91: http://vpa.ktu.lt/index.php/PPA/article/download/13436/7136 | K91: 1 | L91: A | M91: A1 | O91: Africa; Bangladesh; Bhutan; India; Maldives; Nepal; Pakistan; South Asia; South Asian; Sri Lanka | P91: Multi-region | Q91: Y | T91: unclear | W91: auto: South Asia, covers 7 countries – Bangladesh, Bhutan, India, Maldives, Nepal, Pakistan and Sri Lanka; and accounts for about 34% of Asia's population or over 16.5% of the world's population and are home to a vast array of people. | Z91: high | AE91: A1:india | AG91: 0
A92: LM00091 | B92: Financial Implications of Decentralisation: Issues Concerning Resource Mobilisation by Urban Local Bodies | C92: 2000 | D92: Soumen Bagchi | E92: Artha Vijnana Journal of The Gokhale Institute of Politics and Economics | F92: article | G92: 10.21648/arthavij/2000/v42/i4/115858 | H92: W2554180967 | I92: https://doi.org/10.21648/arthavij/2000/v42/i4/115858 | K92: 1 | L92: A | M92: A1 | O92: India | P92: South Asia | Q92: Y | T92: unclear | W92: auto: The Constitution Seventy-fourth Amendment Act 1992, which came into effect on 1 June 1993 is considered to a major breakthrough in the history of urban governance in India. | Z92: high | AE92: A1:india | AG92: 0
A93: LM00092 | B93: Integrated Property Tax The Potential Own Source Revenue of Municipal Finance in Nepal | C93: 2017 | D93: Shankar Prasad Upadhyay; Kamal Das Manandhar | E93: Journal of Advanced Academic Research | F93: article | G93: 10.3126/jaar.v2i1.16593 | H93: W2586314883 | I93: https://doi.org/10.3126/jaar.v2i1.16593 | J93: https://doi.org/10.3126/jaar.v2i1.16593 | K93: 1 | L93: A | M93: A1 | O93: Nepal | P93: South Asia | T93: unclear | W93: auto: No abstract available | Z93: medium | AE93: A1:india | AG93: 0
A94: LM00093 | B94: Participatory Urban Governance and Slum Development in Hyderabad and Kolkata | C94: 2012 | D94: Archana Ghosh | E94: Routledge eBooks | F94: book-chapter | G94: 10.4324/9780203151860-18 | H94: W3201255975 | I94: https://doi.org/10.4324/9780203151860-18 | K94: 1 | L94: A | M94: A1 | O94: Hyderabad; Kolkata | P94: South Asia | Q94: Y | T94: conceptual | W94: auto: Urban governance can be defi ned as the ‘interactive relationship between and within government and non-government forces’ (Stoker 1998: 38). | Z94: high | AE94: A1:india | AG94: 2.9594
A95: LM00094 | B95: Thinking the Delhi, Hyderabad, Kolkata, and Mumbai Experience: Emerging Modes of Urban Governance and State Intervention | C95: 2012 | D95: Joël Ruet | E95: Routledge eBooks | F95: book-chapter | G95: 10.4324/9780203151860-20 | H95: W4246338484 | I95: https://doi.org/10.4324/9780203151860-20 | K95: 1 | L95: A | M95: A1 | O95: Delhi; Hyderabad; India; Kolkata; Mumbai | P95: South Asia | Q95: Y | R95: Y | T95: conceptual | W95: auto: Interactions between various players and the different levels of state machinery have multiplied in number, diversifi ed in nature, and changed in focus. | Z95: high | AE95: A1:india | AG95: 0
A96: LM00095 | B96: Finances of Dhaka City Corporations and Kolkata Municipal Corporation | C96: 2022 | D96: Simanti Bandyopadhyay; Firdousi Naher; Aishna Sharma | E96: SpringerBriefs in economics | F96: book-chapter | G96: 10.1007/978-981-19-2297-8_2 | H96: W4285188090 | I96: https://doi.org/10.1007/978-981-19-2297-8_2 | K96: 1 | L96: A | M96: A1 | O96: Dhaka; Kolkata | P96: South Asia | Q96: Y | T96: unclear | V96: Y | Z96: low | AE96: A1:india | AG96: 2.424
A97: LM00096 | B97: Privatisation, decentralisation and local government in Peninsular Malaysia | C97: 2023 | D97: Kuppusamy Singaravelloo | E97: Edward Elgar Publishing eBooks | F97: book-chapter | G97: 10.4337/9781839104794.00021 | H97: W4321225743 | I97: https://doi.org/10.4337/9781839104794.00021 | K97: 1 | L97: A | M97: A1 | O97: Indonesia; Malaysia; Philippines | P97: Southeast Asia | T97: unclear | V97: Y | W97: auto: This chapter also presents various conflicts local authorities have faced in the country. | Z97: medium | AE97: A1:recent | AG97: 3.1124
A98: LM00097 | B98: Supports for Multi-hazard Risk Reduction in Urban Local Bodies | C98: 2023 | D98: Ripin Kalra | E98: Halduskultuur | F98: article | G98: 10.32994/hk.v22i1.285 | H98: W4376650182 | I98: https://doi.org/10.32994/hk.v22i1.285 | K98: 1 | L98: A | M98: A1 | O98: Bihar; India | P98: South Asia | Q98: Y | T98: conceptual | W98: auto: The research issue that this paper addresses is that of enabling the Urban Local Bodies (ULB) to implement disaster risk reduction and recovery framework(s) developed and agreed on at the national and sub-national levels. | Z98: high | AE98: A1:recent | AG98: 0.4506
A99: LM00098 | B99: Local Government Finance in Britain | C99: 2024 | D99: Stephen J. Balley | E99: Routledge eBooks | F99: book-chapter | G99: 10.4324/9781003514367-12 | H99: W4399744233 | I99: https://doi.org/10.4324/9781003514367-12 | K99: 1 | L99: A | M99: A1 | O99: United Kingdom | P99: Global North | T99: unclear | W99: auto: Local government finance is at a crossroads. | Z99: medium | AE99: A1:recent | AG99: 0
A100: LM00099 | B100: Power and urban governance | C100: 2024 | D100: Jonathan S. Davies; Mark Roberts; Simone Vegliò | E100: Edward Elgar Publishing eBooks | F100: book-chapter | G100: 10.4337/9781802200669.00016 | H100: W4400906880 | I100: https://doi.org/10.4337/9781802200669.00016 | K100: 1 | L100: A | M100: A1 | O100: Chicago | P100: Global North | T100: conceptual | V100: Y | W100: auto: The significance of cities as concentrations of political and economic power can hardly be overstated. | X100: auto: The chapter concludes by suggesting pathways for future research. | Z100: high | AE100: A1:recent | AG100: 4.7039
...

Sheet Gap matrix
A1: Gap matrix — live COUNTIFS over the Records tab (counts update when rows are added)
A2: Counts are of records in this bibliography (a sample), not of all literature; use the Growth tab for OpenAlex-wide counts. Records found only by the supplementary query set (Supplementary = Y) are excluded.
A4: Theme × region
A5: Theme | B5: Name | C5: Global North | D5: China & East Asia | E5: South Asia | F5: Southeast Asia | G5: Africa | H5: Latin America | I5: Middle East | J5: Multi-region | K5: Not place-specific | L5: Total | M5: India flag
A6: A1 | B6: Urban governance, decentralisation & municipal finance | C6: =COUNTIFS(Records!$M:$M,$A6,Records!$AB:$AB,"<>Y",Records!$P:$P,C$5) | D6: =COUNTIFS(Records!$M:$M,$A6,Records!$AB:$AB,"<>Y",Records!$P:$P,D$5) | E6: =COUNTIFS(Records!$M:$M,$A6,Records!$AB:$AB,"<>Y",Records!$P:$P,E$5) | F6: =COUNTIFS(Records!$M:$M,$A6,Records!$AB:$AB,"<>Y",Records!$P:$P,F$5) | G6: =COUNTIFS(Records!$M:$M,$A6,Records!$AB:$AB,"<>Y",Records!$P:$P,G$5) | H6: =COUNTIFS(Records!$M:$M,$A6,Records!$AB:$AB,"<>Y",Records!$P:$P,H$5) | I6: =COUNTIFS(Records!$M:$M,$A6,Records!$AB:$AB,"<>Y",Records!$P:$P,I$5) | J6: =COUNTIFS(Records!$M:$M,$A6,Records!$AB:$AB,"<>Y",Records!$P:$P,J$5) | K6: =COUNTIFS(Records!$M:$M,$A6,Records!$AB:$AB,"<>Y",Records!$P:$P,K$5) | L6: =COUNTIFS(Records!$M:$M,$A6,Records!$AB:$AB,"<>Y") | M6: =COUNTIFS(Records!$M:$M,$A6,Records!$AB:$AB,"<>Y",Records!$Q:$Q,"Y")
A7: A2 | B7: Planning, master plans & land-use regulation | C7: =COUNTIFS(Records!$M:$M,$A7,Records!$AB:$AB,"<>Y",Records!$P:$P,C$5) | D7: =COUNTIFS(Records!$M:$M,$A7,Records!$AB:$AB,"<>Y",Records!$P:$P,D$5) | E7: =COUNTIFS(Records!$M:$M,$A7,Records!$AB:$AB,"<>Y",Records!$P:$P,E$5) | F7: =COUNTIFS(Records!$M:$M,$A7,Records!$AB:$AB,"<>Y",Records!$P:$P,F$5) | G7: =COUNTIFS(Records!$M:$M,$A7,Records!$AB:$AB,"<>Y",Records!$P:$P,G$5) | H7: =COUNTIFS(Records!$M:$M,$A7,Records!$AB:$AB,"<>Y",Records!$P:$P,H$5) | I7: =COUNTIFS(Records!$M:$M,$A7,Records!$AB:$AB,"<>Y",Records!$P:$P,I$5) | J7: =COUNTIFS(Records!$M:$M,$A7,Records!$AB:$AB,"<>Y",Records!$P:$P,J$5) | K7: =COUNTIFS(Records!$M:$M,$A7,Records!$AB:$AB,"<>Y",Records!$P:$P,K$5) | L7: =COUNTIFS(Records!$M:$M,$A7,Records!$AB:$AB,"<>Y") | M7: =COUNTIFS(Records!$M:$M,$A7,Records!$AB:$AB,"<>Y",Records!$Q:$Q,"Y")
A8: A3 | B8: Housing, informality & slums | C8: =COUNTIFS(Records!$M:$M,$A8,Records!$AB:$AB,"<>Y",Records!$P:$P,C$5) | D8: =COUNTIFS(Records!$M:$M,$A8,Records!$AB:$AB,"<>Y",Records!$P:$P,D$5) | E8: =COUNTIFS(Records!$M:$M,$A8,Records!$AB:$AB,"<>Y",Records!$P:$P,E$5) | F8: =COUNTIFS(Records!$M:$M,$A8,Records!$AB:$AB,"<>Y",Records!$P:$P,F$5) | G8: =COUNTIFS(Records!$M:$M,$A8,Records!$AB:$AB,"<>Y",Records!$P:$P,G$5) | H8: =COUNTIFS(Records!$M:$M,$A8,Records!$AB:$AB,"<>Y",Records!$P:$P,H$5) | I8: =COUNTIFS(Records!$M:$M,$A8,Records!$AB:$AB,"<>Y",Records!$P:$P,I$5) | J8: =COUNTIFS(Records!$M:$M,$A8,Records!$AB:$AB,"<>Y",Records!$P:$P,J$5) | K8: =COUNTIFS(Records!$M:$M,$A8,Records!$AB:$AB,"<>Y",Records!$P:$P,K$5) | L8: =COUNTIFS(Records!$M:$M,$A8,Records!$AB:$AB,"<>Y") | M8: =COUNTIFS(Records!$M:$M,$A8,Records!$AB:$AB,"<>Y",Records!$Q:$Q,"Y")
A9: A4 | B9: Eviction, resettlement & displacement | C9: =COUNTIFS(Records!$M:$M,$A9,Records!$AB:$AB,"<>Y",Records!$P:$P,C$5) | D9: =COUNTIFS(Records!$M:$M,$A9,Records!$AB:$AB,"<>Y",Records!$P:$P,D$5) | E9: =COUNTIFS(Records!$M:$M,$A9,Records!$AB:$AB,"<>Y",Records!$P:$P,E$5) | F9: =COUNTIFS(Records!$M:$M,$A9,Records!$AB:$AB,"<>Y",Records!$P:$P,F$5) | G9: =COUNTIFS(Records!$M:$M,$A9,Records!$AB:$AB,"<>Y",Records!$P:$P,G$5) | H9: =COUNTIFS(Records!$M:$M,$A9,Records!$AB:$AB,"<>Y",Records!$P:$P,H$5) | I9: =COUNTIFS(Records!$M:$M,$A9,Records!$AB:$AB,"<>Y",Records!$P:$P,I$5) | J9: =COUNTIFS(Records!$M:$M,$A9,Records!$AB:$AB,"<>Y",Records!$P:$P,J$5) | K9: =COUNTIFS(Records!$M:$M,$A9,Records!$AB:$AB,"<>Y",Records!$P:$P,K$5) | L9: =COUNTIFS(Records!$M:$M,$A9,Records!$AB:$AB,"<>Y") | M9: =COUNTIFS(Records!$M:$M,$A9,Records!$AB:$AB,"<>Y",Records!$Q:$Q,"Y")
A10: A5 | B10: Land, peri-urban & extended urbanisation | C10: =COUNTIFS(Records!$M:$M,$A10,Records!$AB:$AB,"<>Y",Records!$P:$P,C$5) | D10: =COUNTIFS(Records!$M:$M,$A10,Records!$AB:$AB,"<>Y",Records!$P:$P,D$5) | E10: =COUNTIFS(Records!$M:$M,$A10,Records!$AB:$AB,"<>Y",Records!$P:$P,E$5) | F10: =COUNTIFS(Records!$M:$M,$A10,Records!$AB:$AB,"<>Y",Records!$P:$P,F$5) | G10: =COUNTIFS(Records!$M:$M,$A10,Records!$AB:$AB,"<>Y",Records!$P:$P,G$5) | H10: =COUNTIFS(Records!$M:$M,$A10,Records!$AB:$AB,"<>Y",Records!$P:$P,H$5) | I10: =COUNTIFS(Records!$M:$M,$A10,Records!$AB:$AB,"<>Y",Records!$P:$P,I$5) | J10: =COUNTIFS(Records!$M:$M,$A10,Records!$AB:$AB,"<>Y",Records!$P:$P,J$5) | K10: =COUNTIFS(Records!$M:$M,$A10,Records!$AB:$AB,"<>Y",Records!$P:$P,K$5) | L10: =COUNTIFS(Records!$M:$M,$A10,Records!$AB:$AB,"<>Y") | M10: =COUNTIFS(Records!$M:$M,$A10,Records!$AB:$AB,"<>Y",Records!$Q:$Q,"Y")
A11: A6 | B11: Small towns, census towns & secondary cities | C11: =COUNTIFS(Records!$M:$M,$A11,Records!$AB:$AB,"<>Y",Records!$P:$P,C$5) | D11: =COUNTIFS(Records!$M:$M,$A11,Records!$AB:$AB,"<>Y",Records!$P:$P,D$5) | E11: =COUNTIFS(Records!$M:$M,$A11,Records!$AB:$AB,"<>Y",Records!$P:$P,E$5) | F11: =COUNTIFS(Records!$M:$M,$A11,Records!$AB:$AB,"<>Y",Records!$P:$P,F$5) | G11: =COUNTIFS(Records!$M:$M,$A11,Records!$AB:$AB,"<>Y",Records!$P:$P,G$5) | H11: =COUNTIFS(Records!$M:$M,$A11,Records!$AB:$AB,"<>Y",Records!$P:$P,H$5) | I11: =COUNTIFS(Records!$M:$M,$A11,Records!$AB:$AB,"<>Y",Records!$P:$P,I$5) | J11: =COUNTIFS(Records!$M:$M,$A11,Records!$AB:$AB,"<>Y",Records!$P:$P,J$5) | K11: =COUNTIFS(Records!$M:$M,$A11,Records!$AB:$AB,"<>Y",Records!$P:$P,K$5) | L11: =COUNTIFS(Records!$M:$M,$A11,Records!$AB:$AB,"<>Y") | M11: =COUNTIFS(Records!$M:$M,$A11,Records!$AB:$AB,"<>Y",Records!$Q:$Q,"Y")
A12: A7 | B12: Urban infrastructure (water, sanitation, energy) & infrastructural citizenship | C12: =COUNTIFS(Records!$M:$M,$A12,Records!$AB:$AB,"<>Y",Records!$P:$P,C$5) | D12: =COUNTIFS(Records!$M:$M,$A12,Records!$AB:$AB,"<>Y",Records!$P:$P,D$5) | E12: =COUNTIFS(Records!$M:$M,$A12,Records!$AB:$AB,"<>Y",Records!$P:$P,E$5) | F12: =COUNTIFS(Records!$M:$M,$A12,Records!$AB:$AB,"<>Y",Records!$P:$P,F$5) | G12: =COUNTIFS(Records!$M:$M,$A12,Records!$AB:$AB,"<>Y",Records!$P:$P,G$5) | H12: =COUNTIFS(Records!$M:$M,$A12,Records!$AB:$AB,"<>Y",Records!$P:$P,H$5) | I12: =COUNTIFS(Records!$M:$M,$A12,Records!$AB:$AB,"<>Y",Records!$P:$P,I$5) | J12: =COUNTIFS(Records!$M:$M,$A12,Records!$AB:$AB,"<>Y",Records!$P:$P,J$5) | K12: =COUNTIFS(Records!$M:$M,$A12,Records!$AB:$AB,"<>Y",Records!$P:$P,K$5) | L12: =COUNTIFS(Records!$M:$M,$A12,Records!$AB:$AB,"<>Y") | M12: =COUNTIFS(Records!$M:$M,$A12,Records!$AB:$AB,"<>Y",Records!$Q:$Q,"Y")
A13: A8 | B13: Mobility & transport (social science) | C13: =COUNTIFS(Records!$M:$M,$A13,Records!$AB:$AB,"<>Y",Records!$P:$P,C$5) | D13: =COUNTIFS(Records!$M:$M,$A13,Records!$AB:$AB,"<>Y",Records!$P:$P,D$5) | E13: =COUNTIFS(Records!$M:$M,$A13,Records!$AB:$AB,"<>Y",Records!$P:$P,E$5) | F13: =COUNTIFS(Records!$M:$M,$A13,Records!$AB:$AB,"<>Y",Records!$P:$P,F$5) | G13: =COUNTIFS(Records!$M:$M,$A13,Records!$AB:$AB,"<>Y",Records!$P:$P,G$5) | H13: =COUNTIFS(Records!$M:$M,$A13,Records!$AB:$AB,"<>Y",Records!$P:$P,H$5) | I13: =COUNTIFS(Records!$M:$M,$A13,Records!$AB:$AB,"<>Y",Records!$P:$P,I$5) | J13: =COUNTIFS(Records!$M:$M,$A13,Records!$AB:$AB,"<>Y",Records!$P:$P,J$5) | K13: =COUNTIFS(Records!$M:$M,$A13,Records!$AB:$AB,"<>Y",Records!$P:$P,K$5) | L13: =COUNTIFS(Records!$M:$M,$A13,Records!$AB:$AB,"<>Y") | M13: =COUNTIFS(Records!$M:$M,$A13,Records!$AB:$AB,"<>Y",Records!$Q:$Q,"Y")
A14: A9 | B14: Public space, publicness & the street | C14: =COUNTIFS(Records!$M:$M,$A14,Records!$AB:$AB,"<>Y",Records!$P:$P,C$5) | D14: =COUNTIFS(Records!$M:$M,$A14,Records!$AB:$AB,"<>Y",Records!$P:$P,D$5) | E14: =COUNTIFS(Records!$M:$M,$A14,Records!$AB:$AB,"<>Y",Records!$P:$P,E$5) | F14: =COUNTIFS(Records!$M:$M,$A14,Records!$AB:$AB,"<>Y",Records!$P:$P,F$5) | G14: =COUNTIFS(Records!$M:$M,$A14,Records!$AB:$AB,"<>Y",Records!$P:$P,G$5) | H14: =COUNTIFS(Records!$M:$M,$A14,Records!$AB:$AB,"<>Y",Records!$P:$P,H$5) | I14: =COUNTIFS(Records!$M:$M,$A14,Records!$AB:$AB,"<>Y",Records!$P:$P,I$5) | J14: =COUNTIFS(Records!$M:$M,$A14,Records!$AB:$AB,"<>Y",Records!$P:$P,J$5) | K14: =COUNTIFS(Records!$M:$M,$A14,Records!$AB:$AB,"<>Y",Records!$P:$P,K$5) | L14: =COUNTIFS(Records!$M:$M,$A14,Records!$AB:$AB,"<>Y") | M14: =COUNTIFS(Records!$M:$M,$A14,Records!$AB:$AB,"<>Y",Records!$Q:$Q,"Y")
A15: A10 | B15: Urban economy, informal work & street vending | C15: =COUNTIFS(Records!$M:$M,$A15,Records!$AB:$AB,"<>Y",Records!$P:$P,C$5) | D15: =COUNTIFS(Records!$M:$M,$A15,Records!$AB:$AB,"<>Y",Records!$P:$P,D$5) | E15: =COUNTIFS(Records!$M:$M,$A15,Records!$AB:$AB,"<>Y",Records!$P:$P,E$5) | F15: =COUNTIFS(Records!$M:$M,$A15,Records!$AB:$AB,"<>Y",Records!$P:$P,F$5) | G15: =COUNTIFS(Records!$M:$M,$A15,Records!$AB:$AB,"<>Y",Records!$P:$P,G$5) | H15: =COUNTIFS(Records!$M:$M,$A15,Records!$AB:$AB,"<>Y",Records!$P:$P,H$5) | I15: =COUNTIFS(Records!$M:$M,$A15,Records!$AB:$AB,"<>Y",Records!$P:$P,I$5) | J15: =COUNTIFS(Records!$M:$M,$A15,Records!$AB:$AB,"<>Y",Records!$P:$P,J$5) | K15: =COUNTIFS(Records!$M:$M,$A15,Records!$AB:$AB,"<>Y",Records!$P:$P,K$5) | L15: =COUNTIFS(Records!$M:$M,$A15,Records!$AB:$AB,"<>Y") | M15: =COUNTIFS(Records!$M:$M,$A15,Records!$AB:$AB,"<>Y",Records!$Q:$Q,"Y")
A16: A11 | B16: Migration & the city | C16: =COUNTIFS(Records!$M:$M,$A16,Records!$AB:$AB,"<>Y",Records!$P:$P,C$5) | D16: =COUNTIFS(Records!$M:$M,$A16,Records!$AB:$AB,"<>Y",Records!$P:$P,D$5) | E16: =COUNTIFS(Records!$M:$M,$A16,Records!$AB:$AB,"<>Y",Records!$P:$P,E$5) | F16: =COUNTIFS(Records!$M:$M,$A16,Records!$AB:$AB,"<>Y",Records!$P:$P,F$5) | G16: =COUNTIFS(Records!$M:$M,$A16,Records!$AB:$AB,"<>Y",Records!$P:$P,G$5) | H16: =COUNTIFS(Records!$M:$M,$A16,Records!$AB:$AB,"<>Y",Records!$P:$P,H$5) | I16: =COUNTIFS(Records!$M:$M,$A16,Records!$AB:$AB,"<>Y",Records!$P:$P,I$5) | J16: =COUNTIFS(Records!$M:$M,$A16,Records!$AB:$AB,"<>Y",Records!$P:$P,J$5) | K16: =COUNTIFS(Records!$M:$M,$A16,Records!$AB:$AB,"<>Y",Records!$P:$P,K$5) | L16: =COUNTIFS(Records!$M:$M,$A16,Records!$AB:$AB,"<>Y") | M16: =COUNTIFS(Records!$M:$M,$A16,Records!$AB:$AB,"<>Y",Records!$Q:$Q,"Y")
A17: A12 | B17: Gender, caste, class & the city | C17: =COUNTIFS(Records!$M:$M,$A17,Records!$AB:$AB,"<>Y",Records!$P:$P,C$5) | D17: =COUNTIFS(Records!$M:$M,$A17,Records!$AB:$AB,"<>Y",Records!$P:$P,D$5) | E17: =COUNTIFS(Records!$M:$M,$A17,Records!$AB:$AB,"<>Y",Records!$P:$P,E$5) | F17: =COUNTIFS(Records!$M:$M,$A17,Records!$AB:$AB,"<>Y",Records!$P:$P,F$5) | G17: =COUNTIFS(Records!$M:$M,$A17,Records!$AB:$AB,"<>Y",Records!$P:$P,G$5) | H17: =COUNTIFS(Records!$M:$M,$A17,Records!$AB:$AB,"<>Y",Records!$P:$P,H$5) | I17: =COUNTIFS(Records!$M:$M,$A17,Records!$AB:$AB,"<>Y",Records!$P:$P,I$5) | J17: =COUNTIFS(Records!$M:$M,$A17,Records!$AB:$AB,"<>Y",Records!$P:$P,J$5) | K17: =COUNTIFS(Records!$M:$M,$A17,Records!$AB:$AB,"<>Y",Records!$P:$P,K$5) | L17: =COUNTIFS(Records!$M:$M,$A17,Records!$AB:$AB,"<>Y") | M17: =COUNTIFS(Records!$M:$M,$A17,Records!$AB:$AB,"<>Y",Records!$Q:$Q,"Y")
... A53: C18 | B53: Neighbourhood platforms & digital public space (WhatsApp, Nextdoor, RWA groups) | C53: =COUNTIFS(Records!$M:$M,$A53,Records!$AB:$AB,"<>Y",Records!$P:$P,C$5) | D53: =COUNTIFS(Records!$M:$M,$A53,Records!$AB:$AB,"<>Y",Records!$P:$P,D$5) | E53: =COUNTIFS(Records!$M:$M,$A53,Records!$AB:$AB,"<>Y",Records!$P:$P,E$5) | F53: =COUNTIFS(Records!$M:$M,$A53,Records!$AB:$AB,"<>Y",Records!$P:$P,F$5) | G53: =COUNTIFS(Records!$M:$M,$A53,Records!$AB:$AB,"<>Y",Records!$P:$P,G$5) | H53: =COUNTIFS(Records!$M:$M,$A53,Records!$AB:$AB,"<>Y",Records!$P:$P,H$5) | I53: =COUNTIFS(Records!$M:$M,$A53,Records!$AB:$AB,"<>Y",Records!$P:$P,I$5) | J53: =COUNTIFS(Records!$M:$M,$A53,Records!$AB:$AB,"<>Y",Records!$P:$P,J$5) | K53: =COUNTIFS(Records!$M:$M,$A53,Records!$AB:$AB,"<>Y",Records!$P:$P,K$5) | L53: =COUNTIFS(Records!$M:$M,$A53,Records!$AB:$AB,"<>Y") | M53: =COUNTIFS(Records!$M:$M,$A53,Records!$AB:$AB,"<>Y",Records!$Q:$Q,"Y")
B54: All themes | C54: =SUM(C6:C53) | D54: =SUM(D6:D53) | E54: =SUM(E6:E53) | F54: =SUM(F6:F53) | G54: =SUM(G6:G53) | H54: =SUM(H6:H53) | I54: =SUM(I6:I53) | J54: =SUM(J6:J53) | ... M54: =SUM(M6:M53)
A57: Theme × method (inferred from abstract)
A58: Theme | B58: Name | C58: qualitative | D58: quantitative | E58: mixed | F58: review | G58: conceptual | H58: computational | I58: unclear | J58: Total | K58: India flag
A59: A1 | B59: Urban governance, decentralisation & municipal finance | C59: =COUNTIFS(Records!$M:$M,$A59,Records!$AB:$AB,"<>Y",Records!$T:$T,C$58) | D59: =COUNTIFS(Records!$M:$M,$A59,Records!$AB:$AB,"<>Y",Records!$T:$T,D$58) | E59: =COUNTIFS(Records!$M:$M,$A59,Records!$AB:$AB,"<>Y",Records!$T:$T,E$58) | F59: =COUNTIFS(Records!$M:$M,$A59,Records!$AB:$AB,"<>Y",Records!$T:$T,F$58) | G59: =COUNTIFS(Records!$M:$M,$A59,Records!$AB:$AB,"<>Y",Records!$T:$T,G$58) | H59: =COUNTIFS(Records!$M:$M,$A59,Records!$AB:$AB,"<>Y",Records!$T:$T,H$58) | I59: =COUNTIFS(Records!$M:$M,$A59,Records!$AB:$AB,"<>Y",Records!$T:$T,I$58) | J59: =COUNTIFS(Records!$M:$M,$A59,Records!$AB:$AB,"<>Y") | K59: =COUNTIFS(Records!$M:$M,$A59,Records!$AB:$AB,"<>Y",Records!$Q:$Q,"Y")
A60: A2 | B60: Planning, master plans & land-use regulation | C60: =COUNTIFS(Records!$M:$M,$A60,Records!$AB:$AB,"<>Y",Records!$T:$T,C$58) | D60: =COUNTIFS(Records!$M:$M,$A60,Records!$AB:$AB,"<>Y",Records!$T:$T,D$58) | E60: =COUNTIFS(Records!$M:$M,$A60,Records!$AB:$AB,"<>Y",Records!$T:$T,E$58) | F60: =COUNTIFS(Records!$M:$M,$A60,Records!$AB:$AB,"<>Y",Records!$T:$T,F$58) | G60: =COUNTIFS(Records!$M:$M,$A60,Records!$AB:$AB,"<>Y",Records!$T:$T,G$58) | H60: =COUNTIFS(Records!$M:$M,$A60,Records!$AB:$AB,"<>Y",Records!$T:$T,H$58) | I60: =COUNTIFS(Records!$M:$M,$A60,Records!$AB:$AB,"<>Y",Records!$T:$T,I$58) | J60: =COUNTIFS(Records!$M:$M,$A60,Records!$AB:$AB,"<>Y") | K60: =COUNTIFS(Records!$M:$M,$A60,Records!$AB:$AB,"<>Y",Records!$Q:$Q,"Y")
A61: A3 | B61: Housing, informality & slums | C61: =COUNTIFS(Records!$M:$M,$A61,Records!$AB:$AB,"<>Y",Records!$T:$T,C$58) | D61: =COUNTIFS(Records!$M:$M,$A61,Records!$AB:$AB,"<>Y",Records!$T:$T,D$58) | E61: =COUNTIFS(Records!$M:$M,$A61,Records!$AB:$AB,"<>Y",Records!$T:$T,E$58) | F61: =COUNTIFS(Records!$M:$M,$A61,Records!$AB:$AB,"<>Y",Records!$T:$T,F$58) | G61: =COUNTIFS(Records!$M:$M,$A61,Records!$AB:$AB,"<>Y",Records!$T:$T,G$58) | H61: =COUNTIFS(Records!$M:$M,$A61,Records!$AB:$AB,"<>Y",Records!$T:$T,H$58) | I61: =COUNTIFS(Records!$M:$M,$A61,Records!$AB:$AB,"<>Y",Records!$T:$T,I$58) | J61: =COUNTIFS(Records!$M:$M,$A61,Records!$AB:$AB,"<>Y") | K61: =COUNTIFS(Records!$M:$M,$A61,Records!$AB:$AB,"<>Y",Records!$Q:$Q,"Y")
A62: A4 | B62: Eviction, resettlement & displacement | C62: =COUNTIFS(Records!$M:$M,$A62,Records!$AB:$AB,"<>Y",Records!$T:$T,C$58) | D62: =COUNTIFS(Records!$M:$M,$A62,Records!$AB:$AB,"<>Y",Records!$T:$T,D$58) | E62: =COUNTIFS(Records!$M:$M,$A62,Records!$AB:$AB,"<>Y",Records!$T:$T,E$58) | F62: =COUNTIFS(Records!$M:$M,$A62,Records!$AB:$AB,"<>Y",Records!$T:$T,F$58) | G62: =COUNTIFS(Records!$M:$M,$A62,Records!$AB:$AB,"<>Y",Records!$T:$T,G$58) | H62: =COUNTIFS(Records!$M:$M,$A62,Records!$AB:$AB,"<>Y",Records!$T:$T,H$58) | I62: =COUNTIFS(Records!$M:$M,$A62,Records!$AB:$AB,"<>Y",Records!$T:$T,I$58) | J62: =COUNTIFS(Records!$M:$M,$A62,Records!$AB:$AB,"<>Y") | K62: =COUNTIFS(Records!$M:$M,$A62,Records!$AB:$AB,"<>Y",Records!$Q:$Q,"Y")
A63: A5 | B63: Land, peri-urban & extended urbanisation | C63: =COUNTIFS(Records!$M:$M,$A63,Records!$AB:$AB,"<>Y",Records!$T:$T,C$58) | D63: =COUNTIFS(Records!$M:$M,$A63,Records!$AB:$AB,"<>Y",Records!$T:$T,D$58) | E63: =COUNTIFS(Records!$M:$M,$A63,Records!$AB:$AB,"<>Y",Records!$T:$T,E$58) | F63: =COUNTIFS(Records!$M:$M,$A63,Records!$AB:$AB,"<>Y",Records!$T:$T,F$58) | G63: =COUNTIFS(Records!$M:$M,$A63,Records!$AB:$AB,"<>Y",Records!$T:$T,G$58) | H63: =COUNTIFS(Records!$M:$M,$A63,Records!$AB:$AB,"<>Y",Records!$T:$T,H$58) | I63: =COUNTIFS(Records!$M:$M,$A63,Records!$AB:$AB,"<>Y",Records!$T:$T,I$58) | J63: =COUNTIFS(Records!$M:$M,$A63,Records!$AB:$AB,"<>Y") | K63: =COUNTIFS(Records!$M:$M,$A63,Records!$AB:$AB,"<>Y",Records!$Q:$Q,"Y")
A64: A6 | B64: Small towns, census towns & secondary cities | C64: =COUNTIFS(Records!$M:$M,$A64,Records!$AB:$AB,"<>Y",Records!$T:$T,C$58) | D64: =COUNTIFS(Records!$M:$M,$A64,Records!$AB:$AB,"<>Y",Records!$T:$T,D$58) | E64: =COUNTIFS(Records!$M:$M,$A64,Records!$AB:$AB,"<>Y",Records!$T:$T,E$58) | F64: =COUNTIFS(Records!$M:$M,$A64,Records!$AB:$AB,"<>Y",Records!$T:$T,F$58) | G64: =COUNTIFS(Records!$M:$M,$A64,Records!$AB:$AB,"<>Y",Records!$T:$T,G$58) | H64: =COUNTIFS(Records!$M:$M,$A64,Records!$AB:$AB,"<>Y",Records!$T:$T,H$58) | I64: =COUNTIFS(Records!$M:$M,$A64,Records!$AB:$AB,"<>Y",Records!$T:$T,I$58) | J64: =COUNTIFS(Records!$M:$M,$A64,Records!$AB:$AB,"<>Y") | K64: =COUNTIFS(Records!$M:$M,$A64,Records!$AB:$AB,"<>Y",Records!$Q:$Q,"Y")
A65: A7 | B65: Urban infrastructure (water, sanitation, energy) & infrastructural citizenship | C65: =COUNTIFS(Records!$M:$M,$A65,Records!$AB:$AB,"<>Y",Records!$T:$T,C$58) | D65: =COUNTIFS(Records!$M:$M,$A65,Records!$AB:$AB,"<>Y",Records!$T:$T,D$58) | E65: =COUNTIFS(Records!$M:$M,$A65,Records!$AB:$AB,"<>Y",Records!$T:$T,E$58) | F65: =COUNTIFS(Records!$M:$M,$A65,Records!$AB:$AB,"<>Y",Records!$T:$T,F$58) | G65: =COUNTIFS(Records!$M:$M,$A65,Records!$AB:$AB,"<>Y",Records!$T:$T,G$58) | H65: =COUNTIFS(Records!$M:$M,$A65,Records!$AB:$AB,"<>Y",Records!$T:$T,H$58) | I65: =COUNTIFS(Records!$M:$M,$A65,Records!$AB:$AB,"<>Y",Records!$T:$T,I$58) | J65: =COUNTIFS(Records!$M:$M,$A65,Records!$AB:$AB,"<>Y") | K65: =COUNTIFS(Records!$M:$M,$A65,Records!$AB:$AB,"<>Y",Records!$Q:$Q,"Y")
A66: A8 | B66: Mobility & transport (social science) | C66: =COUNTIFS(Records!$M:$M,$A66,Records!$AB:$AB,"<>Y",Records!$T:$T,C$58) | D66: =COUNTIFS(Records!$M:$M,$A66,Records!$AB:$AB,"<>Y",Records!$T:$T,D$58) | E66: =COUNTIFS(Records!$M:$M,$A66,Records!$AB:$AB,"<>Y",Records!$T:$T,E$58) | F66: =COUNTIFS(Records!$M:$M,$A66,Records!$AB:$AB,"<>Y",Records!$T:$T,F$58) | G66: =COUNTIFS(Records!$M:$M,$A66,Records!$AB:$AB,"<>Y",Records!$T:$T,G$58) | H66: =COUNTIFS(Records!$M:$M,$A66,Records!$AB:$AB,"<>Y",Records!$T:$T,H$58) | I66: =COUNTIFS(Records!$M:$M,$A66,Records!$AB:$AB,"<>Y",Records!$T:$T,I$58) | J66: =COUNTIFS(Records!$M:$M,$A66,Records!$AB:$AB,"<>Y") | K66: =COUNTIFS(Records!$M:$M,$A66,Records!$AB:$AB,"<>Y",Records!$Q:$Q,"Y")
A67: A9 | B67: Public space, publicness & the street | C67: =COUNTIFS(Records!$M:$M,$A67,Records!$AB:$AB,"<>Y",Records!$T:$T,C$58) | D67: =COUNTIFS(Records!$M:$M,$A67,Records!$AB:$AB,"<>Y",Records!$T:$T,D$58) | E67: =COUNTIFS(Records!$M:$M,$A67,Records!$AB:$AB,"<>Y",Records!$T:$T,E$58) | F67: =COUNTIFS(Records!$M:$M,$A67,Records!$AB:$AB,"<>Y",Records!$T:$T,F$58) | G67: =COUNTIFS(Records!$M:$M,$A67,Records!$AB:$AB,"<>Y",Records!$T:$T,G$58) | H67: =COUNTIFS(Records!$M:$M,$A67,Records!$AB:$AB,"<>Y",Records!$T:$T,H$58) | I67: =COUNTIFS(Records!$M:$M,$A67,Records!$AB:$AB,"<>Y",Records!$T:$T,I$58) | J67: =COUNTIFS(Records!$M:$M,$A67,Records!$AB:$AB,"<>Y") | K67: =COUNTIFS(Records!$M:$M,$A67,Records!$AB:$AB,"<>Y",Records!$Q:$Q,"Y")
A68: A10 | B68: Urban economy, informal work & street vending | C68: =COUNTIFS(Records!$M:$M,$A68,Records!$AB:$AB,"<>Y",Records!$T:$T,C$58) | D68: =COUNTIFS(Records!$M:$M,$A68,Records!$AB:$AB,"<>Y",Records!$T:$T,D$58) | E68: =COUNTIFS(Records!$M:$M,$A68,Records!$AB:$AB,"<>Y",Records!$T:$T,E$58) | F68: =COUNTIFS(Records!$M:$M,$A68,Records!$AB:$AB,"<>Y",Records!$T:$T,F$58) | G68: =COUNTIFS(Records!$M:$M,$A68,Records!$AB:$AB,"<>Y",Records!$T:$T,G$58) | H68: =COUNTIFS(Records!$M:$M,$A68,Records!$AB:$AB,"<>Y",Records!$T:$T,H$58) | I68: =COUNTIFS(Records!$M:$M,$A68,Records!$AB:$AB,"<>Y",Records!$T:$T,I$58) | J68: =COUNTIFS(Records!$M:$M,$A68,Records!$AB:$AB,"<>Y") | K68: =COUNTIFS(Records!$M:$M,$A68,Records!$AB:$AB,"<>Y",Records!$Q:$Q,"Y")
A69: A11 | B69: Migration & the city | C69: =COUNTIFS(Records!$M:$M,$A69,Records!$AB:$AB,"<>Y",Records!$T:$T,C$58) | D69: =COUNTIFS(Records!$M:$M,$A69,Records!$AB:$AB,"<>Y",Records!$T:$T,D$58) | E69: =COUNTIFS(Records!$M:$M,$A69,Records!$AB:$AB,"<>Y",Records!$T:$T,E$58) | F69: =COUNTIFS(Records!$M:$M,$A69,Records!$AB:$AB,"<>Y",Records!$T:$T,F$58) | G69: =COUNTIFS(Records!$M:$M,$A69,Records!$AB:$AB,"<>Y",Records!$T:$T,G$58) | H69: =COUNTIFS(Records!$M:$M,$A69,Records!$AB:$AB,"<>Y",Records!$T:$T,H$58) | I69: =COUNTIFS(Records!$M:$M,$A69,Records!$AB:$AB,"<>Y",Records!$T:$T,I$58) | J69: =COUNTIFS(Records!$M:$M,$A69,Records!$AB:$AB,"<>Y") | K69: =COUNTIFS(Records!$M:$M,$A69,Records!$AB:$AB,"<>Y",Records!$Q:$Q,"Y")
A70: A12 | B70: Gender, caste, class & the city | C70: =COUNTIFS(Records!$M:$M,$A70,Records!$AB:$AB,"<>Y",Records!$T:$T,C$58) | D70: =COUNTIFS(Records!$M:$M,$A70,Records!$AB:$AB,"<>Y",Records!$T:$T,D$58) | E70: =COUNTIFS(Records!$M:$M,$A70,Records!$AB:$AB,"<>Y",Records!$T:$T,E$58) | F70: =COUNTIFS(Records!$M:$M,$A70,Records!$AB:$AB,"<>Y",Records!$T:$T,F$58) | G70: =COUNTIFS(Records!$M:$M,$A70,Records!$AB:$AB,"<>Y",Records!$T:$T,G$58) | H70: =COUNTIFS(Records!$M:$M,$A70,Records!$AB:$AB,"<>Y",Records!$T:$T,H$58) | I70: =COUNTIFS(Records!$M:$M,$A70,Records!$AB:$AB,"<>Y",Records!$T:$T,I$58) | J70: =COUNTIFS(Records!$M:$M,$A70,Records!$AB:$AB,"<>Y") | K70: =COUNTIFS(Records!$M:$M,$A70,Records!$AB:$AB,"<>Y",Records!$Q:$Q,"Y")
... A106: C18 | B106: Neighbourhood platforms & digital public space (WhatsApp, Nextdoor, RWA groups) | C106: =COUNTIFS(Records!$M:$M,$A106,Records!$AB:$AB,"<>Y",Records!$T:$T,C$58) | D106: =COUNTIFS(Records!$M:$M,$A106,Records!$AB:$AB,"<>Y",Records!$T:$T,D$58) | E106: =COUNTIFS(Records!$M:$M,$A106,Records!$AB:$AB,"<>Y",Records!$T:$T,E$58) | F106: =COUNTIFS(Records!$M:$M,$A106,Records!$AB:$AB,"<>Y",Records!$T:$T,F$58) | G106: =COUNTIFS(Records!$M:$M,$A106,Records!$AB:$AB,"<>Y",Records!$T:$T,G$58) | H106: =COUNTIFS(Records!$M:$M,$A106,Records!$AB:$AB,"<>Y",Records!$T:$T,H$58) | I106: =COUNTIFS(Records!$M:$M,$A106,Records!$AB:$AB,"<>Y",Records!$T:$T,I$58) | J106: =COUNTIFS(Records!$M:$M,$A106,Records!$AB:$AB,"<>Y") | K106: =COUNTIFS(Records!$M:$M,$A106,Records!$AB:$AB,"<>Y",Records!$Q:$Q,"Y")
B107: All themes | C107: =SUM(C59:C106) | D107: =SUM(D59:D106) | E107: =SUM(E59:E106) | F107: =SUM(F59:F106) | G107: =SUM(G59:G106) | H107: =SUM(H59:H106) | I107: =SUM(I59:I106) | J107: =SUM(J59:J106) | K107: =SUM(K59:K106)
A110: Theme × period (publication year)
A111: Theme | B111: Name | C111: 2010–14 | D111: 2015–19 | E111: 2020–26 | F111: Before 2010 | G111: Total
A112: A1 | B112: Urban governance, decentralisation & municipal finance | C112: =COUNTIFS(Records!$M:$M,$A112,Records!$AB:$AB,"<>Y",Records!$C:$C,">=2010",Records!$C:$C,"<=2014") | D112: =COUNTIFS(Records!$M:$M,$A112,Records!$AB:$AB,"<>Y",Records!$C:$C,">=2015",Records!$C:$C,"<=2019") | E112: =COUNTIFS(Records!$M:$M,$A112,Records!$AB:$AB,"<>Y",Records!$C:$C,">=2020",Records!$C:$C,"<=2026") | F112: =COUNTIFS(Records!$M:$M,$A112,Records!$AB:$AB,"<>Y",Records!$C:$C,"<2010") | G112: =COUNTIFS(Records!$M:$M,$A112,Records!$AB:$AB,"<>Y")
A113: A2 | B113: Planning, master plans & land-use regulation | C113: =COUNTIFS(Records!$M:$M,$A113,Records!$AB:$AB,"<>Y",Records!$C:$C,">=2010",Records!$C:$C,"<=2014") | D113: =COUNTIFS(Records!$M:$M,$A113,Records!$AB:$AB,"<>Y",Records!$C:$C,">=2015",Records!$C:$C,"<=2019") | E113: =COUNTIFS(Records!$M:$M,$A113,Records!$AB:$AB,"<>Y",Records!$C:$C,">=2020",Records!$C:$C,"<=2026") | F113: =COUNTIFS(Records!$M:$M,$A113,Records!$AB:$AB,"<>Y",Records!$C:$C,"<2010") | G113: =COUNTIFS(Records!$M:$M,$A113,Records!$AB:$AB,"<>Y")
A114: A3 | B114: Housing, informality & slums | C114: =COUNTIFS(Records!$M:$M,$A114,Records!$AB:$AB,"<>Y",Records!$C:$C,">=2010",Records!$C:$C,"<=2014") | D114: =COUNTIFS(Records!$M:$M,$A114,Records!$AB:$AB,"<>Y",Records!$C:$C,">=2015",Records!$C:$C,"<=2019") | E114: =COUNTIFS(Records!$M:$M,$A114,Records!$AB:$AB,"<>Y",Records!$C:$C,">=2020",Records!$C:$C,"<=2026") | F114: =COUNTIFS(Records!$M:$M,$A114,Records!$AB:$AB,"<>Y",Records!$C:$C,"<2010") | G114: =COUNTIFS(Records!$M:$M,$A114,Records!$AB:$AB,"<>Y")
A115: A4 | B115: Eviction, resettlement & displacement | C115: =COUNTIFS(Records!$M:$M,$A115,Records!$AB:$AB,"<>Y",Records!$C:$C,">=2010",Records!$C:$C,"<=2014") | D115: =COUNTIFS(Records!$M:$M,$A115,Records!$AB:$AB,"<>Y",Records!$C:$C,">=2015",Records!$C:$C,"<=2019") | E115: =COUNTIFS(Records!$M:$M,$A115,Records!$AB:$AB,"<>Y",Records!$C:$C,">=2020",Records!$C:$C,"<=2026") | F115: =COUNTIFS(Records!$M:$M,$A115,Records!$AB:$AB,"<>Y",Records!$C:$C,"<2010") | G115: =COUNTIFS(Records!$M:$M,$A115,Records!$AB:$AB,"<>Y")
A116: A5 | B116: Land, peri-urban & extended urbanisation | C116: =COUNTIFS(Records!$M:$M,$A116,Records!$AB:$AB,"<>Y",Records!$C:$C,">=2010",Records!$C:$C,"<=2014") | D116: =COUNTIFS(Records!$M:$M,$A116,Records!$AB:$AB,"<>Y",Records!$C:$C,">=2015",Records!$C:$C,"<=2019") | E116: =COUNTIFS(Records!$M:$M,$A116,Records!$AB:$AB,"<>Y",Records!$C:$C,">=2020",Records!$C:$C,"<=2026") | F116: =COUNTIFS(Records!$M:$M,$A116,Records!$AB:$AB,"<>Y",Records!$C:$C,"<2010") | G116: =COUNTIFS(Records!$M:$M,$A116,Records!$AB:$AB,"<>Y")
A117: A6 | B117: Small towns, census towns & secondary cities | C117: =COUNTIFS(Records!$M:$M,$A117,Records!$AB:$AB,"<>Y",Records!$C:$C,">=2010",Records!$C:$C,"<=2014") | D117: =COUNTIFS(Records!$M:$M,$A117,Records!$AB:$AB,"<>Y",Records!$C:$C,">=2015",Records!$C:$C,"<=2019") | E117: =COUNTIFS(Records!$M:$M,$A117,Records!$AB:$AB,"<>Y",Records!$C:$C,">=2020",Records!$C:$C,"<=2026") | F117: =COUNTIFS(Records!$M:$M,$A117,Records!$AB:$AB,"<>Y",Records!$C:$C,"<2010") | G117: =COUNTIFS(Records!$M:$M,$A117,Records!$AB:$AB,"<>Y")
A118: A7 | B118: Urban infrastructure (water, sanitation, energy) & infrastructural citizenship | C118: =COUNTIFS(Records!$M:$M,$A118,Records!$AB:$AB,"<>Y",Records!$C:$C,">=2010",Records!$C:$C,"<=2014") | D118: =COUNTIFS(Records!$M:$M,$A118,Records!$AB:$AB,"<>Y",Records!$C:$C,">=2015",Records!$C:$C,"<=2019") | E118: =COUNTIFS(Records!$M:$M,$A118,Records!$AB:$AB,"<>Y",Records!$C:$C,">=2020",Records!$C:$C,"<=2026") | F118: =COUNTIFS(Records!$M:$M,$A118,Records!$AB:$AB,"<>Y",Records!$C:$C,"<2010") | G118: =COUNTIFS(Records!$M:$M,$A118,Records!$AB:$AB,"<>Y")
A119: A8 | B119: Mobility & transport (social science) | C119: =COUNTIFS(Records!$M:$M,$A119,Records!$AB:$AB,"<>Y",Records!$C:$C,">=2010",Records!$C:$C,"<=2014") | D119: =COUNTIFS(Records!$M:$M,$A119,Records!$AB:$AB,"<>Y",Records!$C:$C,">=2015",Records!$C:$C,"<=2019") | E119: =COUNTIFS(Records!$M:$M,$A119,Records!$AB:$AB,"<>Y",Records!$C:$C,">=2020",Records!$C:$C,"<=2026") | F119: =COUNTIFS(Records!$M:$M,$A119,Records!$AB:$AB,"<>Y",Records!$C:$C,"<2010") | G119: =COUNTIFS(Records!$M:$M,$A119,Records!$AB:$AB,"<>Y")
A120: A9 | B120: Public space, publicness & the street | C120: =COUNTIFS(Records!$M:$M,$A120,Records!$AB:$AB,"<>Y",Records!$C:$C,">=2010",Records!$C:$C,"<=2014") | D120: =COUNTIFS(Records!$M:$M,$A120,Records!$AB:$AB,"<>Y",Records!$C:$C,">=2015",Records!$C:$C,"<=2019") | E120: =COUNTIFS(Records!$M:$M,$A120,Records!$AB:$AB,"<>Y",Records!$C:$C,">=2020",Records!$C:$C,"<=2026") | F120: =COUNTIFS(Records!$M:$M,$A120,Records!$AB:$AB,"<>Y",Records!$C:$C,"<2010") | G120: =COUNTIFS(Records!$M:$M,$A120,Records!$AB:$AB,"<>Y")
A121: A10 | B121: Urban economy, informal work & street vending | C121: =COUNTIFS(Records!$M:$M,$A121,Records!$AB:$AB,"<>Y",Records!$C:$C,">=2010",Records!$C:$C,"<=2014") | D121: =COUNTIFS(Records!$M:$M,$A121,Records!$AB:$AB,"<>Y",Records!$C:$C,">=2015",Records!$C:$C,"<=2019") | E121: =COUNTIFS(Records!$M:$M,$A121,Records!$AB:$AB,"<>Y",Records!$C:$C,">=2020",Records!$C:$C,"<=2026") | F121: =COUNTIFS(Records!$M:$M,$A121,Records!$AB:$AB,"<>Y",Records!$C:$C,"<2010") | G121: =COUNTIFS(Records!$M:$M,$A121,Records!$AB:$AB,"<>Y")
A122: A11 | B122: Migration & the city | C122: =COUNTIFS(Records!$M:$M,$A122,Records!$AB:$AB,"<>Y",Records!$C:$C,">=2010",Records!$C:$C,"<=2014") | D122: =COUNTIFS(Records!$M:$M,$A122,Records!$AB:$AB,"<>Y",Records!$C:$C,">=2015",Records!$C:$C,"<=2019") | E122: =COUNTIFS(Records!$M:$M,$A122,Records!$AB:$AB,"<>Y",Records!$C:$C,">=2020",Records!$C:$C,"<=2026") | F122: =COUNTIFS(Records!$M:$M,$A122,Records!$AB:$AB,"<>Y",Records!$C:$C,"<2010") | G122: =COUNTIFS(Records!$M:$M,$A122,Records!$AB:$AB,"<>Y")
A123: A12 | B123: Gender, caste, class & the city | C123: =COUNTIFS(Records!$M:$M,$A123,Records!$AB:$AB,"<>Y",Records!$C:$C,">=2010",Records!$C:$C,"<=2014") | D123: =COUNTIFS(Records!$M:$M,$A123,Records!$AB:$AB,"<>Y",Records!$C:$C,">=2015",Records!$C:$C,"<=2019") | E123: =COUNTIFS(Records!$M:$M,$A123,Records!$AB:$AB,"<>Y",Records!$C:$C,">=2020",Records!$C:$C,"<=2026") | F123: =COUNTIFS(Records!$M:$M,$A123,Records!$AB:$AB,"<>Y",Records!$C:$C,"<2010") | G123: =COUNTIFS(Records!$M:$M,$A123,Records!$AB:$AB,"<>Y")
... A159: C18 | B159: Neighbourhood platforms & digital public space (WhatsApp, Nextdoor, RWA groups) | C159: =COUNTIFS(Records!$M:$M,$A159,Records!$AB:$AB,"<>Y",Records!$C:$C,">=2010",Records!$C:$C,"<=2014") | D159: =COUNTIFS(Records!$M:$M,$A159,Records!$AB:$AB,"<>Y",Records!$C:$C,">=2015",Records!$C:$C,"<=2019") | E159: =COUNTIFS(Records!$M:$M,$A159,Records!$AB:$AB,"<>Y",Records!$C:$C,">=2020",Records!$C:$C,"<=2026") | F159: =COUNTIFS(Records!$M:$M,$A159,Records!$AB:$AB,"<>Y",Records!$C:$C,"<2010") | G159: =COUNTIFS(Records!$M:$M,$A159,Records!$AB:$AB,"<>Y")
B160: All themes | C160: =SUM(C112:C159) | D160: =SUM(D112:D159) | E160: =SUM(E112:E159) | F160: =SUM(F112:F159) | G160: =SUM(G112:G159)

Sheet Growth
A1: Growth — OpenAlex-wide counts per theme (prepared in Stage 2 for the Stage 3 analysis)
A2: Source: scripts/growth_counts.py (data/raw/counts/growth_stage2.json, data/processed/growth_counts.csv). Journal articles and book chapters only (primary location in a journal, book series or ebook platform: repository-only records such as Zenodo are excluded), 2010–2026, each theme's combined query. Counts are multiplied by the theme's estimated precision (random sample of 40 from the full 2015–26 hit set, screened with the theme's rules; borderline counted at the hand keep-rate) and normalised per 10,000 Social Sciences works in the same period under the same filters. 2026 is a partial year (retrieved October 2026); the normalised shares stay comparable because the baseline is equally partial. Growth ratio = normalised share 2020–26 ÷ 2015–19. One precision estimate per theme is applied to both periods.
A4: Theme | B4: Name | C4: Precision est. | D4: Raw 2015–19 | E4: Raw 2020–26 | F4: Adj. per 10k SS 2015–19 | G4: Adj. per 10k SS 2020–26 | H4: Growth ratio | I4: SA raw 2015–19 | J4: SA raw 2020–26 | K4: SA adj. per 10k SA-SS 2015–19 | L4: SA adj. per 10k SA-SS 2020–26 | M4: SA growth ratio | N4: 2026 raw (partial)
A5: A1 | B5: Urban governance, decentralisation & municipal finance | C5: 0.406 | D5: 7489 | E5: 19570 | F5: 3.12 | G5: 5.09 | H5: 1.63 | I5: 725 | J5: 1960 | K5: 16.11 | L5: 17.81 | M5: 1.11 | N5: 3250
A6: A2 | B6: Planning, master plans & land-use regulation | C6: 0.547 | D6: 5441 | E6: 14157 | F6: 3.06 | G6: 4.96 | H6: 1.62 | I6: 223 | J6: 951 | K6: 6.68 | L6: 11.64 | M6: 1.74 | N6: 2607
A7: A3 | B7: Housing, informality & slums | C7: 0.509 | D7: 14671 | E7: 28664 | F7: 7.66 | G7: 9.34 | H7: 1.22 | I7: 2507 | J7: 4567 | K7: 69.8 | L7: 51.99 | M7: 0.74 | N7: 4012
A8: A4 | B8: Eviction, resettlement & displacement | C8: 0.518 | D8: 1997 | E8: 4796 | F8: 1.06 | G8: 1.59 | H8: 1.5 | I8: 248 | J8: 560 | K8: 7.02 | L8: 6.49 | M8: 0.92 | N8: 691
A9: A5 | B9: Land, peri-urban & extended urbanisation | C9: 0.325 | D9: 8487 | E9: 21084 | F9: 2.83 | G9: 4.39 | H9: 1.55 | I9: 995 | J9: 2542 | K9: 17.71 | L9: 18.49 | M9: 1.04 | N9: 4305
A10: A6 | B10: Small towns, census towns & secondary cities | C10: 0.316 | D10: 2328 | E10: 5748 | F10: 0.75 | G10: 1.16 | H10: 1.55 | I10: 215 | J10: 477 | K10: 3.72 | L10: 3.37 | M10: 0.91 | N10: 989
A11: A7 | B11: Urban infrastructure (water, sanitation, energy) & infrastructural citizenship | C11: 0.405 | D11: 3767 | E11: 10091 | F11: 1.57 | G11: 2.62 | H11: 1.67 | I11: 603 | J11: 1571 | K11: 13.37 | L11: 14.24 | M11: 1.07 | N11: 2083
A12: A8 | B12: Mobility & transport (social science) | C12: 0.598 | D12: 1924 | E12: 6064 | F12: 1.18 | G12: 2.32 | H12: 1.97 | I12: 225 | J12: 674 | K12: 7.36 | L12: 9.02 | M12: 1.23 | N12: 1166
A13: A9 | B13: Public space, publicness & the street | C13: 0.416 | D13: 6701 | E13: 16570 | F13: 2.86 | G13: 4.41 | H13: 1.54 | I13: 255 | J13: 765 | K13: 5.8 | L13: 7.12 | M13: 1.23 | N13: 2600
A14: A10 | B14: Urban economy, informal work & street vending | C14: 0.549 | D14: 2442 | E14: 6301 | F14: 1.38 | G14: 2.22 | H14: 1.61 | I14: 354 | J14: 1081 | K14: 10.64 | L14: 13.28 | M14: 1.25 | N14: 969
A15: A11 | B15: Migration & the city | C15: 0.629 | D15: 2315 | E15: 4515 | F15: 1.49 | G15: 1.82 | H15: 1.22 | I15: 276 | J15: 784 | K15: 9.5 | L15: 11.04 | M15: 1.16 | N15: 597
A16: A12 | B16: Gender, caste, class & the city | C16: 0.619 | D16: 1657 | E16: 3844 | F16: 1.05 | G16: 1.52 | H16: 1.45 | I16: 711 | J16: 2027 | K16: 24.07 | L16: 28.06 | M16: 1.17 | N16: 652
... A33: B13 | B33: Mobile phones & everyday digital life | C33: 0.349 | D33: 5300 | E33: 12395 | F33: 1.9 | G33: 2.77 | H33: 1.46 | I33: 944 | J33: 2872 | K33: 18.04 | L33: 22.44 | M33: 1.24 | N33: 1861
A34: B14 | B34: Generative AI & society | C34: 0.632 | D34: 31 | E34: 61291 | F34: 0.02 | G34: 24.82 | H34: 1241 | I34: 0 | J34: 1343 | K34: 0 | L34: 19 | N34: 28713
A35: C1 | B35: Smart cities & smart urbanism | C35: 0.428 | D35: 2782 | E35: 12673 | F35: 1.22 | G35: 3.47 | H35: 2.84 | I35: 234 | J35: 894 | K35: 5.48 | L35: 8.55 | M35: 1.56 | N35: 2637
A36: C2 | B36: Platform urbanism | C36: 0.327 | D36: 212 | E36: 2374 | F36: 0.07 | G36: 0.5 | H36: 7.14 | I36: 12 | J36: 242 | K36: 0.21 | L36: 1.77 | M36: 8.43 | N36: 700
A37: C3 | B37: Digital geographies & code/space | C37: 0.287 | D37: 430 | E37: 627 | F37: 0.13 | G37: 0.12 | H37: 0.92 | I37: 6 | J37: 11 | K37: 0.09 | L37: 0.07 | M37: 0.78 | N37: 87
A38: C4 | B38: Urban informatics & urban computing | C38: 0.434 | D38: 847 | E38: 3257 | F38: 0.38 | G38: 0.9 | H38: 2.37 | I38: 17 | J38: 86 | K38: 0.4 | L38: 0.83 | M38: 2.07 | N38: 601
A39: C5 | B39: Urban data governance & data justice in cities | C39: 0.341 | D39: 233 | E39: 1414 | F39: 0.08 | G39: 0.31 | H39: 3.88 | I39: 7 | J39: 79 | K39: 0.13 | L39: 0.6 | M39: 4.62 | N39: 542
A40: C6 | B40: Urban surveillance, policing & biometrics in public space | C40: 0.269 | D40: 831 | E40: 3460 | F40: 0.23 | G40: 0.6 | H40: 2.61 | I40: 29 | J40: 269 | K40: 0.43 | L40: 1.62 | M40: 3.77 | N40: 754
A41: C7 | B41: Algorithmic & automated urban governance, municipal AI / GenAI | C41: 0.394 | D41: 102 | E41: 2435 | F41: 0.04 | G41: 0.61 | H41: 15.25 | I41: 35 | J41: 201 | K41: 0.76 | L41: 1.77 | M41: 2.33 | N41: 964
A42: C8 | B42: City-level DPI & urban e-government | C42: 0.56 | D42: 804 | E42: 2927 | F42: 0.46 | G42: 1.05 | H42: 2.28 | I42: 70 | J42: 229 | K42: 2.14 | L42: 2.87 | M42: 1.34 | N42: 637
A43: C9 | B43: Digital mobility (ride-hailing, MaaS, digital ticketing, transit apps) | C43: 0.415 | D43: 962 | E43: 5355 | F43: 0.41 | G43: 1.42 | H43: 3.46 | I43: 17 | J43: 221 | K43: 0.39 | L43: 2.05 | M43: 5.26 | N43: 942
A44: C10 | B44: Proptech, housing platforms & short-term rentals | C44: 0.555 | D44: 1419 | E44: 4040 | F44: 0.81 | G44: 1.44 | H44: 1.78 | I44: 17 | J44: 70 | K44: 0.52 | L44: 0.87 | M44: 1.67 | N44: 503
A45: C11 | B45: Digital payments in urban economies (QR, UPI, mobile money) | C45: 0.275 | D45: 1036 | E45: 5136 | F45: 0.29 | G45: 0.9 | H45: 3.1 | I45: 130 | J45: 1854 | K45: 1.95 | L45: 11.39 | M45: 5.84 | N45: 1610
A46: C12 | B46: Civic tech, e-participation & digital urban publics | C46: 0.306 | D46: 293 | E46: 956 | F46: 0.09 | G46: 0.19 | H46: 2.11 | I46: 4 | J46: 59 | K46: 0.07 | L46: 0.4 | M46: 5.71 | N46: 226
... A52: C18 | B52: Neighbourhood platforms & digital public space (WhatsApp, Nextdoor, RWA groups) | C52: 0.095 | D52: 545 | E52: 5524 | F52: 0.05 | G52: 0.34 | H52: 6.8 | I52: 43 | J52: 538 | K52: 0.22 | L52: 1.14 | M52: 5.18 | N52: 1101
A55: Per-year raw counts (same filters)
A56: Theme | B56: Scope | C56: 2010 | D56: 2011 | E56: 2012 | F56: 2013 | G56: 2014 | H56: 2015 | I56: 2016 | J56: 2017 | K56: 2018 | L56: 2019 | M56: 2020 | N56: 2021 | O56: 2022 | P56: 2023 | Q56: 2024 | R56: 2025 | S56: 2026
A57: SS baseline | B57: global | C57: 1547954 | D57: 1587476 | E57: 1688628 | F57: 1808955 | G57: 1892326 | H57: 1947786 | I57: 1895710 | J57: 1906801 | K57: 1960396 | L57: 2033271 | M57: 2247963 | N57: 2182575 | O57: 2087966 | P57: 2256542 | Q57: 2409184 | R57: 2586439 | S57: 1846410
A58: SS baseline | B58: south_asia | C58: 15924 | D58: 19623 | E58: 22261 | F58: 25201 | G58: 26085 | H58: 28727 | I58: 31989 | J58: 38074 | K58: 39570 | L58: 44365 | M58: 52278 | N58: 56283 | O58: 54815 | P58: 61187 | Q58: 69072 | R58: 84242 | S58: 69054
A59: A1 | B59: global | C59: 517 | D59: 603 | E59: 753 | F59: 891 | G59: 941 | H59: 1081 | I59: 1328 | J59: 1494 | K59: 1628 | L59: 1958 | M59: 2234 | N59: 2303 | O59: 2526 | P59: 2594 | Q59: 3026 | R59: 3637 | S59: 3250
A60: A1 | B60: south_asia | C60: 45 | D60: 49 | E60: 90 | F60: 93 | G60: 105 | H60: 126 | I60: 135 | J60: 148 | K60: 145 | L60: 171 | M60: 238 | N60: 213 | O60: 224 | P60: 219 | Q60: 268 | R60: 369 | S60: 429
A61: A2 | B61: global | C61: 587 | D61: 666 | E61: 770 | F61: 889 | G61: 911 | H61: 890 | I61: 917 | J61: 1198 | K61: 1151 | L61: 1285 | M61: 1405 | N61: 1580 | O61: 1468 | P61: 1723 | Q61: 2277 | R61: 3097 | S61: 2607
A62: A2 | B62: south_asia | C62: 7 | D62: 18 | E62: 31 | F62: 27 | G62: 27 | H62: 31 | I62: 42 | J62: 39 | K62: 64 | L62: 47 | M62: 79 | N62: 81 | O62: 88 | P62: 96 | Q62: 142 | R62: 252 | S62: 213
A63: A3 | B63: global | C63: 1281 | D63: 1505 | E63: 1862 | F63: 2087 | G63: 2243 | H63: 2361 | I63: 2664 | J63: 3008 | K63: 3272 | L63: 3366 | M63: 3811 | N63: 3931 | O63: 3730 | P63: 3891 | Q63: 4325 | R63: 4964 | S63: 4012
A64: A3 | B64: south_asia | C64: 171 | D64: 183 | E64: 291 | F64: 369 | G64: 352 | H64: 428 | I64: 526 | J64: 497 | K64: 534 | L64: 522 | M64: 683 | N64: 663 | O64: 588 | P64: 597 | Q64: 599 | R64: 780 | S64: 657
A65: A4 | B65: global | C65: 123 | D65: 169 | E65: 158 | F65: 221 | G65: 221 | H65: 323 | I65: 332 | J65: 402 | K65: 454 | L65: 486 | M65: 641 | N65: 679 | O65: 627 | P65: 688 | Q65: 651 | R65: 819 | S65: 691
A66: A4 | B66: south_asia | C66: 10 | D66: 14 | E66: 25 | F66: 33 | G66: 32 | H66: 38 | I66: 52 | J66: 47 | K66: 47 | L66: 64 | M66: 68 | N66: 48 | O66: 78 | P66: 87 | Q66: 82 | R66: 105 | S66: 92
A67: A5 | B67: global | C67: 854 | D67: 923 | E67: 1108 | F67: 1223 | G67: 1341 | H67: 1286 | I67: 1499 | J67: 1710 | K67: 1912 | L67: 2080 | M67: 2294 | N67: 2516 | O67: 2452 | P67: 2633 | Q67: 2894 | R67: 3990 | S67: 4305
... A154: C18 | B154: south_asia | C154: 1 | D154: 2 | E154: 0 | F154: 0 | G154: 2 | H154: 9 | I154: 1 | J154: 10 | K154: 7 | L154: 16 | M154: 60 | N154: 73 | O154: 69 | P154: 63 | Q154: 59 | R154: 102 | S154: 112

Sheet Emerging terms
A1: Emerging terms — Stage 3
A2: Top 30 keywords/topics whose frequency rose fastest from 2018–21 to 2022–26, with counts and example papers. To be filled in Stage 3.
A4: Rank | B4: Term | C4: Count 2018–21 | D4: Count 2022–26 | E4: Growth | F4: Themes | G4: Example paper 1 (ID) | H4: Example paper 2 (ID) | I4: Example paper 3 (ID)

Sheet Landmarks by theme
A1: Records found in a theme's 'landmarks' slice (top cited works for the query, any year) and kept after screening; repository-only records are excluded; sorted by theme, then citations.
A2: ID | B2: Primary theme | C2: Title | D2: Year | E2: Authors | F2: Venue | G2: Cited-by count | H2: DOI | I2: Region | J2: Places studied | K2: Found in
A3: LM00001 | B3: A1 | C3: From Managerialism to Entrepreneurialism: The Transformation in Urban Governance in Late Capitalism | D3: 1989 | E3: David Harvey | F3: Geografiska Annaler Series B Human Geography | G3: 4713 | H3: 10.1080/04353684.1989.11879583 | I3: Not place-specific | K3: A1:landmarks
A4: LM00002 | B4: A1 | C4: New State Spaces | D4: 2004 | E4: Neil Brenner | F4: Oxford University Press eBooks | G4: 2295 | H4: 10.1093/acprof:oso/9780199270057.001.0001 | I4: Global North | J4: Europe | K4: A1:landmarks
A5: LM00003 | B5: A1 | C5: THE DANGERS OF DECENTRALIZATION | D5: 1995 | E5: Rémy Prud’homme | F5: The World Bank Research Observer | G5: 1897 | H5: 10.1093/wbro/10.2.201 | I5: Not place-specific | K5: A1:landmarks
A6: LM00004 | B6: A1 | C6: New State Spaces: Urban Governance and the Rescaling of Statehood | D6: 2004 | E6: Neil Brenner | F6: OUP Catalogue | G6: 1885 | I6: Not place-specific | K6: A1:landmarks
A7: LM00005 | B7: A1 | C7: Liberalism, Neoliberalism, and Urban Governance: A State–Theoretical Perspective | D7: 2002 | E7: Bob Jessop | F7: Antipode | G7: 1460 | H7: 10.1111/1467-8330.00250 | I7: Not place-specific | K7: A1:landmarks
A8: LM00006 | B8: A1 | C8: Globalisation as Reterritorialisation: The Re-scaling of Urban Governance in the European Union | D8: 1999 | E8: Neil Brenner | F8: Urban Studies | G8: 1134 | H8: 10.1080/0042098993466 | I8: Global North | J8: Europe; European | K8: A1:landmarks
A9: LM00007 | B9: A1 | C9: Spaces of Neoliberalism | D9: 2002 | E9: Neil 1969- Brenner; Nik Theodore | F9: Wiley eBooks | G9: 1059 | H9: 10.1002/9781444397499 | I9: Global North | J9: Canada; Chicago; Europe; Manchester; New York; Toronto; United Kingdom | K9: A1:landmarks
A10: LM00008 | B10: A1 | C10: The Political Economy of Democratic Decentralization | D10: 1999 | E10: James Manor | F10: World Bank, Washington, DC eBooks | G10: 967 | H10: 10.1596/0-8213-4470-6 | I10: Multi-region | J10: Africa; African; Bangladesh; Brazil; Central AsiaJournal; China; Ethiopia; Ghana; India; Indonesia; Italy; Lagos; Malawi; Nigeria; Norway; Pakistan; Sierra Leone; South Africa; South AsiaInternational; South Asian; South Korea; Southeast AsiaEnvironment; Thailand; United Kingdom; United States; Uruguay; West Bengal; Zambia | K10: A1:landmarks; A7:landmarks
A11: LM00009 | B11: A1 | C11: Decentralized Authoritarianism in China | D11: 2008 | E11: Pierre F. Landry | F11: Cambridge University Press eBooks | G11: 847 | H11: 10.1017/cbo9780511510243 | I11: China & East Asia | J11: China | K11: A1:landmarks
A12: LM00010 | B12: A1 | C12: An inconvenient cost: The effects of climate change on municipal bonds | D12: 2019 | E12: Marcus Painter | F12: Journal of Financial Economics | G12: 823 | H12: 10.1016/j.jfineco.2019.06.006 | I12: Not place-specific | K12: A1:landmarks
A13: LM00011 | B13: A1 | C13: Urban Economics and Real Estate Markets | D13: 1995 | E13: Denise DiPasquale; William C. Wheaton | G13: 785 | I13: Not place-specific | K13: A1:landmarks
A14: LM00012 | B14: A1 | C14: Roads, Railroads, and Decentralization of Chinese Cities | D14: 2017 | E14: Nathaniel Brandt Baum-Snow; Loren Brandt; J. Vernon Henderson; Matthew A. Turner; Qinghua Zhang | F14: The Review of Economics and Statistics | G14: 761 | H14: 10.1162/rest_a_00660 | I14: China & East Asia | J14: China | K14: A1:landmarks
A15: LM00013 | B15: A1 | C15: Building Institutional Capacity through Collaborative Approaches to Urban Planning | D15: 1998 | E15: Patsy Healey | F15: Environment and Planning A Economy and Space | G15: 704 | H15: 10.1068/a301531 | I15: Global North | J15: Europe; United Kingdom | K15: A1:landmarks
A16: LM00014 | B16: A1 | C16: Rethinking Decentralization in Developing Countries | D16: 1998 | E16: Jennie I. Litvack; Junaid Aḥmad; Richard Miller Bird | F16: World Bank, Washington, DC eBooks | G16: 634 | H16: 10.1596/0-8213-4350-5 | I16: Multi-region | J16: Africa; African; Australia; Benin; Bolivia; Brazil; Burkina Faso; Chile; China; Europe; European; Ghana; Hungary; India; Indonesia; Kampala; Karnataka; Kolkata; Madhya Pradesh; Mali; Mexico; Odisha; Pakistan; Peru; Philippines; Senegal; Seoul; Southeast Asian; Tanzania; Timor-Leste; Uganda; Ukraine; United States; West Bengal | K16: A14:landmarks; A1:landmarks; A7:landmarks
A17: LM00015 | B17: A1 | C17: Does decentralization increase government responsiveness to local needs? | D17: 2003 | E17: Jean-Paul Faguet | F17: Journal of Public Economics | G17: 566 | H17: 10.1016/s0047-2727(02)00185-8 | I17: Not place-specific | K17: A1:landmarks
A18: LM00016 | B18: A1 | C18: The environment and the entrepreneurial city: searching for the urban ‘sustainability fix’ in Manchester and Leeds | D18: 2004 | E18: Aidan H. While; Andrew E. G. Jonas; David C. Gibbs | F18: International Journal of Urban and Regional Research | G18: 562 | H18: 10.1111/j.0309-1317.2004.00535.x | I18: Global North | J18: Manchester; United Kingdom | K18: A1:landmarks
A19: LM00017 | B19: A1 | C19: Du gouvernement des villes à la gouvernance urbaine | D19: 1995 | E19: Patrick Le Galès | F19: Revue française de science politique | G19: 556 | H19: 10.3406/rfsp.1995.403502 | I19: Global North | J19: France; United Kingdom; United States | K19: A1:landmarks
A20: LM00018 | B20: A1 | C20: Models of Urban Governance | D20: 1999 | E20: Jon Pierre | F20: Urban Affairs Review | G20: 515 | H20: 10.1177/10780879922183988 | I20: Global North | J20: Europe | K20: A1:landmarks
A21: LM00019 | B21: A1 | C21: Inventing Local Democracy | D21: 2000 | E21: Rebecca Neaera Abers | F21: Lynne Rienner Publishers eBooks | G21: 513 | H21: 10.1515/9781626371378 | I21: Latin America | J21: Brazil | K21: A1:landmarks
A22: LM00020 | B22: A1 | C22: European Cities | D22: 2002 | E22: Patrick Le Galès | F22: Oxford University Press eBooks | G22: 512 | H22: 10.1093/acprof:oso/9780199243570.001.0001 | I22: Global North | J22: European | K22: A1:landmarks
A23: LM00021 | B23: A1 | C23: Social Cohesion and Multilevel Urban Governance | D23: 2000 | E23: Ade Kearns; Ray Forrest | F23: Urban Studies | G23: 499 | H23: 10.1080/00420980050011208 | I23: Not place-specific | K23: A1:landmarks
A24: LM00022 | B24: A1 | C24: Urban governance and the production of new state spaces in western Europe, 1960–2000 | D24: 2004 | E24: Neil Brenner | F24: Review of International Political Economy | G24: 491 | H24: 10.1080/0969229042000282864 | I24: Global North | J24: Europe; European | K24: A1:landmarks
A25: LM00023 | B25: A1 | C25: Selling City Futures: The Financialization of Urban Redevelopment Policy | D25: 2010 | E25: Rachel N. Weber | F25: Economic Geography | G25: 473 | H25: 10.1111/j.1944-8287.2010.01077.x | I25: Global North | J25: Chicago; United States | K25: A1:landmarks
A26: LM00024 | B26: A1 | C26: Decentralization, Local Government, and the Welfare State | D26: 2007 | E26: Jefferey M. Sellers; Anders Lidström | F26: Governance | G26: 463 | H26: 10.1111/j.1468-0491.2007.00374.x | I26: Not place-specific | K26: A1:landmarks
A27: LM00025 | B27: A1 | C27: Do Political Parties Matter? Evidence from U.S. Cities* | D27: 2009 | E27: Fernando V. Ferreira; Joseph Gyourko | F27: The Quarterly Journal of Economics | G27: 439 | H27: 10.1162/qjec.2009.124.1.399 | I27: Global North | J27: United States | K27: A1:landmarks
A28: LM00026 | B28: A1 | C28: Source Separation and Decentralization for Wastewater Management | D28: 2013 | E28: Tove A. Larsen; Kai M. Udert; Judit Lienert | F28: IWA Publishing eBooks | G28: 433 | H28: 10.2166/9781780401072 | I28: Not place-specific | K28: A1:landmarks
A29: LM00027 | B29: A1 | C29: China's Changing Urban Governance in the Transition Towards a More Market-oriented Economy | D29: 2002 | E29: Fulong Wu | F29: Urban Studies | G29: 431 | H29: 10.1080/00420980220135491 | I29: China & East Asia | J29: China | K29: A1:landmarks
A30: LM00028 | B30: A1 | C30: China's Local Political Budget Cycles | D30: 2009 | E30: Gang Guo | F30: American Journal of Political Science | G30: 429 | H30: 10.1111/j.1540-5907.2009.00390.x | I30: China & East Asia | J30: China | K30: A1:landmarks
A31: LM00029 | B31: A1 | C31: Decentralisation, participation and accountability in Sahelian forestry: legal instruments of political-administrative control | D31: 1999 | E31: Jesse Ribot | F31: Africa | G31: 423 | H31: 10.2307/1161076 | I31: Africa | J31: Burkina Faso; Mali | K31: A1:landmarks
A32: LM00031 | B32: A1 | C32: Resilience, ecology and adaptation in the experimental city | D32: 2011 | E32: James Evans | F32: Transactions of the Institute of British Geographers | G32: 410 | H32: 10.1111/j.1475-5661.2010.00420.x | I32: Global North | J32: United States | K32: A1:landmarks; A7:landmarks
A33: LM00032 | B33: A1 | C33: Financial Intermediation and the Costs of Trading in an Opaque Market | D33: 2006 | E33: Richard C. Green; Burton Hollifield; Norman Schürhoff | F33: Review of Financial Studies | G33: 408 | H33: 10.1093/rfs/hhl012 | I33: Not place-specific | K33: A1:landmarks
A34: LM00033 | B34: A1 | C34: Decentralization of health systems in Ghana, Zambia, Uganda and the Philippines: a comparative analysis of decision space | D34: 2002 | E34: Thomas John Bossert | F34: Health Policy and Planning | G34: 406 | H34: 10.1093/heapol/17.1.14 | I34: Multi-region | J34: Ghana; Philippines; Uganda; Zambia | K34: A1:landmarks
A35: LM00034 | B35: A1 | C35: Urban Governance and the Politics of Climate change | D35: 2017 | E35: Vanesa Castán Broto | F35: World Development | G35: 404 | H35: 10.1016/j.worlddev.2016.12.031 | I35: Not place-specific | K35: A1:landmarks
A36: LM00035 | B36: A1 | C36: Telecommunications and Organizational Decentralization | D36: 1975 | E36: Jack M. Nilles | F36: IRE Transactions on Communications Systems | G36: 400 | H36: 10.1109/tcom.1975.1092687 | I36: Not place-specific | K36: A1:landmarks
A37: LM00036 | B37: A1 | C37: Social Innovation and Civil Society in Urban Governance: Strategies for an Inclusive City | D37: 2005 | E37: Julia Gerometta; Hartmut Häußermann; Giulia Longo | F37: Urban Studies | G37: 398 | H37: 10.1080/00420980500279851 | I37: Not place-specific | K37: A1:landmarks
A38: LM00037 | B38: A1 | C38: Adaptive urban governance: new challenges for the second generation of urban adaptation strategies to climate change | D38: 2010 | E38: Joern Birkmann; Matthias Garschagen; Frauke Kraas; Nguyen Quang | F38: Sustainability Science | G38: 396 | H38: 10.1007/s11625-010-0111-3 | I38: Not place-specific | K38: A1:landmarks
A39: LM00038 | B39: A1 | C39: The reform of intergovernmental fiscal relations in developing and emerging market economies | D39: 1994 | E39: Anwar Ali Shah | F39: World Bank, Washington, DC eBooks | G39: 389 | H39: 10.1596/0-8213-2836-0 | I39: Multi-region | J39: Africa; Argentina; Benin; Bolivia; Brazil; China; European; Indonesia; Ireland; Latin AmericaLatin; Latin AmericaSSRN; Latin American; Mali; Mexico; Pakistan; Philippines; Poland; South Korea; Switzerland; Vietnam | K39: A1:landmarks
A40: LM00039 | B40: A1 | C40: Decentralisation in Africa: goals, dimensions, myths and challenges | D40: 2003 | E40: Paul Smoke | F40: Public Administration and Development | G40: 384 | H40: 10.1002/pad.255 | I40: Africa | J40: Africa | K40: A1:landmarks
A41: LM00040 | B41: A1 | C41: Transforming governance: Challenges of institutional adaptation and a new politics of space1 | D41: 2006 | E41: Patsy Healey | F41: European Planning Studies | G41: 379 | H41: 10.1080/09654310500420792 | I41: Global North | J41: Europe | K41: A1:landmarks
A42: LM01783 | B42: A10 | C42: Waste Mismanagement in Developing Countries: A Review of Global Issues | D42: 2019 | E42: Navarro Ferronato; Vincenzo Torretta | F42: International Journal of Environmental Research and Public Health | G42: 2296 | H42: 10.3390/ijerph16061060 | I42: Not place-specific | K42: A10:landmarks
A43: LM01784 | B43: A10 | C43: Women and men in the informal economy: a statistical picture | D43: 2018 | E43: Florence Bonnet | G43: 1584 | I43: Not place-specific | K43: A10:landmarks
A44: LM01785 | B44: A10 | C44: Tools of the trade: the socio-technology of arbitrage in a Wall Street trading room | D44: 2004 | E44: Daniel Beunza | F44: Industrial and Corporate Change | G44: 571 | H44: 10.1093/icc/dth015 | I44: Not place-specific | K44: A10:landmarks
A45: LM01786 | B45: A10 | C45: Informal sector or petty commodity production: Dualism or dependence in urban development? | D45: 1978 | E45: Caroline O. N. Moser | F45: World Development | G45: 551 | H45: 10.1016/0305-750x(78)90062-1 | I45: Not place-specific | K45: A10:landmarks
A46: LM01787 | B46: A10 | C46: Footloose Labour | D46: 1996 | E46: Jan Breman | F46: Cambridge University Press eBooks | G46: 532 | H46: 10.1017/cbo9781139171076 | I46: South Asia | J46: Gujarat; India; South Asia | K46: A10:landmarks<-A12
A47: LM01788 | B47: A10 | C47: Street vending and public policy: a global review | D47: 2000 | E47: Ray Bromley | F47: International Journal of Sociology and Social Policy | G47: 404 | H47: 10.1108/01443330010789052 | I47: Not place-specific | K47: A10:landmarks
A48: LM01789 | B48: A10 | C48: Is Informal Normal ? | D48: 2009 | E48: Johannes Jütting; Juan Ramón de Laiglesia | F48: Development Centre studies | G48: 400 | H48: 10.1787/9789264059245-en | I48: China & East Asia | J48: Beijing; China | K48: A10:landmarks
A49: LM01790 | B49: A10 | C49: Informal employment in developing countries | D49: 2011 | E49: Isabel Günther; Andrey Launov | F49: Journal of Development Economics | G49: 370 | H49: 10.1016/j.jdeveco.2011.01.001 | I49: Not place-specific | K49: A10:landmarks
A50: LM01791 | B50: A10 | C50: Competing Perspectives on the Latin American Informal Sector | D50: 1993 | E50: Alejandro Portes; Richard Y. Schauffler | F50: Population and Development Review | G50: 359 | H50: 10.2307/2938384 | I50: Latin America | J50: Latin America; Latin American | K50: A10:landmarks; A10:landmarks<-A11
A51: LM01792 | B51: A10 | C51: Forbearance | D51: 2016 | E51: Alisha C. Holland | F51: American Political Science Review | G51: 357 | H51: 10.1017/s0003055416000083 | I51: Latin America | J51: Latin America | K51: A10:landmarks
A52: LM01793 | B52: A10 | C52: The urban informal sector | D52: 1976 | E52: Dipak Mazumdar | F52: World Development | G52: 350 | H52: 10.1016/0305-750x(76)90047-4 | I52: Not place-specific | K52: A10:landmarks
A53: LM01794 | B53: A10 | C53: Forbearance as Redistribution | D53: 2017 | E53: Alisha C. Holland | F53: Cambridge University Press eBooks | G53: 347 | H53: 10.1017/9781316795613 | I53: Not place-specific | K53: A10:landmarks
A54: LM01795 | B54: A10 | C54: Waste pickers and cities | D54: 2016 | E54: Sônia Maria Dias | F54: Environment and Urbanization | G54: 345 | H54: 10.1177/0956247816657302 | I54: Not place-specific | K54: A10:landmarks
A55: LM01796 | B55: A10 | C55: Urban Livelihoods: A People-centred Approach to Reducing Poverty | D55: 2014 | E55: Carole Rakodi; Tony Lloyd‐Jones | G55: 344 | I55: Not place-specific | K55: A10:landmarks
A56: LM01797 | B56: A10 | C56: Emerging trends in informal sector recycling in developing and transition countries | D56: 2013 | E56: Chukwunonye Ezeah; Jak A. Fazakerley; Clive L. Roberts | F56: Waste Management | G56: 316 | H56: 10.1016/j.wasman.2013.06.020 | I56: Not place-specific | K56: A10:landmarks
A57: LM01798 | B57: A10 | C57: Is informal normal? : towards more and better jobs in developing countries | D57: 2009 | E57: Johannes Jütting | F57: OECD eBooks | G57: 299 | I57: Multi-region | J57: Africa; Cairo; Calcutta; Moscow; South Asia; sub-Saharan | K57: A10:landmarks
A58: LM01800 | B58: A10 | C58: Street vendors, and postmodernity: conflict and compromise in the global economy | D58: 2000 | E58: John C. Cross | F58: International Journal of Sociology and Social Policy | G58: 288 | H58: 10.1108/01443330010789061 | I58: Not place-specific | K58: A10:landmarks
A59: LM01801 | B59: A10 | C59: Revanchist Urbanism Heads South: The Regulation of Indigenous Beggars and Street Vendors in Ecuador | D59: 2007 | E59: Kate Swanson | F59: Antipode | G59: 282 | H59: 10.1111/j.1467-8330.2007.00548.x | I59: Latin America | J59: Ecuador; Quito | K59: A10:landmarks
A60: LM01802 | B60: A10 | C60: Street vendors and cities | D60: 2016 | E60: Sally Roever; Caroline Skinner | F60: Environment and Urbanization | G60: 280 | H60: 10.1177/0956247816653898 | I60: Multi-region | J60: Ahmedabad; India; Lima; Peru | K60: A10:landmarks; A4:landmarks
A61: LM01803 | B61: A10 | C61: Out of the shadows : political action and the informal economy in Latin America | D61: 2006 | E61: Patricia Fernández‐Kelly; Jon Shefner | F61: Pennsylvania State University Press eBooks | G61: 276 | I61: Latin America | J61: Argentina; Brazil; Latin America; Mexico | K61: A10:landmarks
A62: LM01804 | B62: A10 | C62: Resisting the Entrepreneurial City: Street Vendors' Struggle in Mexico City's Historic Center | D62: 2009 | E62: Verónica Crossa | F62: International Journal of Urban and Regional Research | G62: 272 | H62: 10.1111/j.1468-2427.2008.00823.x | I62: Latin America | J62: Mexico; Mexico City | K62: A10:landmarks
A63: LM01805 | B63: A10 | C63: Urban livelihoods—a people-centred approach to reducing poverty | D63: 2003 | E63: Florian Steinberg | F63: Habitat International | G63: 258 | H63: 10.1016/s0197-3975(03)00034-1 | I63: Not place-specific | K63: A10:landmarks
A64: LM01806 | B64: A10 | C64: The urban informal economy, local inclusion and achieving a global green transformation | D64: 2015 | E64: Donald A. Brown; Gordon McGranahan | F64: Habitat International | G64: 255 | H64: 10.1016/j.habitatint.2015.11.002 | I64: Not place-specific | K64: A10:landmarks
A65: LM01808 | B65: A10 | C65: Household waste and health risks affecting waste pickers and the environment in low- and middle-income countries | D65: 2017 | E65: Jutta Gutberlet; Sayed Mohammad Nazim Uddin | F65: International Journal of Occupational and Environmental Health | G65: 238 | H65: 10.1080/10773525.2018.1484996 | I65: Latin America | J65: Brazil | K65: A10:landmarks
A66: LM01809 | B66: A10 | C66: Informal Politics | D66: 1998 | E66: John C. Cross | F66: Stanford University Press eBooks | G66: 237 | H66: 10.1515/9780804765114 | I66: Latin America | J66: Mexico; Mexico City | K66: A10:landmarks
A67: LM01810 | B67: A10 | C67: Crisis, Informalization and the Urban Informal Sector in Sub‐Saharan Africa | D67: 1995 | E67: Kate Meagher | F67: Development and Change | G67: 236 | H67: 10.1111/j.1467-7660.1995.tb00552.x | I67: Multi-region | J67: Africa; Latin American | K67: A10:landmarks
A68: LM01811 | B68: A10 | C68: Waste Picker Organizations and Their Contribution to the Circular Economy: Two Case Studies from a Global South Perspective | D68: 2017 | E68: Jutta Gutberlet; Sebastián Carenzo; Jaan‐Henrik Kain; Adalberto Mantovani Martiniano de Azevedo | F68: Resources | G68: 229 | H68: 10.3390/resources6040052 | I68: Latin America | J68: Argentina; Brazil | K68: A10:landmarks
A69: LM01812 | B69: A10 | C69: The slowing of sub-Saharan Africa's urbanization: evidence and implications for urban livelihoods | D69: 2009 | E69: Deborah Potts | F69: Environment and Urbanization | G69: 224 | H69: 10.1177/0956247809103026 | I69: Africa | J69: Africa; African; Benin; Burkina Faso; Ivory Coast; Mali; Mozambique; Niger; Senegal; Zambia; Zimbabwe; sub-Saharan | K69: A10:landmarks; A11:landmarks
A70: LM01813 | B70: A10 | C70: Sustainable solid waste management toward an inclusive society: Integration of the informal sector | D70: 2010 | E70: Emenda Sembiring; Vilas Nitivattananon | F70: Resources Conservation and Recycling | G70: 221 | H70: 10.1016/j.resconrec.2009.12.010 | I70: Not place-specific | K70: A10:landmarks
A71: LM01814 | B71: A10 | C71: Urban Poverty and Party Populism in African Democracies | D71: 2013 | E71: Danielle Resnick | G71: 219 | H71: 10.1017/cbo9781139568265 | I71: Africa | J71: Africa; African; Senegal; Zambia | K71: A10:landmarks
A72: LM01815 | B72: A10 | C72: Building a circular plastics economy with informal waste pickers: Recyclate quality, business model, and societal impacts | D72: 2020 | E72: Markus Gall; Melanie Wiener; Cintia Chagas de Oliveira; Reinhold W. Lang; Erik G. Hansen | F72: Resources Conservation and Recycling | G72: 218 | H72: 10.1016/j.resconrec.2020.104685 | I72: Africa | J72: Kenya; Nairobi | K72: A10:landmarks
A73: LM01816 | B73: A10 | C73: Bureaucratic form and the informal economy | D73: 2006 | E73: Keith Hart | G73: 217 | H73: 10.1093/0199204764.003.0002 | I73: Not place-specific | K73: A10:landmarks
A74: LM01817 | B74: A10 | C74: Ordinary states: Everyday corruption and the politics of space in Mumbai | D74: 2011 | E74: Jonathan Shapiro Anjaria | F74: American Ethnologist | G74: 217 | H74: 10.1111/j.1548-1425.2010.01292.x | I74: South Asia | J74: India; Mumbai | K74: A10:landmarks
A75: LM01819 | B75: A10 | C75: Historical Review of Waste Management and Recycling in South Africa | D75: 2017 | E75: Linda Godfrey; Suzan H. H. Oelofse | F75: Resources | G75: 207 | H75: 10.3390/resources6040057 | I75: Africa | J75: Africa; African; South Africa | K75: A10:landmarks
A76: LM01820 | B76: A10 | C76: Globalization and Home-Based Workers | D76: 2000 | E76: Marilyn Carr; Martha Alter Chen; Jane Tate | F76: Feminist Economics | G76: 205 | H76: 10.1080/135457000750020164 | I76: Not place-specific | K76: A10:landmarks
A77: LM01821 | B77: A10 | C77: Skills Development in Sub-Saharan Africa | D77: 2004 | E77: Richard K. Johanson; Arvil V. Adams | G77: 205 | H77: 10.1596/978-0-8213-5680-7 | I77: Multi-region | J77: Africa; African; Boston; Botswana; Ghana; India; Kenya; Namibia; South Africa; Sri Lanka; Sudan; Thailand; Uganda; sub-Saharan | K77: A10:landmarks
A78: LM01823 | B78: A10 | C78: Urbanization and Underdevelopment: A Global Study of Modernization, Urban Bias, and Economic Dependency | D78: 1987 | E78: York W. Bradshaw | F78: American Sociological Review | G78: 199 | H78: 10.2307/2095451 | I78: Not place-specific | K78: A10:landmarks
A79: LM01825 | B79: A10 | C79: Street Vendors in the Global Urban Economy | D79: 2012 | E79: Sharit K. Bhowmik | F79: Routledge eBooks | G79: 194 | H79: 10.4324/9780203150542 | I79: Multi-region | J79: Africa; Bangkok; Cambodia; Delhi; India; Latin America; Mumbai; Phnom Penh; Sao Paulo; Venezuela | K79: A10:landmarks
A80: LM01826 | B80: A10 | C80: Mainstreaming informal employment and gender in poverty reduction : a handbook for policy - makers and other stakeholders | D80: 2004 | E80: Martha Alter Chen; Joann Vanek; Marilyn Carr | G80: 184 | I80: South Asia | J80: India | K80: A10:landmarks
A81: LM01828 | B81: A10 | C81: Street Traders and the Emerging Spaces for Urban Voice and Citizenship in African Cities | D81: 2010 | E81: Alison Hamilton Brown; Michal Lyons; Ibrahima Dankoco | F81: Urban Studies | G81: 181 | H81: 10.1177/0042098009351187 | I81: Africa | J81: African; Ghana; Lesotho; Senegal; Tanzania | K81: A10:landmarks
A82: LM01839 | B82: A10 | C82: The Role of Market Women in the Informal Urban Economy in Kumasi | D82: 2012 | E82: T. Y. Baah-Ennumh; Gifty Adom‐Asamoah | F82: Journal of Science and Technology (Ghana) | G82: 37 | H82: 10.4314/just.v32i2.8 | I82: Africa | J82: Ghana; Kumasi | K82: A10:landmarks<-C14
A83: LM01840 | B83: A10 | C83: Beyond traditional trade unionism: innovative worker responses in three African cities | D83: 2021 | E83: Edward C. Webster; Carmen Ludwig; Fikile Masikane; Dave Spooner | F83: Globalizations | G83: 37 | H83: 10.1080/14747731.2021.1874253 | I83: Africa | J83: African; Cape Town; Johannesburg; Kampala | K83: A10:landmarks<-C14
A84: LM01946 | B84: A11 | C84: Migration unemployment and development: a two-sector analysis. | D84: 1970 | E84: Harris; Michael P. Todaro | F84: American Economic Review | G84: 6391 | I84: Not place-specific | K84: A11:landmarks
A85: LM01947 | B85: A11 | C85: TheHukouSystem and Rural-Urban Migration in China: Processes and Changes | D85: 1999 | E85: Kam Wing Chan; Li Zhang | F85: The China Quarterly | G85: 1319 | H85: 10.1017/s0305741000001351 | I85: China & East Asia | J85: China | K85: A11:landmarks
A86: LM01949 | B86: A11 | C86: Rural-urban migration, urban unemployment and underemployment, and job-search activity in LDCs | D86: 1975 | E86: Gary S. Fields | F86: Journal of Development Economics | G86: 800 | H86: 10.1016/0304-3878(75)90014-0 | I86: Not place-specific | K86: A11:landmarks
A87: LM01950 | B87: A11 | C87: Rural–urban migration and urbanization in China: Evidence from time-series and cross-section analyses | D87: 2003 | E87: Kevin Honglin Zhang; Shunfeng Song | F87: China Economic Review | G87: 735 | H87: 10.1016/j.chieco.2003.09.018 | I87: China & East Asia | J87: China | K87: A11:landmarks
A88: LM01951 | B88: A11 | C88: Economic Development and International Migration in Comparative Perspective | D88: 1988 | E88: Douglas S. Massey | F88: Population and Development Review | G88: 660 | H88: 10.2307/1972195 | I88: Multi-region | J88: European; Mexico; United States | K88: A11:landmarks; A4:landmarks
A89: LM01952 | B89: A11 | C89: Migration from rural areas of poor countries: The impact on rural productivity and income distribution | D89: 1980 | E89: Michael Lipton | F89: World Development | G89: 638 | H89: 10.1016/0305-750x(80)90047-9 | I89: Not place-specific | K89: A11:landmarks
A90: LM01953 | B90: A11 | C90: The Dual Imperative in Refugee Research: Some Methodological and Ethical Considerations in Social Science Research on Forced Migration | D90: 2003 | E90: Karen Jacobsen; Loren B. Landau | F90: Disasters | G90: 602 | H90: 10.1111/1467-7717.00228 | I90: Africa | J90: Johannesburg | K90: A11:landmarks
A91: LM01955 | B91: A11 | C91: Systems Approach to a Theory of Rural‐Urban Migration | D91: 1970 | E91: Akin L. Mabogunje | F91: Geographical Analysis | G91: 583 | H91: 10.1111/j.1538-4632.1970.tb00140.x | I91: Not place-specific | K91: A11:landmarks
A92: LM01956 | B92: A11 | C92: Labor Market Outcomes and Reforms in China | D92: 2012 | E92: Xin Meng | F92: The Journal of Economic Perspectives | G92: 530 | H92: 10.1257/jep.26.4.75 | I92: China & East Asia | J92: China | K92: A11:landmarks
A93: LM01957 | B93: A11 | C93: The Household Registration System and Migrant Labor in China: Notes on a Debate | D93: 2010 | E93: Kam Wing Chan | F93: Population and Development Review | G93: 525 | H93: 10.1111/j.1728-4457.2010.00333.x | I93: China & East Asia | J93: China | K93: A11:landmarks
A94: LM01958 | B94: A11 | C94: Rural migrant workers in urban China: living a marginalised life | D94: 2006 | E94: Daniel Fu Keung Wong; Chang Ying Li; He Xue Song | F94: International Journal of Social Welfare | G94: 520 | H94: 10.1111/j.1468-2397.2007.00475.x | I94: China & East Asia | J94: China | K94: A11:landmarks; A11:landmarks<-A1
A95: LM01959 | B95: A11 | C95: Great Expectations? The Subjective Well-being of Rural–Urban Migrants in China | D95: 2009 | E95: John B. Knight; Ramani Gunatilaka | F95: World Development | G95: 515 | H95: 10.1016/j.worlddev.2009.03.002 | I95: China & East Asia | J95: China | K95: A11:landmarks
A96: LM01960 | B96: A11 | C96: The Elite, the Natives, and the Outsiders: Migration and Labor Market Segmentation in Urban China | D96: 2002 | E96: C. Cindy Fan | F96: Annals of the Association of American Geographers | G96: 449 | H96: 10.1111/1467-8306.00282 | I96: Multi-region | J96: China; Guangzhou; Russia | K96: A11:landmarks
A97: LM01961 | B97: A11 | C97: The impact of weather anomalies on migration in sub-Saharan Africa | D97: 2012 | E97: Luca Marchiori; Jean-François Maystadt; Ingmar Schumacher | F97: Journal of Environmental Economics and Management | G97: 443 | H97: 10.1016/j.jeem.2012.02.001 | I97: Africa | J97: Africa; sub-Saharan | K97: A11:landmarks
A98: LM01962 | B98: A11 | C98: How migration restrictions limit agglomeration and productivity in China | D98: 2005 | E98: Chun-Chung Au; J. Vernon Henderson | F98: Journal of Development Economics | G98: 437 | H98: 10.1016/j.jdeveco.2005.04.002 | I98: China & East Asia | J98: China | K98: A11:landmarks
A99: LM01963 | B99: A11 | C99: CITIES AND DEVELOPMENT | D99: 2009 | E99: J. Vernon Henderson | F99: Journal of Regional Science | G99: 433 | H99: 10.1111/j.1467-9787.2009.00636.x | I99: Multi-region | J99: China; India | K99: A11:landmarks
A100: LM01964 | B100: A11 | C100: The impact of rural out-migration on land use transition in China: Past, present and trend | D100: 2014 | E100: Ruishan Chen; Chao Ye; Yunlong Cai; Xiaoshi Xing; Qiong Chen | F100: Land Use Policy | G100: 425 | H100: 10.1016/j.landusepol.2013.10.003 | I100: China & East Asia | J100: China | K100: A11:landmarks
...

Sheet India subset
A1: Records whose title/abstract name India or an Indian place (Delhi/NCR and Haryana flags in the extra columns).
A2: ID | B2: Primary theme | C2: Title | D2: Year | E2: Authors | F2: Venue | G2: Cited-by count | H2: DOI | I2: Region | J2: Places studied | K2: Found in | L2: Delhi/NCR flag | M2: Haryana flag
A3: LM00101 | B3: A1 | C3: Water service provision in rapidly urbanising villages: a comparison of rural and urban governance in Mumbai and Chennai regions in India | D3: 2026 | E3: Renjitha Maniyil Haridasan; Alison Parker; May N. Sule | F3: Environmental Science Water Research & Technology | G3: 1 | H3: 10.1039/d5ew00935a | I3: South Asia | J3: Chennai; India; Mumbai | K3: A1:india
A4: LM00130 | B4: A1 | C4: FINANCIAL SUSTAINABILITY OF URBAN LOCAL BODIES: A COMPARATIVE EVALUATION OF LUCKNOW AND VARANASI | D4: 2026 | E4: Sonali Jaiswal; Dr. Archana Singh | F4: EPRA International Journal of Economic and Business Review | G4: 0 | H4: 10.36713/epra25785 | I4: South Asia | J4: India; Lucknow; Varanasi | K4: A1:recent
A5: LM00131 | B5: A1 | C5: Urban Local Bodies in India: An Analysis of Public Service Delivery Mechanisms | D5: 2026 | E5: Randeep Dhoot | F5: International Journal of Social Science and Education Research | G5: 0 | H5: 10.33545/26649845.2026.v8.i1b.508 | I5: South Asia | J5: India | K5: A1:recent
A6: LM00133 | B6: A1 | C6: Local government system in Pakistan, India, and Bangladesh: Review of research priorities and gaps | D6: 2026 | E6: Amna Mushtaq Gill; Majid Mushtaq | F6: Journal of Agricultural Policy and Transformation | G6: 0 | H6: 10.66529/agripat.2026.2.1.32 | I6: South Asia | J6: Bangladesh; India; Pakistan; South Asia; South Asian | K6: A1:india
A7: LM00135 | B7: A1 | C7: Empowering Inclusive Urban Governance | D7: 2026 | E7: Monalisa Mohanty; Barsha Poricha; Bashabi Dasgupta; Kasmita Basing | F7: Routledge eBooks | G7: 0 | H7: 10.4324/9781003630333-57 | I7: South Asia | J7: India; Odisha | K7: A1:recent
A8: LM00160 | B8: A1 | C8: Contrasting Models of Urban Governance: A Comparative Study of Noida and Gurugram | D8: 2026 | E8: Pranoy Braruah | F8: Zenodo (CERN European Organization for Nuclear Research) | G8: 0 | H8: 10.5281/zenodo.18204545 | I8: South Asia | J8: Delhi; Gurugram; India; Noida | K8: A1:india | L8: Y | M8: Y
A9: LM00164 | B9: A1 | C9: Role of Urban Local Bodies in Improving Sustainable Urban Development: A Case Study of Patna Municipal Corporation Area | D9: 2026 | E9: Dr. Ravi Prakash; Prashant Kumar | F9: Zenodo (CERN European Organization for Nuclear Research) | G9: 0 | H9: 10.5281/zenodo.22127819 | I9: South Asia | J9: Bihar; India; Patna | K9: A1:recent
A10: LM00165 | B10: A1 | C10: ROLE OF URBAN LOCAL BODIES | D10: 2026 | E10: ARSHMEET KAUR | F10: Zenodo (CERN European Organization for Nuclear Research) | G10: 0 | H10: 10.5281/zenodo.22671228 | I10: South Asia | J10: India | K10: A1:recent
A11: LM00166 | B11: A1 | C11: ORGANISATIONAL & ADMINISTRATIVE STRUCTURE OF MUNICIPAL CORPORATION FARIDABAD | D11: 2026 | E11: Anil Malre | F11: International Journal of Advanced Research and Multidisciplinary Trends (IJARMT) | G11: 0 | I11: South Asia | J11: Faridabad; Haryana; India | K11: A1:recent | L11: Y | M11: Y
A12: LM00064 | B12: A1 | C12: Housing adequacy in Delhi, Dhaka and Karachi: Strategies for promoting sustainable and inclusive housing | D12: 2025 | E12: Sohail Ahmad; Faisal Munir; Ram Avtar; Tanjil Sowgat; Debolina Kundu; Ya Ping Wang | F12: Cities | G12: 7 | H12: 10.1016/j.cities.2025.105779 | I12: South Asia | J12: Delhi; Dhaka; India; Karachi | K12: A1:india | L12: Y
A13: LM00129 | B13: A1 | C13: The Informal Economy and Municipal Revenue: A Hidden Fiscal Resource for Indian Urban Local Bodies? | D13: 2025 | E13: MUSTHAF MUSTHAF | F13: International Journal on Science and Technology | G13: 0 | H13: 10.71097/ijsat.v16.i3.7374 | I13: South Asia | J13: India | K13: A1:india; A1:recent; C14:india
A14: LM00158 | B14: A1 | C14: 74th CONSTITUTIONAL AMENDMENT ACT AND ITS IMPLICATION ON URBAN LOCAL BODIES: STUDY ON URBAN LOCAL GOVERNANCE IN DIBRUGARH MUNICIPAL CORPORATION OF ASSAM, INDIA | D14: 2025 | E14: Ritu Devi; Munindra Kakati; Deepom Baruah | F14: Zenodo (CERN European Organization for Nuclear Research) | G14: 0 | H14: 10.5281/zenodo.17731835 | I14: South Asia | J14: India | K14: A1:recent
A15: LM00159 | B15: A1 | C15: The Impact of Women's Empowerment on Political Involvement in Urban Local Bodies | D15: 2025 | E15: Shazia Unwan Musarrat | F15: Zenodo (CERN European Organization for Nuclear Research) | G15: 0 | H15: 10.5281/zenodo.18046689 | I15: South Asia | J15: India | K15: A1:recent
A16: LM00167 | B16: A1 | C16: Urban Governance - Greater Noida - Looking Towards the Future | D16: 2025 | E16: Dr.Anusha pachori | F16: European Economic Letters (EEL) | G16: 0 | I16: South Asia | J16: Greater Noida; India; Noida | K16: A1:india | L16: Y
A17: LM00170 | B17: A1 | C17: A Historical Overview of Women's Political Participation in Urban Local Bodies | D17: 2025 | E17: Simran; Dr. Sonika | F17: Shodh Patra : International Journal of Multidisciplinary Studies | G17: 0 | I17: South Asia | J17: India | K17: A1:recent
A18: LM00122 | B18: A1 | C18: Structure and Functioning of Urban Local Bodies in Infrastructure and its Challenges | D18: 2024 | E18: AR Gupta; Pl. Arundhatee Mishra | F18: INTERANTIONAL JOURNAL OF SCIENTIFIC RESEARCH IN ENGINEERING AND MANAGEMENT | G18: 0 | H18: 10.55041/ijsrem29205 | I18: South Asia | J18: India | K18: A1:recent
A19: LM00125 | B19: A1 | C19: An Overview of Accounting Reforms in Indian Urban Local Bodies | D19: 2024 | E19: M. Yadagiri; K. Ranjitha - | F19: Journal of Economics Finance and Management Studies | G19: 0 | H19: 10.47191/jefms/v7-i11-35 | I19: South Asia | J19: India | K19: A1:recent
A20: LM00154 | B20: A1 | C20: After Three Decades of Democratic Decentralisation: Finances of the Urban Local Bodies in Andhra Pradesh | D20: 2024 | E20: Bishnu Prasad Mohapatra | F20: Research Square | G20: 0 | H20: 10.21203/rs.3.rs-3992848/v1 | I20: South Asia | J20: Andhra Pradesh; India | K20: A1:recent
A21: LM00155 | B21: A1 | C21: Olga Teli versus Bombay municipal Corporation & ORS | D21: 2024 | E21: Madesa Iqbal | F21: SSRN Electronic Journal | G21: 0 | H21: 10.2139/ssrn.4890965 | I21: South Asia | J21: Bombay | K21: A1:india; A1:recent
A22: LM00168 | B22: A1 | C22: Municipal Corporation Election In Tamil Nadu: | D22: 2024 | E22: Dr. S. Jayakumar K. Senthil Kumar | F22: Library Progress (International) | G22: 0 | I22: South Asia | J22: India; Tamil Nadu | K22: A1:recent
A23: LM00169 | B23: A1 | C23: Decentralization And Local Government | D23: 2024 | E23: Chitrashekhar Chiralli | F23: Educational Administration Theory and Practice journal | G23: 0 | I23: South Asia | J23: India | K23: A1:recent
A24: LM00097 | B24: A1 | C24: Supports for Multi-hazard Risk Reduction in Urban Local Bodies | D24: 2023 | E24: Ripin Kalra | F24: Halduskultuur | G24: 1 | H24: 10.32994/hk.v22i1.285 | I24: South Asia | J24: Bihar; India | K24: A1:recent
A25: LM00103 | B25: A1 | C25: Civic Center for Municipal Corporation of Delhi | D25: 2023 | E25: Akanksha Sharma | F25: ScholarWorks@UMassAmherst (University of Massachusetts Amherst) | G25: 1 | H25: 10.7275/1425897 | I25: South Asia | J25: Delhi; India | K25: A1:recent | L25: Y
A26: LM00116 | B26: A1 | C26: Financing the Infrastructure of Municipal Corporation on Sustainable Basis: A Case Study of Vasai Virar Municipal Corporation | D26: 2023 | E26: Sanjay Jayawant Rode | F26: MANAGEMENT AND ECONOMICS REVIEW | G26: 0 | H26: 10.24818/mer/2023.02-05 | I26: South Asia | J26: Mumbai | K26: A1:recent
A27: LM00121 | B27: A1 | C27: Indian Municipal Finance 2023 | D27: 2023 | E27: Mithlesh Verma | G27: 0 | H27: 10.24943/imf11.2023 | I27: South Asia | J27: India | K27: A1:india
A28: LM00151 | B28: A1 | C28: 74TH AMENDMENT AND MUNICIPALITIES IN MAHARASHTRA CONSTITUTING CIVIC BODIES ACCORDING TO NEW STATUTES | D28: 2023 | E28: Shahid M. Zakaullah | F28: Zenodo (CERN European Organization for Nuclear Research) | G28: 0 | H28: 10.5281/zenodo.8106017 | I28: South Asia | J28: India; Maharashtra | K28: A1:recent
A29: LM00152 | B29: A1 | C29: URBAN LOCAL GOVERNMENTS IN MAHARASHTRA COMPOSITION OF CIVIC STRUCTURE AND THE 74TH AMENDMENT | D29: 2023 | E29: Shahid M. Zakaullah | F29: Zenodo (CERN European Organization for Nuclear Research) | G29: 0 | H29: 10.5281/zenodo.8105632 | I29: South Asia | J29: India; Maharashtra | K29: A1:recent
A30: LM00153 | B30: A1 | C30: Application of Geospatial Platform for Enhancing Property Tax in Shakarpur Municipal Corporation Region, Delhi | D30: 2023 | E30: Rahul Pratap Shahi; Manjit Singh | F30: Zenodo (CERN European Organization for Nuclear Research) | G30: 0 | H30: 10.5281/zenodo.8214197 | I30: South Asia | J30: Delhi; India | K30: A1:india | L30: Y
A31: LM00049 | B31: A1 | C31: Integrated Influencing Mechanism of Potential Drivers on Seasonal Variability of LST in Kolkata Municipal Corporation, India | D31: 2022 | E31: Dipankar Bera; Nilanjana Das Chatterjee; Faisal Mumtaz; Santanu Dinda; Subrata Ghosh; Na Zhao; Sudip Bera; Aqil Tariq | F31: Land | G31: 30 | H31: 10.3390/land11091461 | I31: South Asia | J31: India; Kolkata | K31: A1:india
A32: LM00073 | B32: A1 | C32: Determinants of Own Revenues in Urban Local Bodies: Evidence from an Indian State | D32: 2022 | E32: Kala Seetharam Sridhar; Vishal Ravi | F32: Environment and Urbanization Asia | G32: 4 | H32: 10.1177/09754253221076317 | I32: South Asia | J32: India; Karnataka | K32: A1:recent
A33: LM00083 | B33: A1 | C33: Indian Municipal Finance 2022 | D33: 2022 | E33: Aromar Revi; Madhumitha Srinivasan; Amir Bashir Bazaz; Manish Kant Dubey; Midhat Fatima Safdar | G33: 2 | H33: 10.24943/imf02.2022 | I33: South Asia | J33: India | K33: A1:india
A34: LM00095 | B34: A1 | C34: Finances of Dhaka City Corporations and Kolkata Municipal Corporation | D34: 2022 | E34: Simanti Bandyopadhyay; Firdousi Naher; Aishna Sharma | F34: SpringerBriefs in economics | G34: 1 | H34: 10.1007/978-981-19-2297-8_2 | I34: South Asia | J34: Dhaka; Kolkata | K34: A1:india
A35: LM00149 | B35: A1 | C35: Property Tax in India | D35: 2022 | E35: Aakriti Ahuja | F35: SSRN Electronic Journal | G35: 0 | H35: 10.2139/ssrn.4065991 | I35: South Asia | J35: India | K35: A1:india
A36: LM00070 | B36: A1 | C36: Metropolitan and Peri-Urban Governance in India: Case Study of Chennai Metropolitan Area | D36: 2020 | E36: Chetna Singh | F36: Indian Journal of Public Administration | G36: 5 | H36: 10.1177/0019556120906586 | I36: South Asia | J36: Chennai; India; South Asia | K36: A1:india
A37: LM00147 | B37: A1 | C37: Towards Sustainable Cities: Lessons from Urban Decentralization in India and Bangladesh | D37: 2020 | E37: Simanti Bandyopadhyay; Firdousi Naher; Aishna Sharma | F37: RePEc: Research Papers in Economics | G37: 0 | I37: South Asia | J37: Bangladesh; Dhaka; India; Kolkata; South Asian | K37: A1:india
A38: LM00069 | B38: A1 | C38: Metropolitan governance and local decentralisation in India: case of Chennai and Kolkata metropolitan regions | D38: 2019 | E38: Arindam Biswas; Tetsuo Kidokoro; Fumihiko Seta | F38: Asia-Pacific Journal of Regional Science | G38: 5 | H38: 10.1007/s41685-019-00115-w | I38: South Asia | J38: Chennai; India; Kolkata | K38: A1:india
A39: LM00051 | B39: A1 | C39: Outsourced urban governance as a state rescaling strategy in Hyderabad, India | D39: 2018 | E39: Loraine Kennedy; Ashima Sood | F39: Cities | G39: 22 | H39: 10.1016/j.cities.2018.09.001 | I39: South Asia | J39: Hyderabad; India | K39: A1:india
A40: LM00078 | B40: A1 | C40: Transforming Urban Governance to Manage Uncertainty and Climate Change in Mumbai, India | D40: 2018 | E40: Hans Nicolai Adam; Devanathan Parthasarathy; N. C. Narayanan | F40: Figshare | G40: 4 | I40: South Asia | J40: India; Mumbai | K40: A1:india
A41: LM00108 | B41: A1 | C41: Income and disbursement of Urban Local Bodies: A Study of Kurnool Municipal Corporation | D41: 2018 | E41: Samadri Muniswami | F41: International Journal of Scientific Research and Management (IJSRM) | G41: 0 | H41: 10.18535/ijsrm/v6i2.em10 | I41: South Asia | J41: Bombay; Calcutta; India; Madras | K41: A1:india
A42: LM00042 | B42: A1 | C42: Urban governance in India | D42: 2017 | E42: Isher Judge Ahluwalia | F42: Journal of Urban Affairs | G42: 137 | H42: 10.1080/07352166.2016.1271614 | I42: South Asia | J42: India | K42: A1:india; A1:india<-A7
A43: LM00043 | B43: A1 | C43: Arsenic in groundwater of the Kolkata Municipal Corporation (KMC), India: Critical review and modes of mitigation | D43: 2017 | E43: Dipankar Chakraborti; Bhaskar Das; Mohammad Mahmudur Rahman‬; Bishwajit Nayak; Arup Pal; Mrinal Kumar Sengupta; Sad Ahamed; Md. Amir Hossain; Uttam Kumar Chowdhury; Bhajan Kumar Biswas et al. | F43: Chemosphere | G43: 76 | H43: 10.1016/j.chemosphere.2017.04.051 | I43: South Asia | J43: India; Kolkata | K43: A1:india
A44: LM00107 | B44: A1 | C44: Fiscal Decentralization and Urban Local Finance in India : A Case Study of Haryana | D44: 2017 | E44: Jagdeep Kumar; Rajpal Singh | F44: Arthshastra Indian Journal of Economics & Research | G44: 0 | H44: 10.17010/aijer/2017/v6i6/120116 | I44: South Asia | J44: Haryana; India | K44: A1:india | M44: Y
A45: LM00068 | B45: A1 | C45: Local government finance: challenges in revenue-raising at the Municipal Corporation of Delhi | D45: 2015 | E45: Simanti Bandyopadhyay | F45: Commonwealth Journal of Local Governance | G45: 5 | H45: 10.5130/cjlg.v0i0.4486 | I45: South Asia | J45: Delhi; India | K45: A1:india | L45: Y
A46: LM00090 | B46: A1 | C46: The Capacity of Local Government in South Asia | D46: 2015 | E46: Amitava Basu | F46: Public Policy And Administration | G46: 1 | H46: 10.5755/j01.ppaa.14.3.13436 | I46: Multi-region | J46: Africa; Bangladesh; Bhutan; India; Maldives; Nepal; Pakistan; South Asia; South Asian; Sri Lanka | K46: A1:india
A47: LM00140 | B47: A1 | C47: Gender Related Educational Development Index (GEDI) of Kolkata Municipal Corporation (KMC) India | D47: 2015 | E47: Tusi Das; Saswati Mookherjee | G47: 0 | I47: South Asia | J47: India; Kolkata | K47: A1:india
A48: LM00065 | B48: A1 | C48: Dimension of decentralization process and rural local government in India : a comparison with Bangladesh | D48: 2014 | E48: Md Taufiqul Islam | F48: Journal of South Asian Studies | G48: 7 | I48: South Asia | J48: Bangladesh; India; West Bengal | K48: A1:india
A49: LM00089 | B49: A1 | C49: Financial Health of Urban Local Bodies of Rajasthan with Special Reference to Jodhpur Municipal Corporation | D49: 2013 | E49: S. Chitra | F49: IOSR Journal of Humanities and Social Science | G49: 1 | H49: 10.9790/0837-1865967 | I49: South Asia | J49: India; Rajasthan | K49: A1:india
A50: LM00080 | B50: A1 | C50: A Comparative Overview of Urban Governance in Delhi, Hyderabad, Kolkata, and Mumbai | D50: 2012 | E50: Joël Ruet; Keshab Das; Agnès Huchon; Guillaume Tricot | F50: Routledge eBooks | G50: 3 | H50: 10.4324/9780203151860-10 | I50: South Asia | J50: Delhi; Hyderabad; India; Kolkata; Mumbai | K50: A1:india | L50: Y
A51: LM00084 | B51: A1 | C51: Assessing Urban Governance through the Prism of Healthcare Services in Delhi, Hyderabad and Mumbai | D51: 2012 | E51: Loraine Kennedy, Ravi Duggal and Ste´phanie Tawa Lama-Rewal | F51: Routledge eBooks | G51: 2 | H51: 10.4324/9780203151860-16 | I51: South Asia | J51: Delhi; Hyderabad; India; Mumbai | K51: A1:india | L51: Y
A52: LM00093 | B52: A1 | C52: Participatory Urban Governance and Slum Development in Hyderabad and Kolkata | D52: 2012 | E52: Archana Ghosh | F52: Routledge eBooks | G52: 1 | H52: 10.4324/9780203151860-18 | I52: South Asia | J52: Hyderabad; Kolkata | K52: A1:india
A53: LM00094 | B53: A1 | C53: Thinking the Delhi, Hyderabad, Kolkata, and Mumbai Experience: Emerging Modes of Urban Governance and State Intervention | D53: 2012 | E53: Joël Ruet | F53: Routledge eBooks | G53: 1 | H53: 10.4324/9780203151860-20 | I53: South Asia | J53: Delhi; Hyderabad; India; Kolkata; Mumbai | K53: A1:india | L53: Y
A54: LM00105 | B54: A1 | C54: Pragmatic Municipal Finance Reform in India | D54: 2012 | E54: Anand Sahasranaman | F54: Environment and Urbanization Asia | G54: 0 | H54: 10.1177/0975425312473334 | I54: Multi-region | J54: Africa; Brazil; India; South Africa | K54: A1:india
A55: LM00056 | B55: A1 | C55: Mumbai Human Development Report 2009 , (Municipal Corporation of Greater Mumbai), 2009 | D55: 2010 | E55: Chetan Vaidya; Satmohini Srivastva | F55: Environment and Urbanization Asia | G55: 15 | H55: 10.1177/097542531000100214 | I55: South Asia | J55: Mumbai | K55: A1:india
A56: LM00081 | B56: A1 | C56: Role of women councillors in urban local bodies : a case study of the Kolkata and the Howrah Municipal Corporation | D56: 2010 | E56: Anjana Ghosh | F56: Medical Entomology and Zoology | G56: 3 | I56: South Asia | J56: Kolkata | K56: A1:india
A57: LM00148 | B57: A1 | C57: Municipal Finance A Comparative Study Of Chennai And Hyderabad Municipal Corporations | D57: 2010 | E57: R. Kanaka Durga | F57: Shodhganga | G57: 0 | I57: South Asia | J57: Chennai; Hyderabad | K57: A1:india
A58: LM00062 | B58: A1 | C58: Democratic Decentralization and Empowerment of Local Government Associations in Kerala | D58: 2009 | E58: N Ramakantan | F58: Commonwealth Journal of Local Governance | G58: 7 | H58: 10.5130/cjlg.v0i2.995 | I58: South Asia | J58: India; Kerala | K58: A1:india
A59: LM00077 | B59: A1 | C59: A comparative overview of urban governance in Delhi, Hybderabad, Kolkata, and Mumbai | D59: 2009 | E59: Anindita Ghosh; Loraine Kennedy; Joël Ruet; Stéphanie Tawa Lama‐Rewal; Marie‐Hélène Zérah | G59: 4 | I59: South Asia | J59: Delhi; India; Kolkata; Mumbai | K59: A1:india | L59: Y
A60: LM00104 | B60: A1 | C60: Comparing urban governance in Delhi, Hyderabad, Kolkata, and Mumbai | D60: 2009 | E60: Stéphanie Tawa Lama‐Rewal; Archana Ghosh; Loraine Kennedy; Joël Ruet; Marie‐Hélène Zérah | F60: HAL (Le Centre pour la Communication Scientifique Directe) | G60: 1 | I60: South Asia | J60: Delhi; Hyderabad; India; Kolkata; Mumbai | K60: A1:india | L60: Y
A61: LM00139 | B61: A1 | C61: Urban Local Bodies and Management of Environment: Role of Kolhapur Municipal Corporation (KMC) in Maharashtra | D61: 2009 | E61: P.S. Kamble | F61: Advances In Management | G61: 0 | I61: South Asia | J61: India; Maharashtra | K61: A1:india
A62: LM00061 | B62: A1 | C62: Urban Governance in India—Spotlight on Mumbai | D62: 2008 | E62: Maria Socorro Diógenes Pinto | F62: SAGE Publications India Pvt Ltd eBooks | G62: 8 | H62: 10.4135/9788132101390.n2 | I62: South Asia | J62: India; Mumbai | K62: A1:india
A63: LM00136 | B63: A1 | C63: Communicative Planning and Democratic Decentralisation in India- Case of Kolkata City | D63: 2008 | E63: Antarin Chakrabarty | F63: BIBSYS Brage (BIBSYS (Norway)) | G63: 0 | I63: South Asia | J63: India; Kolkata; West Bengal | K63: A15:india; A1:india
A64: LM00150 | B64: A1 | C64: Women in the Calcutta Municipal Corporation | D64: 2008 | E64: Stéphanie Tawa Lama‐Rewal | F64: HAL (Le Centre pour la Communication Scientifique Directe) | G64: 0 | I64: South Asia | J64: Calcutta | K64: A1:india
A65: LM00041 | B65: A1 | C65: Remote Sensing and GIS Techniques for Evaluation of Groundwater Quality in Municipal Corporation of Hyderabad (Zone-V), India | D65: 2007 | E65: S.S. Asadi; Padmaja Vuppala; M. Anji Reddy | F65: International Journal of Environmental Research and Public Health | G65: 251 | H65: 10.3390/ijerph2007010008 | I65: South Asia | J65: Hyderabad; India | K65: A1:india
A66: LM00048 | B66: A1 | C66: Municipal Finance in India: An Assessment | D66: 2007 | E66: P. K. Mohanty; B. M. Misra; Rajan Goyal; P. D. Jeromi | F66: RePEc: Research Papers in Economics | G66: 42 | I66: South Asia | J66: India | K66: A1:india
A67: LM00138 | B67: A1 | C67: Urban risk communication in Ahmedabad - India: between slum dwellers and the municipal corporation. | D67: 2007 | E67: C Woiwode | F67: OpenGrey (Institut de l'Information Scientifique et Technique) | G67: 0 | I67: South Asia | J67: Ahmedabad; India | K67: A1:india
A68: LM00141 | B68: A1 | C68: Institutional structure for Urban governance in Ahmedabad and Hyderabad | D68: 2005 | E68: Vinita Yadav | F68: INFLIBNET | G68: 0 | I68: South Asia | J68: Ahmedabad; Hyderabad | K68: A1:india
A69: LM00045 | B69: A1 | C69: Implementing property tax reforms in Bangalore: an actor-network perspective | D69: 2004 | E69: Shirin Madon; Sundeep Sahay; Jyotsna Sahay | F69: Information and Organization | G69: 66 | H69: 10.1016/j.infoandorg.2004.07.002 | I69: South Asia | J69: Bangalore | K69: A1:india
A70: LM00059 | B70: A1 | C70: Women's Reservations and Electoral Politics in Urban Local Bodies: An Analysis of Chennai Municipal Corporation Elections, 2001 | D70: 2003 | E70: Archana Ghosh | F70: Indian Journal of Gender Studies | G70: 9 | H70: 10.1177/097152150301000106 | I70: South Asia | J70: Chennai | K70: A1:india
A71: LM00071 | B71: A1 | C71: Supporting decentralised urban governance : training women municipal councillors in Mumbai, India | D71: 2003 | E71: Bernhard Holzner; Joop de Wit | F71: RePEc: Research Papers in Economics | G71: 5 | I71: Multi-region | J71: India; Mumbai; Netherlands | K71: A1:india
A72: LM00145 | B72: A1 | C72: Progress after the 74th amendment in Kerala local government institutions | D72: 2002 | E72: Angelique Chettiparamb | G72: 0 | I72: South Asia | J72: Kerala | K72: A1:india
A73: LM00091 | B73: A1 | C73: Financial Implications of Decentralisation: Issues Concerning Resource Mobilisation by Urban Local Bodies | D73: 2000 | E73: Soumen Bagchi | F73: Artha Vijnana Journal of The Gokhale Institute of Politics and Economics | G73: 1 | H73: 10.21648/arthavij/2000/v42/i4/115858 | I73: South Asia | J73: India | K73: A1:india
A74: LM00008 | B74: A1 | C74: The Political Economy of Democratic Decentralization | D74: 1999 | E74: James Manor | F74: World Bank, Washington, DC eBooks | G74: 967 | H74: 10.1596/0-8213-4470-6 | I74: Multi-region | J74: Africa; African; Bangladesh; Brazil; Central AsiaJournal; China; Ethiopia; Ghana; India; Indonesia; Italy; Lagos; Malawi; Nigeria; Norway; Pakistan; Sierra Leone; South Africa; South AsiaInternational; South Asian; South Korea; Southeast AsiaEnvironment; Thailand; United Kingdom; United States; Uruguay; West Bengal; Zambia | K74: A1:landmarks; A7:landmarks
A75: LM00014 | B75: A1 | C75: Rethinking Decentralization in Developing Countries | D75: 1998 | E75: Jennie I. Litvack; Junaid Aḥmad; Richard Miller Bird | F75: World Bank, Washington, DC eBooks | G75: 634 | H75: 10.1596/0-8213-4350-5 | I75: Multi-region | J75: Africa; African; Australia; Benin; Bolivia; Brazil; Burkina Faso; Chile; China; Europe; European; Ghana; Hungary; India; Indonesia; Kampala; Karnataka; Kolkata; Madhya Pradesh; Mali; Mexico; Odisha; Pakistan; Peru; Philippines; Senegal; Seoul; Southeast Asian; Tanzania; Timor-Leste; Uganda; Ukraine; United States; West Bengal | K75: A14:landmarks; A1:landmarks; A7:landmarks
A76: LM00106 | B76: A1 | C76: Decentralisation and Local Government Reform in India | D76: 1985 | E76: Abhijit Datta | F76: Indian Journal of Public Administration | G76: 0 | H76: 10.1177/0019556119850309 | I76: South Asia | J76: India | K76: A1:india
A77: LM00137 | B77: A1 | C77: Finances of Bangalore Municipal Corporation | D77: 1979 | E77: S. Rama Rao | F77: Medical Entomology and Zoology | G77: 0 | I77: South Asia | J77: Bangalore | K77: A1:india
A78: LM00142 | B78: A1 | C78: Municipal Corporation Building, Mumbai | D78: 1893 | E78: Frederick William Stevens | G78: 0 | I78: South Asia | J78: Bombay; Mumbai | K78: A1:india
A79: LM01928 | B79: A10 | C79: Estimating Informal-Economy Gross Value Added for Bengaluru, 2025–26 | D79: 2026 | E79: Atri Cidambi | F79: Oxford Journal of Student Scholarship | G79: 0 | H79: 10.65161/recbaccpsxgjkvrgm | I79: South Asia | J79: Bengaluru; India | K79: A10:india
A80: LM01929 | B80: A10 | C80: A Model on Urban Migration of Informal Sector Workers: with Reference to India | D80: 2026 | E80: S. N. Saha | F80: International Journal of Innovative Science and Research Technology (IJISRT) | G80: 0 | H80: 10.38124/ijisrt/26sep833 | I80: Multi-region | J80: Africa; India; Latin America | K80: A10:recent
A81: LM01941 | B81: A10 | C81: Informal Sector Employment and Legal Invisibilization of Migrant Labour | D81: 2026 | E81: Purbita Das | F81: Zenodo (CERN European Organization for Nuclear Research) | G81: 0 | H81: 10.5281/zenodo.20699564 | I81: South Asia | J81: India | K81: A10:recent
A82: LM01903 | B82: A10 | C82: Role of the Informal Sector in Employment Generation: A Comparative Study of Urban and Rural Areas | D82: 2025 | E82: Madhav Anand | F82: RESEARCH HUB International Multidisciplinary Research Journal | G82: 0 | H82: 10.53573/rhimrj.2025.v12n1.004 | I82: South Asia | J82: India | K82: A10:recent
A83: LM01937 | B83: A10 | C83: The Role of Labour Law in Protecting Informal Sector Workers in Urban India | D83: 2025 | E83: Sumit Saini | F83: SSRN Electronic Journal | G83: 0 | H83: 10.2139/ssrn.5513779 | I83: South Asia | J83: India | K83: A10:recent
A84: LM01938 | B84: A10 | C84: WOMEN IN URBAN INFORMAL ECONOMY: CASE STUDY OF DOMESTIC WORKERS AND STREET VENDORS IN GURUGRAM | D84: 2025 | E84: Samaya Chauhan; Dr. Faraz Ahmad | F84: Zenodo (CERN European Organization for Nuclear Research) | G84: 0 | H84: 10.5281/zenodo.17959273 | I84: South Asia | J84: Gurugram; India | K84: A10:india | L84: Y | M84: Y
A85: LM01939 | B85: A10 | C85: Determinants of Urban Migration Among Informal Sector Workers in India — Evidence from Delhi | D85: 2025 | E85: TANMAY RAGHU | F85: National University of Singapore | G85: 0 | I85: South Asia | J85: Delhi; India | K85: A10:india; A10:recent | L85: Y
A86: LM01867 | B86: A10 | C86: FEMALE DOMESTIC LABORERS IN THE URBAN INFORMAL ECONOMY: A CASE ANALYSIS OF DELHI | D86: 2024 | F86: International Research Journal of Modernization in Engineering Technology and Science | G86: 2 | H86: 10.56726/irjmets60741 | I86: South Asia | J86: Delhi; India | K86: A10:india; A10:recent | L86: Y
A87: LM01901 | B87: A10 | C87: Legal Recognition and Social Equality for Street Hawkers in Urban India: A Spatial Study of Delhi & Patna | D87: 2024 | E87: Mayank Raj - | F87: International Journal For Multidisciplinary Research | G87: 0 | H87: 10.36948/ijfmr.2024.v06i03.22586 | I87: South Asia | J87: Delhi; India; Patna | K87: A10:india | L87: Y
A88: LM01844 | B88: A10 | C88: Urban informal economy and vulnerabilities of domestic waste-pickers: A case of Chandigarh, India | D88: 2023 | E88: Kulwinder Singh; Naresh Singla; Manjit Sharma; Jatinder Singh | F88: Waste Management & Research The Journal for a Sustainable Circular Economy | G88: 22 | H88: 10.1177/0734242x231154141 | I88: South Asia | J88: Chandigarh; India | K88: A10:india; A10:recent
A89: LM01894 | B89: A10 | C89: The Reach of Fiscal Stimulus for Urban Women Informal Sector Workers in Bengaluru during COVID-19 | D89: 2023 | E89: R. Vijayamba | F89: Routledge eBooks | G89: 0 | H89: 10.4324/9781003451990-4 | I89: South Asia | J89: Bengaluru; India; Karnataka | K89: A10:recent
A90: LM01888 | B90: A10 | C90: Workers in the Urban Informal Sector | D90: 2022 | E90: Nidhi Tandon; Pratyusha Basu; Omkumar Krishnan; R.V. Bhavani | F90: Routledge eBooks | G90: 0 | H90: 10.4324/9781003264194-6 | I90: South Asia | J90: India | K90: A10:india; A10:recent
A91: LM01889 | B91: A10 | C91: Migrants and Their Livelihoods in the Urban Informal Sector | D91: 2022 | E91: S. S. Sripriya | F91: Routledge eBooks | G91: 0 | H91: 10.4324/9781003287667-18 | I91: South Asia | J91: India; Mumbai | K91: A10:india; A10:recent
A92: LM01890 | B92: A10 | C92: Revisiting schooling access and urban livelihoods | D92: 2022 | E92: Loritta Chan | F92: Geoforum | G92: 0 | H92: 10.1016/j.geoforum.2022.08.006 | I92: South Asia | J92: India | K92: A10:recent
A93: LM01892 | B93: A10 | C93: An investigation of socio-economic conditions of street hawkers: a case study of Hyderabad, Sindh, Pakistan | D93: 2022 | E93: Nazia Dharejo; Atif Hussain Dharejo; Noor un Nisa; Hakim Ali Mahesar | F93: Liberal Arts and Social Sciences International Journal (LASSIJ) | G93: 0 | H93: 10.47264/idea.lassij/6.1.15 | I93: South Asia | J93: Hyderabad; Pakistan | K93: A10:india; A10:recent
A94: LM01887 | B94: A10 | C94: Gender and Urban Informal Sector Employment: An Analysis from Southern Punjab, Pakistan | D94: 2021 | E94: Durdana Qaiser Gillani; Hassan Shakeel Shah; Hafiza Nadia Bashir | F94: Journal of Economic Impact | G94: 0 | H94: 10.52223/jei3032104 | I94: South Asia | J94: Pakistan; Punjab | K94: A10:india
A95: LM01830 | B95: A10 | C95: “We live and we do this work”: Women waste pickers’ experiences of wellbeing in Ahmedabad, India | D95: 2020 | E95: Josie Wittmer | F95: World Development | G95: 73 | H95: 10.1016/j.worlddev.2020.105253 | I95: South Asia | J95: Ahmedabad; India | K95: A10:india
A96: LM01860 | B96: A10 | C96: Women Waste Pickers’ Lives during the COVID-19 Lockdown in Ahmedabad, India | D96: 2020 | E96: Josie Wittmer; Sharada Srinivasan; Mubina Qureshi | F96: SSRN Electronic Journal | G96: 4 | H96: 10.2139/ssrn.3885161 | I96: South Asia | J96: Ahmedabad; India | K96: A10:india
A97: LM01864 | B97: A10 | C97: COVID-19 Crisis and the Informal Economy: Informal Workers in Ahmedabad, India | D97: 2020 | E97: Wiego; Sewa | F97: OpenDocs (Institute of Development Studies) | G97: 3 | I97: South Asia | J97: Ahmedabad; India | K97: A10:india
A98: LM01865 | B98: A10 | C98: COVID-19 Crisis and the Informal Economy: Informal Workers in Delhi, India | D98: 2020 | E98: Wiego | F98: OpenDocs (Institute of Development Studies) | G98: 3 | I98: South Asia | J98: Delhi; India | K98: A10:india | L98: Y
A99: LM01831 | B99: A10 | C99: Street vending in urban ‘informal’ markets: Reflections from case-studies of street vendors in Delhi (India) and Phnom Penh City (Cambodia) | D99: 2019 | E99: Richa Sekhani; Deepanshu Mohan; Sanjana Medipally | F99: Cities | G99: 70 | H99: 10.1016/j.cities.2019.01.010 | I99: Multi-region | J99: Cambodia; Delhi; India; Phnom Penh | K99: A10:india | L99: Y
A100: LM01856 | B100: A10 | C100: Fruit and Vegetable Street Vendors in Urban Informal Sector in Hyderabad, India | D100: 2019 | E100: A. Samarpitha | F100: International Journal of Current Microbiology and Applied Sciences | G100: 5 | H100: 10.20546/ijcmas.2019.811.113 | I100: South Asia | J100: Hyderabad; India; Telangana | K100: A10:india
...

Sheet Shortlist
A1: Records touching the researcher's current leads (stations, waiting, night-time mobility, fare integration/NCMC, rail-led urbanism, elevated infrastructure, Haryana secondary cities). Tagging only; it does not affect search or screening.
A2: ID | B2: Primary theme | C2: Title | D2: Year | E2: Authors | F2: Venue | G2: Cited-by count | H2: DOI | I2: Region | J2: Places studied | K2: Found in | L2: Shortlist tag
A3: LM00142 | B3: A1 | C3: Municipal Corporation Building, Mumbai | D3: 1893 | E3: Frederick William Stevens | G3: 0 | I3: South Asia | J3: Bombay; Mumbai | K3: A1:india | L3: railway station
A4: LM00208 | B4: A2 | C4: Transit’s Value-Added Effects: Light and Commuter Rail Services and Commercial Land Values | D4: 2002 | E4: Robert Cervero; Michael Duncan | F4: Transportation Research Record Journal of the Transportation Research Board | G4: 280 | H4: 10.3141/1805-02 | I4: Not place-specific | K4: S5:landmarks | L4: rail station; transit-oriented development
A5: LM00210 | B5: A2 | C5: Transforming Cities with Transit | D5: 2013 | E5: Robert Cervero; Hiroaki R. Suzuki; Kanako Iuchi | F5: World Bank, Washington, DC eBooks | G5: 257 | H5: 10.1596/978-0-8213-9745-9 | I5: Multi-region | J5: Ahmedabad; Bogota; Colombia; India | K5: S5:landmarks | L5: transit-oriented development
A6: LM00211 | B6: A2 | C6: Financing Transit-Oriented Development with Land Values: Adapting Land Value Capture in Developing Countries | D6: 2015 | E6: Hiroaki R. Suzuki; Jin Murakami; Yu‐Hung Hong; Beth Tamayose | F6: World Bank, Washington, DC eBooks | G6: 212 | H6: 10.1596/978-1-4648-0149-5 | I6: China & East Asia | J6: China; Hong Kong; Tokyo | K6: S5:landmarks | L6: transit-oriented development
A7: LM00212 | B7: A2 | C7: Green TODs: marrying transit-oriented development and green urbanism | D7: 2011 | E7: Robert Cervero; Cathleen Sullivan | F7: International Journal of Sustainable Development & World Ecology | G7: 191 | H7: 10.1080/13504509.2011.570801 | I7: Global North | J7: Australia; Germany; Sweden | K7: S5:landmarks | L7: transit-oriented development
A8: LM00214 | B8: A2 | C8: Intra-city access to inter-city transport nodes: The implications of high-speed-rail station locations for the urban development of Chinese cities | D8: 2016 | E8: Mi Diao; Yi Zhu; Jiren Zhu | F8: Urban Studies | G8: 177 | H8: 10.1177/0042098016646686 | I8: China & East Asia | J8: China; Guangzhou; Hangzhou | K8: S5:landmarks | L8: rail station; train stations
A9: LM00217 | B9: A2 | C9: Benefits of Proximity to Rail on Housing Markets: Experiences in Santa Clara County | D9: 2002 | E9: Robert Cervero; Michael Duncan | F9: Journal of Public Transportation | G9: 134 | H9: 10.5038/2375-0901.5.1.1 | I9: Not place-specific | K9: S5:landmarks | L9: rail station; transit-oriented development
A10: LM00221 | B10: A2 | C10: Forty years of modelling rapid transit’s land value uplift in North America: moving beyond the tip of the iceberg | D10: 2016 | E10: Christopher D. Higgins; Pavlos Kanaroglou | F10: Transport Reviews | G10: 121 | H10: 10.1080/01441647.2016.1174748 | I10: Global North | J10: North America | K10: S5:landmarks | L10: transit-oriented development
A11: LM00223 | B11: A2 | C11: The impacts of built environment characteristics of rail station areas on household travel behavior | D11: 2018 | E11: Keunhyun Park; Reid Ewing; Brenda Case Scheer; Guang Tian | F11: Cities | G11: 112 | H11: 10.1016/j.cities.2017.12.015 | I11: Not place-specific | K11: S5:landmarks | L11: rail station
A12: LM00224 | B12: A2 | C12: Alternative transit-oriented development evaluation in sustainable built environment planning | D12: 2016 | E12: Wann-Ming Wey; Heng Zhang; Yu-Jie Chang | F12: Habitat International | G12: 107 | H12: 10.1016/j.habitatint.2016.03.003 | I12: Not place-specific | K12: S5:landmarks | L12: transit-oriented development
A13: LM00225 | B13: A2 | C13: Do rail transit stations encourage neighbourhood retail activity? | D13: 2014 | E13: Jenny Schuetz | F13: Urban Studies | G13: 91 | H13: 10.1177/0042098014549128 | I13: Not place-specific | K13: S5:landmarks | L13: transit-oriented development
A14: LM00228 | B14: A2 | C14: Rapid transit, transit-oriented development, and the contextual sensitivity of land value uplift in Toronto | D14: 2017 | E14: Christopher D. Higgins; Pavlos Kanaroglou | F14: Urban Studies | G14: 77 | H14: 10.1177/0042098017712680 | I14: Global North | J14: Toronto | K14: S5:landmarks | L14: transit-oriented development
A15: LM00231 | B15: A2 | C15: What caused differential impacts on high-speed railway station area development? Evidence from global nighttime light data | D15: 2019 | E15: Taotao Deng; Chen Gan; Anthony D. Perl; Dandan Wang | F15: Cities | G15: 69 | H15: 10.1016/j.cities.2019.102568 | I15: Not place-specific | K15: S5:landmarks | L15: railway station
A16: LM00233 | B16: A2 | C16: Public Transport and Sustainable Urbanism: Global Lessons | D16: 2016 | E16: Perry Pei-Ju Yang; Seng How Lew | F16: Routledge eBooks | G16: 67 | H16: 10.4324/9781315550008-10 | I16: Global North | J16: Australia | K16: S5:landmarks | L16: transit-oriented development
A17: LM00234 | B17: A2 | C17: The urban regeneration of west-bay, business district of Doha (State of Qatar): A transit-oriented development enhancing livability | D17: 2018 | E17: Raffaello Furlan; Attilio Petruccioli; Mark David Major; Sara Zaina; Samar Zaina; Mahmoud Al Saeed; Dina Saleh | F17: Journal of Urban Management | G17: 67 | H17: 10.1016/j.jum.2018.10.001 | I17: Middle East | J17: Doha; Qatar | K17: S5:landmarks | L17: transit-oriented development
A18: LM00235 | B18: A2 | C18: Effects of transit-oriented development (TOD) on housing prices: A case study in Wuhan, China | D18: 2020 | E18: Jianyi Li; Hao Huang | F18: Research in Transportation Economics | G18: 66 | H18: 10.1016/j.retrec.2020.100813 | I18: China & East Asia | J18: China; Wuhan | K18: S5:landmarks | L18: transit-oriented development
A19: LM00236 | B19: A2 | C19: Institutional barriers to financing transit-oriented development in China: Analyzing informal land value capture strategies | D19: 2019 | E19: Jinshuo Wang; D. Ary A. Samsura; Erwin van der Krabben | F19: Transport Policy | G19: 63 | H19: 10.1016/j.tranpol.2019.07.010 | I19: China & East Asia | J19: China | K19: S5:landmarks | L19: transit-oriented development
A20: LM00237 | B20: A2 | C20: Measuring the built environment of green transit-oriented development: A factor-cluster analysis of rail station areas in Singapore | D20: 2021 | E20: Shaofei Niu; Ang Hu; Zhongwei Shen; Ying Li Huang; Yanchuan Mou | F20: Frontiers of Architectural Research | G20: 60 | H20: 10.1016/j.foar.2021.03.005 | I20: Southeast Asia | J20: Singapore | K20: S5:landmarks | L20: rail station; transit-oriented development
A21: LM00238 | B21: A2 | C21: Travel Behavior in TODs vs. Non-TODs: Using Cluster Analysis and Propensity Score Matching | D21: 2018 | E21: Keunhyun Park; Reid Ewing; Brenda Case Scheer; Shabnam Sifat Ara Khan | F21: Transportation Research Record Journal of the Transportation Research Board | G21: 59 | H21: 10.1177/0361198118774159 | I21: Global North | J21: United States | K21: S5:landmarks | L21: transit-oriented development
A22: LM00242 | B22: A2 | C22: The travel, equity and wellbeing impacts of transit-oriented development in Global South | D22: 2022 | E22: Fenglong Wang; Yuya Zheng; Wenjie Wu; Donggen Wang | F22: Transportation Research Part D Transport and Environment | G22: 48 | H22: 10.1016/j.trd.2022.103512 | I22: Not place-specific | K22: S5:recent | L22: transit-oriented development
A23: LM00253 | B23: A2 | C23: A framework to measure transit-oriented development around transit nodes: Case study of a mass rapid transit system in Dhaka, Bangladesh | D23: 2023 | E23: Md. Anwar Uddin; Md. Shamsul Hoque; Tahsin Tamanna; Saima Adiba; Shah Md Muniruzzaman; Mohammad Shahriyar Parvez | F23: PLoS ONE | G23: 30 | H23: 10.1371/journal.pone.0280275 | I23: South Asia | J23: Bangladesh; Dhaka | K23: S5:india | L23: transit-oriented development
A24: LM00254 | B24: A2 | C24: Transit-oriented development strategy in Taiwan: An application of land value capture | D24: 2022 | E24: Barbara T.H. Yen; Cheng‐Min Feng; Tsai-Chen Lee | F24: Asian Transport Studies | G24: 29 | H24: 10.1016/j.eastsj.2022.100094 | I24: China & East Asia | J24: Taipei; Taiwan | K24: S5:recent | L24: transit-oriented development
A25: LM00255 | B25: A2 | C25: Reconfiguring Vertical Urbanism: The Example of Tall Buildings and Transit-Oriented Development (TB-TOD) in Hong Kong | D25: 2022 | E25: Kheir M Al-Kodmany; Charlie Q. L. Xue; Cong Sun | F25: Buildings | G25: 27 | H25: 10.3390/buildings12020197 | I25: China & East Asia | J25: Hong Kong | K25: S5:recent | L25: transit-oriented development
A26: LM00259 | B26: A2 | C26: Smart urbanism, citizen-centric approaches and integrated environmental services in transit-oriented development in Jakarta, Indonesia | D26: 2023 | E26: I Wayan Koko Suryawan; Rachmat Mulyana; Iva Yenis Septiariva; Wisnu Prayogo; Sapta Suhardono; Mega Mutiara Sari; Nova Ulhasanah | F26: Research in Globalization | G26: 25 | H26: 10.1016/j.resglo.2023.100181 | I26: Southeast Asia | J26: Indonesia; Jakarta | K26: S5:recent | L26: transit-oriented development
A27: LM00266 | B27: A2 | C27: Shifting Discourse about Transit-Oriented Development in Mumbai, India | D27: 2014 | E27: Lubaina Rangwala; Rejeet Mathews; Sanjay Sridhar | F27: Transportation Research Record Journal of the Transportation Research Board | G27: 12 | H27: 10.3141/2451-07 | I27: South Asia | J27: India; Mumbai | K27: S5:india | L27: railway stations; transit-oriented development
A28: LM00268 | B28: A2 | C28: Examination on the Influence Area of Transit-Oriented Development: Considering Multimodal Accessibility in New Delhi, India | D28: 2019 | E28: Sangeetha Ann; Meilan Jiang; Ghasak I.M.A. Mothafer; Toshiyuki Yamamoto | F28: Sustainability | G28: 12 | H28: 10.3390/su11092621 | I28: South Asia | J28: Delhi; India; New Delhi | K28: S5:india | L28: metro stations; transit-oriented development
A29: LM00269 | B29: A2 | C29: Synergizing Land Value Capture and Transit-Oriented Development: A Study of Bengaluru Metro | D29: 2021 | E29: Jaya Dhindaw; Sree Kumar Kumaraswamy; Surya Prakash; Radha Chanchani; Amartya Deb | G29: 12 | H29: 10.46830/wripn.20.00082 | I29: South Asia | J29: Bangalore; Bengaluru; Karnataka | K29: S5:india | L29: metro rail; metro stations; transit-oriented development
A30: LM00279 | B30: A2 | C30: Rethinking urbanism in Doha : The Qatar National Museum transit-oriented development | D30: 2023 | E30: Eman Saleh Al Fadala; Raffaello Furlan; Reem Awwaad; Khalida Lifam Marthya; Tagwa A. A. Osman; Rashid Saad Al-Matwi | F30: Journal of urban regeneration and renewal | G30: 6 | H30: 10.69554/oqvj7569 | I30: Middle East | J30: Doha; Qatar | K30: S5:recent | L30: metro station; metro stations; transit-oriented development
A31: LM00280 | B31: A2 | C31: Sustainable Transit Oriented Development: Solving Congestion Problem at Delhi | D31: 2012 | E31: Anuj Jaiswal; Kanishka Raj Rathore; Devansh Jain | F31: SSRN Electronic Journal | G31: 6 | I31: South Asia | J31: Delhi; India | K31: S5:india | L31: transit-oriented development
A32: LM00281 | B32: A2 | C32: Transit-Oriented Development in Planning History | D32: 2023 | E32: Yudi Liu; Akito Murayama; Rikutaro Manabe; Ryoichi Nitanai | F32: Urban and Regional Planning Review | G32: 5 | H32: 10.14398/urpr.10.94 | I32: Multi-region | J32: Japan; North America | K32: S5:recent | L32: transit-oriented development
A33: LM00284 | B33: A2 | C33: Issues and Challenges for Transit-Oriented Development in the Scenario of a Developing Country: The Case of Kolkata Metropolitan Area, India | D33: 2020 | E33: Subrata Paul; Abhinanda Chatterjee; Souvanic Roy | F33: Springer geography | G33: 4 | H33: 10.1007/978-3-030-25879-5_4 | I33: South Asia | J33: India; Kolkata | K33: S5:india | L33: transit-oriented development
A34: LM00289 | B34: A2 | C34: Land Value Capture and Transit Oriented Development (TOD): A Comparative Review of Indian TOD Policies Measures | D34: 2022 | E34: Sahil Singh Kapoor; Tejwant Singh Brar | F34: International Journal of Management and Humanities | G34: 3 | H34: 10.35940/ijmh.g1448.038722 | I34: South Asia | J34: India | K34: S5:india; S5:recent | L34: transit-oriented development
A35: LM00299 | B35: A2 | C35: Smart Growth and Transit Oriented Development: Financing and Execution Challenges in India | D35: 2021 | E35: Alok Kumar Mishra; Shibani Mishra | F35: IntechOpen eBooks | G35: 2 | H35: 10.5772/intechopen.95034 | I35: South Asia | J35: India | K35: S5:india | L35: transit-oriented development
A36: LM00300 | B36: A2 | C36: FRAMEWORK FOR ESTABLISHING FEASIBLE TRANSIT ORIENTED DEVELOPMENT LOCATIONS: A CASE STUDY IN HYDERABAD, INDIA | D36: 2018 | F36: International Journal for Traffic and Transport Engineering | G36: 2 | H36: 10.7708/ijtte.2018.8(2).07 | I36: Multi-region | J36: Australia; Hyderabad; India; United Kingdom; United States | K36: S5:india | L36: transit-oriented development
A37: LM00304 | B37: A2 | C37: Emerging evidence on transit-oriented development in the Global South | D37: 2023 | E37: Fenglong Wang; Wenjie Wu; Donggen Wang | F37: Transportation Research Part D Transport and Environment | G37: 2 | H37: 10.1016/j.trd.2023.103898 | I37: Not place-specific | K37: S5:recent | L37: transit-oriented development
A38: LM00315 | B38: A2 | C38: Realizing India’s Potential for Transit-Oriented Development and Land Value Capture: A Qualitative and Quantitative Approach | D38: 2022 | G38: 1 | H38: 10.22617/spr220271-2 | I38: South Asia | J38: India | K38: S5:india; S5:recent | L38: metro rail; transit-oriented development
A39: LM00323 | B39: A2 | C39: Influence of the Mass Rapid Transit System on Plotted Residential Property Prices: A Case Study of Gurugram, India | D39: 2025 | E39: Sneh Fandian; Manoj Panwar | F39: Journal of Contemporary Urban Affairs | G39: 1 | H39: 10.25034/ijcua.2025.v9n2-4 | I39: South Asia | J39: Delhi; Gurugram; India | K39: S5:india | L39: metro station
A40: LM00324 | B40: A2 | C40: Transit-oriented development and land value capture in China: a public–private partnership perspective | D40: 2025 | E40: Xiongbin Lin; Kunyao Wei; Qiuling Lin; Ian R. MacLachlan | F40: Transportmetrica B Transport Dynamics | G40: 1 | H40: 10.1080/21680566.2025.2569408 | I40: China & East Asia | J40: China | K40: S5:recent | L40: transit-oriented development
A41: LM00335 | B41: A2 | C41: REVIEW OF DDA’s TRANSIT ORIENTED DEVELOPMENT GUIDELINES FOR DELHI | D41: 2022 | E41: Harikrishna Gopal Nambiar | G41: 0 | H41: 10.46529/darch.202229 | I41: Multi-region | J41: Delhi; India; New York | K41: S5:india | L41: metro rail; metro station; metro stations
A42: LM00337 | B42: A2 | C42: Financing transportation infrastructure through Land Value Capture | D42: 2022 | E42: OECD | F42: OECD regional development papers | G42: 0 | H42: 10.1787/8015065d-en | I42: Multi-region | J42: France; Japan; South Korea; United Kingdom | K42: S5:recent | L42: transit-oriented development
A43: LM00351 | B43: A2 | C43: LAND VALUE CAPTURE SEBAGAI INOVASI PEMBIAYAAN NONPEMERINTAH DI KOTA PEKALONGAN | D43: 2024 | E43: Wisnu Pradoto; Muhammad Safrul; Nurul Anam Ramli | F43: Jurnal Litbang Kota Pekalongan | G43: 0 | H43: 10.54911/litbang.v22i1.303 | I43: Not place-specific | K43: S5:recent | L43: transit-oriented development
A44: LM00352 | B44: A2 | C44: TRANSIT ORIENTED DEVELOPMENT POLICY OF INDIA AND THE BARRIERS IN ITS IMPLEMENTATION | D44: 2024 | E44: Shivam Gupta; Prachi Narang; Deepashree Choudhury | F44: ShodhKosh Journal of Visual and Performing Arts | G44: 0 | H44: 10.29121/shodhkosh.v5.iicomabe.2024.2167 | I44: South Asia | J44: India | K44: S5:india; S5:recent | L44: transit-oriented development
A45: LM00353 | B45: A2 | C45: THE POTENTIAL OF LAND VALUE CAPTURE FOR A TRANSIT-ORIENTED DEVELOPMENT INITIATIVE IN PEKALONGAN CITY CENTER | D45: 2024 | E45: Wisnu Pradoto; Mardwi Rahdriawan; Muhammad Safrul; Nurul Anam Ramli | F45: Jurnal Pengembangan Kota | G45: 0 | H45: 10.14710/jpk.12.1.23-34 | I45: Not place-specific | K45: S5:recent | L45: railway station; transit-oriented development
A46: LM00358 | B46: A2 | C46: The Impact of Metro Rail on Real Estate/Property Markets and Travel Behaviour: A Study of Mumbai Metro Corridor | D46: 2025 | E46: Ramakrishna Nallathiga; Rohan Bharambe; Khushi Balavi; Aishwarya Govekar; Tanvi Pawar | F46: Lecture notes in civil engineering | G46: 0 | H46: 10.1007/978-981-96-4898-6_21 | I46: South Asia | J46: Mumbai | K46: S5:india; S5:recent | L46: metro rail
A47: LM00359 | B47: A2 | C47: Financing Urban Mobility: Integrating Land Value Capture Mechanisms for Metro Projects in India | D47: 2025 | E47: Ayisha Reem | F47: International Journal For Multidisciplinary Research | G47: 0 | H47: 10.36948/ijfmr.2025.v07i02.41160 | I47: South Asia | J47: India | K47: S5:india; S5:recent | L47: metro rail; transit-oriented development
A48: LM00360 | B48: A2 | C48: Revenue Generation Using Land Value Capture Mechanism: A Case of Pune Metro Rail Project | D48: 2020 | E48: Smita K. Patil; Shruti Vaishampayan | F48: Journal of Real Estate Construction & Management | G48: 0 | H48: 10.1177/2977657020200101 | I48: South Asia | J48: Pune | K48: S5:india | L48: metro rail
A49: LM00361 | B49: A2 | C49: IMPACT OF METRO RAIL PROJECTS ON COMMERCIAL DEVELOPMENT IN URBAN INDIA: A REVIEW | D49: 2025 | E49: Pramod Kumar Jha | F49: International Scientific Journal of Engineering and Management | G49: 0 | H49: 10.55041/isjem04567 | I49: South Asia | J49: Delhi; Hyderabad; India; Indore; Kochi; Meerut | K49: S5:india; S5:recent | L49: metro rail; transit-oriented development
A50: LM00363 | B50: A2 | C50: Evaluation of Land Value Capture Measures Toward Transit-Oriented Development in India | D50: 2025 | F50: Asian Development Bank Institute eBooks | G50: 0 | H50: 10.56506/utri5659 | I50: South Asia | J50: India | K50: S5:india; S5:recent | L50: transit-oriented development
A51: LM00364 | B51: A2 | C51: Landscape of Transit-Oriented Development in India: A Case Study of the Hyderabad Metro | D51: 2025 | F51: Asian Development Bank Institute eBooks | G51: 0 | H51: 10.56506/donh9005 | I51: South Asia | J51: Hyderabad; India | K51: S5:india | L51: transit-oriented development
A52: LM00366 | B52: A2 | C52: Optimizing Transit-Oriented Development Strategies Integrating Land Value Capture in Chennai’s Metro Corridor | D52: 2025 | E52: Nandini S; Bala Eswari Macha; Debapratim Pandit | F52: Transportation research procedia | G52: 0 | H52: 10.1016/j.trpro.2025.12.116 | I52: South Asia | J52: Chennai; India | K52: S5:india; S5:recent | L52: transit-oriented development
A53: LM00374 | B53: A2 | C53: Developing a Contextual Transit-Oriented Development (TOD) Typology: A Case Study of Kolkata and Mumbai | D53: 2026 | E53: Amit Kumar Bala; Ajay Kumar | F53: Civil Engineering and Architecture | G53: 0 | H53: 10.13189/cea.2026.141340 | I53: South Asia | J53: India; Kolkata; Mumbai | K53: S5:india | L53: transit-oriented development
A54: LM00375 | B54: A2 | C54: CAPTURING THE UNEARNED CITY: AN EVIDENCE BASED FRAMEWORK FOR LAND VALUE CAPTURE AROUND METRO CORRIDORS IN INDIA | D54: 2026 | E54: Dr. Sarita Admune | F54: International Journal of Research In Commerce and Management Studies | G54: 0 | H54: 10.38193/ijrcms.2026.8359 | I54: South Asia | J54: India | K54: S5:india; S5:recent | L54: metro rail
A55: LM00376 | B55: A2 | C55: The Impact of Metro on Real Estate Property Markets: A Case Study of Hyderabad Metro Rail Project | D55: 2026 | E55: Sai Durga Prasad Chunchu; Pechetty Kesavan; Satyabrat Swain; Ramakrishna Nallathiga | G55: 0 | H55: 10.17492/jpi/nicmar/260536 | I55: South Asia | J55: Hyderabad | K55: S5:india; S5:recent | L55: metro rail
A56: LM00379 | B56: A2 | C56: Land Value Capture for Transportation Infrastructure Financing: A Systematic Literature Review of Transit-Oriented Development and Land-Value Creation | D56: 2026 | E56: Alifia Fauziyyah Adhima; Muhammad Yusuf; Gentiga Muhammad Zairin | F56: Prosperia Journal of Economic Development Accounting and Global Markets | G56: 0 | H56: 10.65310/ekxztg48 | I56: Not place-specific | K56: S5:recent | L56: transit-oriented development
A57: LM00380 | B57: A2 | C57: Measuring Transit-Oriented Development Readiness in a Declining Central Business District: A Methodological Framework for the Global South | D57: 2026 | E57: Nawshin Ahmed; Shahriar Iqbal Raj | F57: Journal of Contemporary Urban Affairs | G57: 0 | H57: 10.25034/ijcua.2026.v10n2-3 | I57: South Asia | J57: Dhaka | K57: S5:recent | L57: transit-oriented development
A58: LM00392 | B58: A2 | C58: Real Estate Prices in Mumbai::Does the Metro Rail Have an Impact? | D58: 2014 | E58: Gandhi, Sahil; Tandel, Vaidehi; id_orcid 0000-0001-6322-0068; Pethe, Abhay; Phatak, Vidyadhar; Rishbud, Sushrut | F58: Research Explorer (The University of Manchester) | G58: 0 | I58: South Asia | J58: Mumbai | K58: S5:india | L58: metro rail
A59: LM00396 | B59: A2 | C59: A Case for Data-driven Urbanism: Graph Machine Learning-Based Approaches for Transit-Oriented Development Decision Support | D59: 2026 | E59: Leo Lin Meng | F59: UNSWorks (University of New South Wales, Sydney, Australia) | G59: 0 | H59: 10.26190/unsworks/31985 | I59: Global North | J59: New York; United Kingdom | K59: S5:recent | L59: transit-oriented development
A60: LM00398 | B60: A2 | C60: Transforming the Asian Motorcycle City? Evaluating the Travel and Urban Development Effects of the Mass Rapid Transit in Taipei, Taiwan | D60: 2023 | E60: Bing-yu Chiu | F60: ScholarlyCommons (University of Pennsylvania) | G60: 0 | I60: China & East Asia | J60: Taipei; Taiwan | K60: S5:recent | L60: metro stations; transit-oriented development
A61: LM00403 | B61: A2 | C61: Impact of Metro Rail Projects on Urban Development | D61: 2026 | E61: P K Abhilash | F61: Zenodo (CERN European Organization for Nuclear Research) | G61: 0 | H61: 10.5281/zenodo.20660286 | I61: Not place-specific | K61: S5:recent | L61: metro rail
A62: LM00404 | B62: A2 | C62: Urban Development Influenced by Metro Rail Infrastructure | D62: 2026 | E62: P K Abhilash | F62: Zenodo (CERN European Organization for Nuclear Research) | G62: 0 | H62: 10.5281/zenodo.20659662 | I62: Not place-specific | K62: S5:recent | L62: metro rail
A63: LM00411 | B63: A2 | C63: Railway Urbanism: A Genealogy of Transit-Oriented Development and Sustainability in Greater Paris | D63: 2026 | E63: Mariana Reis Santos | F63: HAL (Le Centre pour la Communication Scientifique Directe) | G63: 0 | H63: 10.5281/zenodo.22231390 | I63: Global North | J63: Paris | K63: S5:recent | L63: rail station; transit-oriented development
A64: LM00412 | B64: A2 | C64: Why Transit-Oriented Development Underperforms Its Policy in India: A Structured Review of Delhi, Ahmedabad and Bengaluru Against the Financing Question | D64: 2026 | E64: Yash Arora | F64: Zenodo (CERN European Organization for Nuclear Research) | G64: 0 | H64: 10.5281/zenodo.22699581 | I64: South Asia | J64: Ahmedabad; Bengaluru; Delhi; India | K64: A2:india; S5:india | L64: transit-oriented development
A65: LM00977 | B65: A6 | C65: Construction of Heritage: Small and Medium Towns of Gurgaon District | D65: 2016 | E65: Parul G. Munjal | F65: Journal of Heritage Management | G65: 3 | H65: 10.1177/2455929616682079 | I65: South Asia | J65: Gurgaon; India | K65: A6:india | L65: Haryana secondary city
A66: LM01000 | B66: A6 | C66: Integrating Built Heritage in Development Planning: Small and medium towns of Gurgaon District | D66: 2020 | F66: International Journal of Innovative Technology and Exploring Engineering | G66: 1 | H66: 10.35940/ijitee.d1016.0394s20 | I66: South Asia | J66: Gurgaon; Haryana; India | K66: A6:india | L66: Haryana secondary city
A67: LM01049 | B67: A6 | C67: Challenges in a Small Town of Kalanaur Municipality, District: Rohtak (Haryana), India | D67: 2024 | E67: Satvir Singh | F67: INTERNATIONAL JOURNAL OF ADVANCE RESEARCH IN COMPUTER SCIENCE AND MANAGEMENT STUDIES | G67: 0 | H67: 10.61161/ijarcsms.v12i11.3 | I67: South Asia | J67: Haryana; India; Rohtak | K67: S7:india; S7:recent | L67: Haryana secondary city
A68: LM01077 | B68: A6 | C68: ANALYSIS OF AREAL GROWTH OF SONIPAT, A CLASS I CITY OF NATIONAL CAPITAL REGION-HARYANA | D68: 2024 | E68: Dr. Parul Rana | F68: Leadership Education Personality An Interdisciplinary Journal | G68: 0 | H68: 10.1366/vts73981 | I68: South Asia | J68: Delhi; Haryana; India; Sonipat | K68: S7:india; S7:recent | L68: Haryana secondary city
A69: LM01085 | B69: A6 | C69: Size,functions and infrastructural development in small and medium towns of Haryana (1961-1991) | D69: 1999 | E69: Kuldip Singh | F69: INFLIBNET | G69: 0 | I69: South Asia | J69: Haryana; India | K69: A6:india | L69: Haryana secondary city
A70: LM01086 | B70: A6 | C70: India’s census towns face a governance deficit | D70: 2012 | E70: edenis | F70: OpenEdition (OpenEdition) | G70: 0 | H70: 10.58079/ulmb | I70: South Asia | J70: Delhi; Gurgaon; India | K70: A6:india | L70: Haryana secondary city
A71: LM01106 | B71: A6 | C71: Child Sex Ratio in Small Towns of Haryana: A Geographical Analysis 2001-2011 | D71: 2022 | E71: Priyanka | F71: International journal of economic perspectives | G71: 0 | I71: South Asia | J71: Haryana; India | K71: S7:recent | L71: Haryana secondary city
A72: LM01107 | B72: A6 | C72: Occupational Structure of Small Towns in Haryana: 2011 | D72: 2023 | E72: Poonam and Monika | F72: International journal of economic perspectives | G72: 0 | I72: South Asia | J72: Haryana; India | K72: A6:india; S7:india; S7:recent | L72: Haryana secondary city
A73: LM01157 | B73: A7 | C73: A study on the traffic impact of the road corridors due to flyover construction at Surabaya intersection, Banda Aceh of Indonesia | D73: 2017 | E73: Sofyan Muhammad Saleh; Sugiarto Sugiarto; Almira Hilal; Dedek Ariansyah | F73: AIP conference proceedings | G73: 47 | H73: 10.1063/1.5011559 | I73: Southeast Asia | J73: Indonesia; Surabaya | K73: S6:landmarks | L73: flyover
A74: LM01164 | B74: A7 | C74: Sound emission comparisons between the box-section and U-section concrete viaducts for elevated railway | D74: 2012 | E74: Tianxing Wu; Jiahua Liu | F74: Noise Control Engineering Journal | G74: 38 | H74: 10.3397/1.3701023 | I74: Not place-specific | K74: S6:landmarks | L74: elevated railway; viaducts
A75: LM01171 | B75: A7 | C75: Engineering Formality: Flyover and Skywalk Construction in Mumbai | D75: 2018 | E75: Andrew Harris | F75: International Journal of Urban and Regional Research | G75: 27 | H75: 10.1111/1468-2427.12525 | I75: South Asia | J75: Mumbai | K75: S6:india | L75: flyover; flyovers
A76: LM01185 | B76: A7 | C76: Impact of Flyovers in Dhaka City of Bangladesh on the Affected People in the Adjacent Area | D76: 2012 | E76: Md. Abu Taleb; Shamsuzzaman Majumder | F76: International Journal of Engineering and Technology | G76: 10 | H76: 10.7763/ijet.2012.v4.327 | I76: South Asia | J76: Bangladesh; Dhaka | K76: S6:india | L76: flyover; flyovers
A77: LM01195 | B77: A7 | C77: Comprehensive analysis of the impact of elevated metro line infrastructure on the urban heat island effect in Chennai: A multi-model approach | D77: 2024 | E77: Prashanthini Rajagopal; Radhakrishnan Shanthi Priya | F77: Energy and Buildings | G77: 7 | H77: 10.1016/j.enbuild.2024.114541 | I77: South Asia | J77: Chennai | K77: S6:india | L77: elevated metro
A78: LM01198 | B78: A7 | C78: A Sustainable approach to reduce Embodied and Operational Cooling Energy for an Elevated Metro Rail Station of Ahmedabad, India, using Building Information Modelling (BIM) and Factor Comparison Method | D78: 2022 | E78: Hirakraj Bapat; Debasis Sarkar; Rajesh Gujar | F78: Journal of The Institution of Engineers (India) Series A | G78: 6 | H78: 10.1007/s40030-021-00594-1 | I78: South Asia | J78: Ahmedabad; India | K78: S6:india | L78: elevated metro; rail station
A79: LM01203 | B79: A7 | C79: Infrastructural Development and Vulnerabilities: A Sociological Study of Two Selected Flyovers in Dhaka City, Bangladesh | D79: 2019 | E79: Shamsul Arefin; Tamanna Rashid; Didarul Habib | F79: Open Journal of Social Sciences | G79: 4 | H79: 10.4236/jss.2019.77003 | I79: South Asia | J79: Bangladesh; Dhaka | K79: S6:india | L79: flyover; flyovers
A80: LM01205 | B80: A7 | C80: Inhabiting Flyover Geographies: Flows, Interstices, and Walking Bodies in Karachi | D80: 2024 | E80: Aseela Haque | F80: Urban Planning | G80: 4 | H80: 10.17645/up.7168 | I80: South Asia | J80: Karachi; Pakistan | K80: S6:india | L80: flyover; flyovers; under the flyover
A81: LM01209 | B81: A7 | C81: Sentiment Analysis on the Elevated Expressway in Bangladesh: A Machine Learning and Deep Learning Approach | D81: 2024 | E81: Samiha Maisha Jeba; Rajib Khan; Md Shoaib Ahmed; Tanjim Taharat Aurpa; Satya Ranjan Dash | G81: 4 | H81: 10.1109/peeiacon63629.2024.10800150 | I81: South Asia | J81: Bangladesh | K81: S6:india | L81: elevated expressway
A82: LM01219 | B82: A7 | C82: Urban development and livelihoods of the poor in Dhaka | D82: 2004 | E82: Nasrin Khandoker; Jonathan Rouse | F82: Loughborough University Institutional Repository (Loughborough University) | G82: 3 | I82: South Asia | J82: Bangladesh; Dhaka | K82: S6:india | L82: flyover
A83: LM01222 | B83: A7 | C83: 665 Statistical modelling for crossing behaviour of pedestrians on urban road: case study Delhi, India | D83: 2016 | E83: Mariya Khatoon; Geetam Tiwari; Niladri Chatterjee | F83: Traffic safety | G83: 1 | H83: 10.1136/injuryprev-2016-042156.665 | I83: South Asia | J83: Delhi; India | K83: S6:india | L83: flyover; flyovers
A84: LM01223 | B84: A7 | C84: UNDERGROUND AND ELEVATED METRO RAIL | D84: 2019 | E84: Awari Mahesh Babu | F84: EPRA International Journal of Multidisciplinary Research (IJMR) | G84: 1 | H84: 10.36713/epra3745 | I84: South Asia | J84: India | K84: S6:india | L84: elevated metro; metro rail
A85: LM01232 | B85: A7 | C85: Analysis of pedestrian behaviour and risk while crossing road at signalised intersection of Delhi, India: before and after construction of flyover | D85: 2010 | E85: Mariya Khatoon; M S Minhas; Geetam Tiwari; Niladri Chatterjee | F85: Injury Prevention | G85: 0 | H85: 10.1136/ip.2010.029215.824 | I85: South Asia | J85: Delhi; India | K85: S6:india | L85: flyover; flyovers
A86: LM01233 | B86: A7 | C86: A Case Study on Flyover in Urban Context | D86: 2022 | E86: Basant Twarit; Singh Neeraj Kumar; Singh Anand Kumar | F86: Lecture notes in civil engineering | G86: 0 | H86: 10.1007/978-981-16-6647-6_5 | I86: Not place-specific | K86: S6:recent | L86: flyover
